package o;

import android.annotation.SuppressLint;
import android.app.Activity;
import android.app.Dialog;
import android.content.Context;
import android.content.res.Resources;
import android.graphics.Point;
import android.os.Build.VERSION;
import android.util.DisplayMetrics;
import android.util.TypedValue;
import android.view.Display;
import android.view.LayoutInflater;
import android.view.View;
import android.view.View.OnClickListener;
import android.view.ViewGroup;
import android.view.Window;
import android.view.WindowManager;
import android.view.WindowManager.LayoutParams;
import android.widget.Button;
import android.widget.CheckBox;
import android.widget.ImageView;
import android.widget.TextView;

public final class Ln
  extends Lj
{
  static String ʻˋ = "com.slideme.sam.manager";
  private static char[] ʾॱ = { 97, 110, 100, 114, 111, 105, 46, 99, 116, 101, 112, 109, 80, 107, 103, 73, 102, 98, 104, 106, 108, 113, 115, 117, 118 };
  private static char ʿॱ = '\005';
  private static String ˈॱ = "";
  private static int ˊʻ;
  private static long ˊʼ = -2114059855416870274L;
  private static int ˊʽ;
  private static char[] ˋʼ = { 20166, -2903, 14889, 24999, -22737, -5465, 4135, 22410, -25305, -16203, 1599 };
  CheckBox ʹ;
  boolean ʻˊ = false;
  boolean ʻᐝ = false;
  View.OnClickListener ʼˊ = new Lp(this);
  View.OnClickListener ʼˋ = new Lt(this);
  View.OnClickListener ʼᐝ = new Lq(this);
  private TextView ʽˊ;
  private int ʽˋ;
  private ImageView ʽᐝ;
  private TextView ˉॱ;
  Button ꜞ;
  public Context ꞌ;
  ImageView ﹳ;
  Button ﾞ;
  public ˊ ﾟ;
  
  static
  {
    ˊʽ = 0;
    ˊʻ = 1;
  }
  
  public Ln() {}
  
  /* Error */
  private static String ˊˋ()
  {
    // Byte code:
    //   0: goto +73 -> 73
    //   3: astore 6
    //   5: aload 6
    //   7: athrow
    //   8: iconst_1
    //   9: istore_1
    //   10: goto +83 -> 93
    //   13: iconst_0
    //   14: istore_1
    //   15: goto +78 -> 93
    //   18: new 134	java/lang/String
    //   21: dup
    //   22: aload 7
    //   24: invokespecial 137	java/lang/String:<init>	([C)V
    //   27: areturn
    //   28: getstatic 91	o/Ln:ˋʼ	[C
    //   31: astore 6
    //   33: aload 6
    //   35: iload_0
    //   36: iconst_0
    //   37: iadd
    //   38: caload
    //   39: i2l
    //   40: lstore_2
    //   41: iload_0
    //   42: i2l
    //   43: lstore 4
    //   45: aload 7
    //   47: iload_0
    //   48: lload_2
    //   49: lload 4
    //   51: getstatic 78	o/Ln:ˊʼ	J
    //   54: lmul
    //   55: lxor
    //   56: ldc2_w 138
    //   59: lxor
    //   60: l2i
    //   61: i2c
    //   62: castore
    //   63: iload_0
    //   64: iconst_1
    //   65: iadd
    //   66: istore_0
    //   67: goto +52 -> 119
    //   70: goto +11 -> 81
    //   73: bipush 11
    //   75: newarray char
    //   77: astore 7
    //   79: iconst_0
    //   80: istore_0
    //   81: iload_0
    //   82: bipush 11
    //   84: if_icmpge +6 -> 90
    //   87: goto -79 -> 8
    //   90: goto -77 -> 13
    //   93: iload_1
    //   94: tableswitch	default:+22->116, 0:+-76->18, 1:+-66->28
    //   116: goto -108 -> 8
    //   119: getstatic 95	o/Ln:ˊʻ	I
    //   122: bipush 13
    //   124: iadd
    //   125: istore_1
    //   126: iload_1
    //   127: sipush 128
    //   130: irem
    //   131: putstatic 93	o/Ln:ˊʽ	I
    //   134: iload_1
    //   135: iconst_2
    //   136: irem
    //   137: ifeq +6 -> 143
    //   140: goto -70 -> 70
    //   143: goto -62 -> 81
    // Local variable table:
    //   start	length	slot	name	signature
    //   35	50	0	i	int
    //   9	128	1	j	int
    //   40	9	2	l1	long
    //   43	7	4	l2	long
    //   3	3	6	localException	Exception
    //   31	3	6	arrayOfChar1	char[]
    //   22	56	7	arrayOfChar2	char[]
    // Exception table:
    //   from	to	target	type
    //   28	33	3	java/lang/Exception
    //   45	63	3	java/lang/Exception
  }
  
  private static String ˋ(char[] paramArrayOfChar)
  {
    break label649;
    int i;
    int j = i;
    break label438;
    label8:
    j = 0;
    break label348;
    label13:
    char[] arrayOfChar2;
    char[] arrayOfChar1;
    int n;
    int m;
    int k;
    arrayOfChar2[i] = arrayOfChar1[(n * m + k)];
    int i2;
    int i1;
    arrayOfChar2[(i + 1)] = arrayOfChar1[(i2 * m + i1)];
    for (;;)
    {
      try
      {
        i = ˊʽ + 121;
        ˊʻ = i % 128;
        if (i % 2 != 0)
        {
          continue;
          j = 86;
          break label811;
          j = ˊʻ + 41;
          ˊʽ = j % 128;
          if (j % 2 != 0) {
            continue;
          }
          continue;
          j = 1;
          continue;
          j = ˊʻ;
          j += 39;
          ˊʽ = j % 128;
          if (j % 2 != 0) {
            continue;
          }
          continue;
          j = 6;
          break label811;
          arrayOfChar2[i] = ((char)(i1 - 119));
          arrayOfChar2[(i + 1)] = ((char)(k - 119));
          j = i;
          continue;
          arrayOfChar2[i] = arrayOfChar1[(n * m + (i1 + m - 1) % m)];
          arrayOfChar2[(i + 1)] = arrayOfChar1[(i2 * m + (k + m - 1) % m)];
          continue;
          if (n == i2) {
            break label8;
          }
          continue;
          j = i;
        }
        switch (k)
        {
        default: 
          continue;
          i = k;
          continue;
          j = ˊʽ + 101;
          ˊʻ = j % 128;
          if (j % 2 != 0)
          {
            continue;
            j = 31;
            continue;
            k = 73;
            j = i;
            continue;
            i = 0;
            continue;
            i1 = paramArrayOfChar[i];
            k = paramArrayOfChar[(i + 1)];
            if (i1 == k) {
              continue;
            }
            continue;
            j = ˊʽ + 89;
            ˊʻ = j % 128;
            if (j % 2 == 0) {
              continue;
            }
            continue;
            i = 0;
            continue;
            switch (j)
            {
            }
            break label13;
            return new String(arrayOfChar2);
            switch (j)
            {
            case 22: 
            default: 
              continue;
              switch (j)
              {
              default: 
                continue;
              }
              break;
            }
          }
          break;
        case 0: 
          i = j + 2;
          continue;
          j = 0;
          continue;
          k = 29;
          j = i;
          continue;
          k = 1;
          continue;
          arrayOfChar2[i] = arrayOfChar1[((n + m - 1) % m * m + i1)];
          arrayOfChar2[(i + 1)] = arrayOfChar1[((i2 + m - 1) % m * m + k)];
          j = i;
          continue;
          switch (i)
          {
          default: 
            continue;
            switch (j)
            {
            default: 
              continue;
              n = i1 / m;
              i1 %= m;
              i2 = k / m;
              k %= m;
              if (i1 == k) {
                continue;
              }
              continue;
              j = ˊʻ + 93;
              ˊʽ = j % 128;
              if (j % 2 != 0) {
                break label846;
              }
              j = i;
            }
            break;
          }
          try
          {
            j = ˊʻ + 45;
            ˊʽ = j % 128;
            if (j % 2 != 0) {
              break;
            }
            j = i;
          }
          catch (Exception paramArrayOfChar)
          {
            throw paramArrayOfChar;
          }
          arrayOfChar1 = ʾॱ;
          m = ʿॱ;
          arrayOfChar2 = new char[30];
          continue;
          j = 20;
          continue;
          j = ˊʻ + 69;
          ˊʽ = j % 128;
          if (j % 2 != 0) {
            break label843;
          }
          continue;
          k = 0;
          continue;
          arrayOfChar2[i] = ((char)(i1 - 119));
          arrayOfChar2[(i + 1)] = ((char)(k - 119));
          continue;
          i = 0;
          k = 0;
          continue;
          j = 22;
          break;
        case 1: 
          label348:
          label438:
          label649:
          i += 2;
          continue;
          j = 68;
          continue;
          i = j;
          switch (k)
          {
          }
          i = j;
          continue;
          if (i < 30) {
            continue;
          }
          break;
        }
        i = 1;
        continue;
        j = 1;
        continue;
        switch (j)
        {
        }
      }
      catch (Exception paramArrayOfChar)
      {
        throw paramArrayOfChar;
      }
      label811:
      continue;
      label843:
      continue;
      label846:
      j = i;
    }
  }
  
  /* Error */
  public final boolean ˋ(String paramString)
  {
    // Byte code:
    //   0: goto +367 -> 367
    //   3: iconst_1
    //   4: istore_2
    //   5: goto +339 -> 344
    //   8: aload_1
    //   9: ifnull +6 -> 15
    //   12: goto +326 -> 338
    //   15: goto +380 -> 395
    //   18: iconst_0
    //   19: istore_2
    //   20: goto +271 -> 291
    //   23: aload_3
    //   24: invokeinterface 148 1 0
    //   29: ifeq +6 -> 35
    //   32: goto -29 -> 3
    //   35: goto +384 -> 419
    //   38: goto -15 -> 23
    //   41: iconst_1
    //   42: istore_2
    //   43: goto +248 -> 291
    //   46: aload_3
    //   47: invokeinterface 154 1 0
    //   52: astore_3
    //   53: goto -30 -> 23
    //   56: iconst_1
    //   57: istore_2
    //   58: goto +260 -> 318
    //   61: astore_1
    //   62: aload_1
    //   63: athrow
    //   64: iconst_0
    //   65: istore_2
    //   66: goto +252 -> 318
    //   69: aload_3
    //   70: invokeinterface 158 1 0
    //   75: astore 4
    //   77: aload_1
    //   78: bipush 30
    //   80: newarray char
    //   82: dup
    //   83: iconst_0
    //   84: ldc -97
    //   86: castore
    //   87: dup
    //   88: iconst_1
    //   89: ldc -96
    //   91: castore
    //   92: dup
    //   93: iconst_2
    //   94: ldc -95
    //   96: castore
    //   97: dup
    //   98: iconst_3
    //   99: ldc -94
    //   101: castore
    //   102: dup
    //   103: iconst_4
    //   104: ldc -93
    //   106: castore
    //   107: dup
    //   108: iconst_5
    //   109: ldc -92
    //   111: castore
    //   112: dup
    //   113: bipush 6
    //   115: ldc -97
    //   117: castore
    //   118: dup
    //   119: bipush 7
    //   121: ldc -91
    //   123: castore
    //   124: dup
    //   125: bipush 8
    //   127: ldc -92
    //   129: castore
    //   130: dup
    //   131: bipush 9
    //   133: ldc -96
    //   135: castore
    //   136: dup
    //   137: bipush 10
    //   139: ldc -95
    //   141: castore
    //   142: dup
    //   143: bipush 11
    //   145: ldc -90
    //   147: castore
    //   148: dup
    //   149: bipush 12
    //   151: ldc -90
    //   153: castore
    //   154: dup
    //   155: bipush 13
    //   157: ldc -94
    //   159: castore
    //   160: dup
    //   161: bipush 14
    //   163: ldc -92
    //   165: castore
    //   166: dup
    //   167: bipush 15
    //   169: ldc -91
    //   171: castore
    //   172: dup
    //   173: bipush 16
    //   175: ldc -89
    //   177: castore
    //   178: dup
    //   179: bipush 17
    //   181: ldc -88
    //   183: castore
    //   184: dup
    //   185: bipush 18
    //   187: ldc -91
    //   189: castore
    //   190: dup
    //   191: bipush 19
    //   193: ldc -89
    //   195: castore
    //   196: dup
    //   197: bipush 20
    //   199: ldc -96
    //   201: castore
    //   202: dup
    //   203: bipush 21
    //   205: ldc -87
    //   207: castore
    //   208: dup
    //   209: bipush 22
    //   211: ldc -86
    //   213: castore
    //   214: dup
    //   215: bipush 23
    //   217: ldc -95
    //   219: castore
    //   220: dup
    //   221: bipush 24
    //   223: ldc -85
    //   225: castore
    //   226: dup
    //   227: bipush 25
    //   229: ldc -84
    //   231: castore
    //   232: dup
    //   233: bipush 26
    //   235: ldc -83
    //   237: castore
    //   238: dup
    //   239: bipush 27
    //   241: ldc -93
    //   243: castore
    //   244: dup
    //   245: bipush 28
    //   247: ldc -85
    //   249: castore
    //   250: dup
    //   251: bipush 29
    //   253: ldc -97
    //   255: castore
    //   256: invokestatic 175	o/Ln:ˋ	([C)Ljava/lang/String;
    //   259: invokevirtual 178	java/lang/String:intern	()Ljava/lang/String;
    //   262: invokestatic 184	java/lang/Class:forName	(Ljava/lang/String;)Ljava/lang/Class;
    //   265: invokestatic 186	o/Ln:ˊˋ	()Ljava/lang/String;
    //   268: invokevirtual 178	java/lang/String:intern	()Ljava/lang/String;
    //   271: invokevirtual 190	java/lang/Class:getField	(Ljava/lang/String;)Ljava/lang/reflect/Field;
    //   274: aload 4
    //   276: invokevirtual 196	java/lang/reflect/Field:get	(Ljava/lang/Object;)Ljava/lang/Object;
    //   279: invokevirtual 200	java/lang/String:equals	(Ljava/lang/Object;)Z
    //   282: ifeq +6 -> 288
    //   285: goto -221 -> 64
    //   288: goto -232 -> 56
    //   291: iload_2
    //   292: tableswitch	default:+20->312, 1:+101->393
    //   312: goto -304 -> 8
    //   315: astore_1
    //   316: aload_1
    //   317: athrow
    //   318: iload_2
    //   319: tableswitch	default:+17->336, 1:+-281->38
    //   336: iconst_1
    //   337: ireturn
    //   338: bipush 52
    //   340: istore_2
    //   341: goto +57 -> 398
    //   344: iload_2
    //   345: tableswitch	default:+19->364, 0:+48->393
    //   364: goto -295 -> 69
    //   367: aload_0
    //   368: getfield 202	o/Ln:ꞌ	Landroid/content/Context;
    //   371: astore_3
    //   372: aload_3
    //   373: invokevirtual 208	android/content/Context:getPackageManager	()Landroid/content/pm/PackageManager;
    //   376: astore_3
    //   377: aload_3
    //   378: iconst_0
    //   379: invokevirtual 214	android/content/pm/PackageManager:getInstalledPackages	(I)Ljava/util/List;
    //   382: astore_3
    //   383: aload_3
    //   384: ifnull +6 -> 390
    //   387: goto -369 -> 18
    //   390: goto -349 -> 41
    //   393: iconst_0
    //   394: ireturn
    //   395: bipush 8
    //   397: istore_2
    //   398: iload_2
    //   399: lookupswitch	default:+17->416, 8:+-6->393
    //   416: goto -370 -> 46
    //   419: iconst_0
    //   420: istore_2
    //   421: goto -77 -> 344
    // Local variable table:
    //   start	length	slot	name	signature
    //   0	424	0	this	Ln
    //   0	424	1	paramString	String
    //   4	417	2	i	int
    //   23	361	3	localObject1	Object
    //   75	200	4	localObject2	Object
    // Exception table:
    //   from	to	target	type
    //   367	372	61	java/lang/Exception
    //   377	383	61	java/lang/Exception
    //   372	377	315	java/lang/Exception
  }
  
  @SuppressLint({"NewApi"})
  public final void ˎ()
  {
    super.ˎ();
    if (this.ᐝ != null)
    {
      int i = this.ᐝ.getWindow().getAttributes().width;
      Object localObject;
      if (Build.VERSION.SDK_INT >= 13)
      {
        if (this.ˊᐝ == null) {
          localObject = null;
        } else {
          localObject = (ᵕ)this.ˊᐝ.ˎ;
        }
        localObject = ((ᵕ)localObject).getWindowManager().getDefaultDisplay();
        Point localPoint = new Point();
        ((Display)localObject).getSize(localPoint);
        i = localPoint.x;
      }
      else
      {
        if (this.ˊᐝ == null) {
          localObject = null;
        } else {
          localObject = (ᵕ)this.ˊᐝ.ˎ;
        }
        i = ((ᵕ)localObject).getWindowManager().getDefaultDisplay().getWidth();
      }
      int j = (int)TypedValue.applyDimension(1, 24.0F, ʼ().getDisplayMetrics());
      int k = this.ᐝ.getWindow().getAttributes().height;
      this.ᐝ.getWindow().setLayout(i - j, k);
    }
  }
  
  public final View ˏ(LayoutInflater paramLayoutInflater, ViewGroup paramViewGroup)
  {
    paramLayoutInflater = paramLayoutInflater.inflate(Ls.iF.quick_share_video_frangment, paramViewGroup, false);
    try
    {
      this.ʽˋ = ((Activity)this.ꞌ).getRequestedOrientation();
      ʼ().getConfiguration();
      ((Activity)this.ꞌ).getWindowManager().getDefaultDisplay().getRotation();
      paramViewGroup = new DisplayMetrics();
      ((Activity)this.ꞌ).getWindowManager().getDefaultDisplay().getMetrics(paramViewGroup);
      int i = paramViewGroup.widthPixels;
      i = paramViewGroup.heightPixels;
      if (this.ᐝ != null)
      {
        this.ᐝ.getWindow().requestFeature(1);
        this.ᐝ.getWindow().setBackgroundDrawableResource(17170445);
      }
      this.ʽᐝ = ((ImageView)paramLayoutInflater.findViewById(Ls.ˋ.imggoogleplay));
      this.ꜞ = ((Button)paramLayoutInflater.findViewById(Ls.ˋ.buttonNoTahnks));
      this.ꜞ.setOnClickListener(this.ʼˊ);
      this.ﾞ = ((Button)paramLayoutInflater.findViewById(Ls.ˋ.buttonRemind));
      this.ﾞ.setOnClickListener(this.ʼᐝ);
      this.ﹳ = ((ImageView)paramLayoutInflater.findViewById(Ls.ˋ.imggoogleplay));
      this.ﹳ.setOnClickListener(this.ʼˋ);
      this.ʹ = ((CheckBox)paramLayoutInflater.findViewById(Ls.ˋ.checkBoxHide));
      this.ʹ.setOnCheckedChangeListener(new Lo(this));
      this.ʽˊ = ((TextView)paramLayoutInflater.findViewById(Ls.ˋ.textAppTitle));
      this.ʽˊ.setText(String.format(ʼ().getString(Ls.if.app_love), new Object[] { String.format(ʼ().getString(Ls.if.app_name), new Object[0]) }));
      this.ˉॱ = ((TextView)paramLayoutInflater.findViewById(Ls.ˋ.textRateApp));
      this.ˉॱ.setText(String.format(ʼ().getString(Ls.if.app_love_desc), new Object[] { String.format(ʼ().getString(Ls.if.app_name), new Object[0]) }));
      if ((!this.ʻˊ) && (!this.ʻᐝ))
      {
        if (ˋ(ʻˋ))
        {
          this.ˉॱ.setText(String.format(ʼ().getString(Ls.if.app_love_desc_slideme), new Object[] { String.format(ʼ().getString(Ls.if.app_name), new Object[0]) }));
          this.ʽᐝ.setImageResource(Ls.If.slideme_logo);
          return paramLayoutInflater;
        }
      }
      else
      {
        if (this.ʻˊ)
        {
          this.ˉॱ.setText(String.format(ʼ().getString(Ls.if.app_love_desc_samsung), new Object[] { String.format(ʼ().getString(Ls.if.app_name), new Object[0]) }));
          this.ʽᐝ.setImageResource(Ls.If.samsung_logo);
        }
        if (this.ʻᐝ)
        {
          this.ˉॱ.setText(String.format(ʼ().getString(Ls.if.app_love_desc_amazon), new Object[] { String.format(ʼ().getString(Ls.if.app_name), new Object[0]) }));
          this.ʽᐝ.setImageResource(Ls.If.amazon_apps_store);
        }
      }
      return paramLayoutInflater;
    }
    catch (Exception paramViewGroup)
    {
      for (;;) {}
    }
    ˎ(true);
    return paramLayoutInflater;
  }
  
  public final void ͺ()
  {
    super.ͺ();
    if ((!this.ʻˊ) && (!this.ʻᐝ)) {
      ˋ(ʻˋ);
    }
  }
  
  public final void ᐝ()
  {
    ((Activity)this.ꞌ).setRequestedOrientation(this.ʽˋ);
    super.ᐝ();
  }
  
  public static abstract interface ˊ
  {
    public abstract void ˊ(boolean paramBoolean);
  }
}
