package com.soomla.traceback.i;

import android.app.Activity;
import android.app.Application;
import android.content.BroadcastReceiver;
import android.content.Context;
import android.content.Intent;
import android.content.IntentFilter;
import android.content.pm.ActivityInfo;
import android.content.pm.ApplicationInfo;
import android.content.pm.PackageInfo;
import android.content.pm.PackageManager;
import android.content.pm.PackageManager.NameNotFoundException;
import android.content.pm.ResolveInfo;
import android.os.Handler;
import android.os.Looper;
import android.text.TextUtils;
import com.soomla.traceback.AdAction;
import com.soomla.traceback.AdListener;
import com.soomla.traceback.Advertising.AdType;
import com.soomla.traceback.InstallBroadcastReceiver;
import com.soomla.traceback.LocalEvent;
import com.soomla.traceback.LocalEventConsts;
import com.soomla.traceback.LogUtils;
import com.soomla.traceback.SafeRunnable;
import com.soomla.traceback.SoomlaTraceback;
import com.soomla.traceback.TracebackListener;
import com.soomla.traceback.UidReadyCallback;
import com.soomla.traceback.UserAdActionsCallback;
import java.util.ArrayList;
import java.util.Iterator;
import java.util.List;
import java.util.Map;
import java.util.PriorityQueue;
import java.util.Queue;
import java.util.concurrent.BlockingQueue;
import java.util.concurrent.PriorityBlockingQueue;
import org.json.JSONArray;
import org.json.JSONException;
import org.json.JSONObject;

public class q
  extends SoomlaTraceback
{
  private static long ˊˊ = 0L;
  private static char[] ˋˋ;
  private static int ˌ = 1;
  private static int ˎˏ;
  private static final String[] ˏ = { ˋ('\000', 8, 3516).intern(), ˋ('Ը', 8, 3524).intern(), ˋ(38773, 5, 3532).intern(), ˋ('⼸', 7, 3537).intern(), ˋ('\000', 9, 3544).intern(), ˋ('䓽', 8, 3553).intern(), ˋ(36220, 7, 3561).intern(), ˋ('焥', 8, 3568).intern(), ˋ('\000', 10, 3576).intern(), ˋ(59431, 10, 3586).intern(), ˋ(41878, 12, 3596).intern(), ˋ('ネ', 11, 3608).intern(), ˋ('枬', 10, 3619).intern(), ˋ('\000', 6, 3629).intern(), ˋ('㓂', 5, 3635).intern(), ˋ('恛', 4, 3640).intern(), ˋ('\000', 6, 3644).intern(), ˋ(';', 6, 3650).intern(), ˋ(55472, 6, 3656).intern(), ˋ(42830, 11, 3662).intern(), ˋ('\000', 10, 3673).intern(), ˋ('窄', 4, 3683).intern(), ˋ('\000', 8, 3687).intern(), ˋ('\000', 10, 3695).intern(), ˋ('\000', 6, 3705).intern(), ˋ('\000', 9, 3711).intern(), ˋ('\000', 15, 3720).intern(), ˋ(54101, 7, 3735).intern(), ˋ('Ԃ', 6, 3742).intern(), ˋ('\000', 10, 3748).intern(), ˋ(60404, 8, 3758).intern(), ˋ(48596, 5, 3766).intern(), ˋ(33722, 7, 3771).intern(), ˋ('\000', 5, 3778).intern(), ˋ('\000', 5, 3783).intern(), ˋ('\000', 9, 3788).intern(), ˋ('\000', 9, 3797).intern(), ˋ('稳', 6, 3806).intern(), ˋ('\000', 7, 3812).intern(), ˋ('\000', 6, 3819).intern(), ˋ('\000', 8, 3825).intern(), ˋ('\000', 10, 3833).intern(), ˋ('\000', 6, 3843).intern(), ˋ('䍲', 8, 3849).intern(), ˋ('䀬', 8, 3857).intern(), ˋ('\000', 6, 3865).intern(), ˋ('\000', 5, 3871).intern(), ˋ('स', 6, 3876).intern(), ˋ('\000', 8, 3882).intern(), ˋ('競', 7, 3890).intern() };
  private static q ॱ;
  private n ʻ;
  private int ʻॱ;
  private boolean ʼ = false;
  private Thread ʼॱ;
  private boolean ʽ = false;
  private BlockingQueue<au> ʽॱ = new PriorityBlockingQueue();
  private aq ʾ = null;
  private Thread ʿ;
  private ao ˈ = null;
  private ap ˉ = null;
  private m ˊ;
  private as ˊˋ;
  private Thread.UncaughtExceptionHandler ˊॱ;
  private boolean ˊᐝ = false;
  private boolean ˋ = false;
  private ax ˋˊ = new ax();
  private List<TracebackListener> ˋॱ = new ArrayList();
  private boolean ˎ = false;
  private a ˏॱ;
  private List<au> ͺ;
  private i ॱˊ = null;
  private Context ॱˋ;
  private Handler ॱˎ;
  private boolean ॱᐝ;
  private boolean ᐝ = false;
  private int ᐝॱ;
  
  static {}
  
  private q() {}
  
  private void ʻॱ()
  {
    try
    {
      if (this.ʼॱ == null)
      {
        this.ʼॱ = new Thread(new SafeRunnable()
        {
          private static long ˎ = -666705358457137681L;
          
          private static String ˏ(String paramAnonymousString)
          {
            paramAnonymousString = (char[])paramAnonymousString.toCharArray();
            paramAnonymousString = c.ॱ(ˎ, paramAnonymousString);
            int i = 4;
            for (;;)
            {
              int j;
              if (i < paramAnonymousString.length) {
                j = 1;
              } else {
                j = 0;
              }
              if (j == 0) {
                break;
              }
              paramAnonymousString[i] = ((char)(int)(paramAnonymousString[i] ^ paramAnonymousString[(i % 4)] ^ (i - 4) * ˎ));
              i += 1;
            }
            return new String(paramAnonymousString, 4, paramAnonymousString.length - 4);
          }
          
          public final void safeRun()
          {
            LogUtils.LogDebug(ˏ("줉汌?՗쥚秬䓗黹Ʀ墸鲊昃ꥊ7칟焎䰽").intern(), ˏ("ᙝ᥏鑛젂ᘘೖ뿠覡䆕瓄អ凤륋?佸㤪ᄌОꝩ腷䣅淢Ự棞ꂕ헴皢』ᡔ㵪깩顒瀝敼ص澚ꯎ쫴綀㟁Ψ㊪핆齋筱驧്杂팿숩擇캗૾⯞?隱").intern());
            for (;;)
            {
              if (Thread.currentThread().isInterrupted()) {
                break label95;
              }
              try
              {
                q.ॱ(q.this, (au)q.ˏ(q.this).take());
              }
              catch (InterruptedException localInterruptedException)
              {
                for (;;) {}
              }
            }
            LogUtils.LogError(ˏ("줉汌?՗쥚秬䓗黹Ʀ墸鲊昃ꥊ7칟焎䰽").intern(), ˏ("赾僌뀨⣮贻䕕鮓楍?㵇㏑너≨闘欋?訯䶝茚憛폦②㪃蠲㮶鱷動탶荥璻訇碵Ⲻ≘轭ル荳姢휦领筦翓폹⥳螢䠄议䂮⹦釀戔瘚閭?ၢ黀䅙늉䡥⛕꥔椑").intern());
            synchronized (q.this)
            {
              q.ʼ(q.this);
              return;
            }
            label95:
          }
        });
        this.ʼॱ.start();
      }
      return;
    }
    finally
    {
      localObject = finally;
      throw localObject;
    }
  }
  
  private i ʼॱ()
  {
    try
    {
      if (this.ॱˊ == null) {
        this.ॱˊ = new i();
      }
      i localI = this.ॱˊ;
      return localI;
    }
    finally {}
  }
  
  private long ʽ(String paramString)
  {
    try
    {
      long l = this.ॱˋ.getPackageManager().getPackageInfo(paramString, 0).lastUpdateTime;
      return l;
    }
    catch (Throwable paramString)
    {
      for (;;) {}
    }
    return 0L;
  }
  
  private List<ApplicationInfo> ʽॱ()
  {
    try
    {
      List localList = this.ॱˋ.getPackageManager().getInstalledApplications(0);
      return localList;
    }
    catch (Exception localException)
    {
      String str = ˋ('\000', 16, 0).intern();
      StringBuilder localStringBuilder = new StringBuilder();
      localStringBuilder.append(ˋ('廊', 34, 2960).intern());
      localStringBuilder.append(localException.getLocalizedMessage());
      LogUtils.LogError(str, localStringBuilder.toString());
    }
    return new ArrayList();
  }
  
  private static void ʾ()
  {
    LogUtils.LogDebug(ˋ('\000', 16, 0).intern(), ˋ('\000', 30, 3146).intern());
    IntentFilter localIntentFilter = new IntentFilter();
    localIntentFilter.addAction(ˋ('଎', 36, 3176).intern());
    ˎ().ॱˋ.registerReceiver(new at(), localIntentFilter);
  }
  
  private void ʿ()
  {
    try
    {
      notify();
      return;
    }
    finally
    {
      localObject = finally;
      throw localObject;
    }
  }
  
  private boolean ˈ()
  {
    for (;;)
    {
      try
      {
        Object localObject2 = new JSONArray();
        Object localObject1 = this.ͺ.iterator();
        Object localObject3;
        if (!((Iterator)localObject1).hasNext())
        {
          i = 1;
          if (i != 0)
          {
            localObject3 = y.ˏ(ˋ(new JSONObject(), true), false, false);
            ((JSONObject)localObject3).put(ˋ('ᤗ', 6, 3019).intern(), localObject2);
            g localG = g.ॱ();
            if (!this.ᐝ) {
              localObject1 = this.ˊ.ʻ();
            } else {
              localObject1 = this.ˊ.ʼ();
            }
            localObject1 = aw.ˎ((JSONObject)localObject3, localG.ˏ((String)localObject1));
            if (localObject1 != null) {
              break label505;
            }
            i = 52;
            break label508;
            i = ((av)localObject1).ॱ().ˎ();
            if (i < 200) {
              i = 0;
            } else {
              i = 1;
            }
            if (i == 1)
            {
              i = ˎˏ + 5;
              ˌ = i % 128;
              if (i % 2 != 0) {
                i = 59;
              } else {
                i = 74;
              }
              if (i != 74 ? ((av)localObject1).ॱ().ˎ() <= 299 : ((av)localObject1).ॱ().ˎ() <= 299) {}
            }
            else
            {
              if (((av)localObject1).ॱ().ˎ() == 403) {
                break label516;
              }
              i = 0;
              if (i != 1)
              {
                localObject2 = ˋ('\000', 16, 0).intern();
                localObject3 = new StringBuilder();
                ((StringBuilder)localObject3).append(ˋ('ᥬ', 51, 3063).intern());
                ((StringBuilder)localObject3).append(((av)localObject1).ॱ().ˎ());
                ((StringBuilder)localObject3).append(ˋ('僂', 1, 3114).intern());
                ((StringBuilder)localObject3).append(((av)localObject1).ॱ().ˋ());
                LogUtils.LogDebug((String)localObject2, ((StringBuilder)localObject3).toString());
                return false;
              }
              i = ˎˏ + 109;
              ˌ = i % 128;
              ˎ(true);
              return true;
            }
            localObject1 = ˋ('\000', 16, 0).intern();
            localObject3 = new StringBuilder();
            ((StringBuilder)localObject3).append(ˋ('\000', 38, 3025).intern());
            ((StringBuilder)localObject3).append(localObject2);
            LogUtils.LogDebug((String)localObject1, ((StringBuilder)localObject3).toString());
            return true;
          }
          ((JSONArray)localObject2).put(((au)((Iterator)localObject1).next()).ˏ());
          continue;
        }
        i = 0;
      }
      catch (Exception localException)
      {
        localObject2 = ˋ('\000', 16, 0).intern();
        localObject3 = new StringBuilder();
        ((StringBuilder)localObject3).append(ˋ('\000', 31, 3115).intern());
        ((StringBuilder)localObject3).append(localException.toString());
        LogUtils.LogError((String)localObject2, ((StringBuilder)localObject3).toString());
        return false;
      }
      continue;
      label505:
      int i = 27;
      label508:
      if (i != 27)
      {
        return false;
        label516:
        i = 1;
      }
    }
  }
  
  private void ˉ()
  {
    LogUtils.LogDebug(ˋ('\000', 16, 0).intern(), ˋ('\000', 25, 2994).intern());
    PriorityQueue localPriorityQueue = this.ˈ.ˋ(this.ˊ.ˊ());
    if (localPriorityQueue != null) {
      try
      {
        if ((!localPriorityQueue.isEmpty()) && (this.ͺ == null))
        {
          this.ͺ = new ArrayList();
          for (;;)
          {
            au localAu = (au)localPriorityQueue.poll();
            if (localAu == null) {
              break;
            }
            this.ͺ.add(localAu);
          }
          try
          {
            if (this.ͺ.isEmpty())
            {
              this.ͺ = null;
              return;
            }
            new Thread(new SafeRunnable()
            {
              public final void safeRun()
              {
                boolean bool = q.ॱˎ(q.this);
                if (bool)
                {
                  ??? = q.ʼॱ(q.this).iterator();
                  while (((Iterator)???).hasNext())
                  {
                    au localAu = (au)((Iterator)???).next();
                    q.ᐝॱ(q.this).ˊ(localAu);
                  }
                }
                synchronized (q.this)
                {
                  q.ॱᐝ(q.this);
                  if (bool) {
                    q.ʻॱ(q.this);
                  }
                  return;
                }
              }
            }).start();
            return;
          }
          finally {}
        }
      }
      finally
      {
        break label161;
      }
    }
    return;
    label161:
    throw localObject2;
  }
  
  private static JSONObject ˊ(String paramString1, Map<String, String> paramMap, String paramString2)
  {
    JSONObject localJSONObject = new JSONObject();
    try
    {
      localJSONObject.put(ˋ('\000', 3, 2257).intern(), paramString1);
      localJSONObject.put(ˋ('\000', 3, 2260).intern(), new JSONObject(paramMap));
      localJSONObject.put(ˋ('\000', 4, 2263).intern(), paramString2);
      return localJSONObject;
    }
    catch (JSONException paramString1)
    {
      LogUtils.LogError(ˋ('\000', 16, 0).intern(), ˋ('\000', 30, 2267).intern(), paramString1);
    }
    return localJSONObject;
  }
  
  private static JSONObject ˊ(List<String> paramList)
  {
    JSONObject localJSONObject = new JSONObject();
    if (paramList != null) {
      i = 10;
    } else {
      i = 21;
    }
    if (i != 10) {
      return localJSONObject;
    }
    int i = ˌ + 23;
    ˎˏ = i % 128;
    if (paramList.size() == 0) {
      i = 49;
    } else {
      i = 5;
    }
    if (i != 49)
    {
      Object localObject = new JSONArray();
      paramList = paramList.iterator();
      for (;;)
      {
        if (paramList.hasNext()) {
          i = 31;
        } else {
          i = 30;
        }
        if (i == 30) {
          break;
        }
        ((JSONArray)localObject).put((String)paramList.next());
      }
      try
      {
        localJSONObject.put(ˋ('\000', 4, 2791).intern(), localObject);
        return localJSONObject;
      }
      catch (JSONException paramList)
      {
        localObject = ˋ('\000', 16, 0).intern();
        StringBuilder localStringBuilder = new StringBuilder();
        localStringBuilder.append(ˋ('\000', 19, 2795).intern());
        localStringBuilder.append(paramList.getLocalizedMessage());
        LogUtils.ExtLogError((String)localObject, localStringBuilder.toString());
        return localJSONObject;
      }
    }
    return localJSONObject;
  }
  
  private static boolean ˊ(TracebackListener paramTracebackListener)
  {
    int i;
    if (y.ˎ(ˋ(55176, 5, 2522).intern(), paramTracebackListener.getMinAgentVersion()) >= 0) {
      i = 1;
    } else {
      i = 70;
    }
    return i == 1;
  }
  
  private static void ˊˊ()
  {
    ˊˊ = 6143996979664462529L;
    ˋˋ = new char[] { 83, 8846, 17869, 26638, -29880, -21116, -12122, -3309, 5754, 14504, 23529, 32302, -24210, -15444, -6419, 2340, -15443, -7856, -31213, -21552, 18582, 28250, 4908, 12491, -10857, -1196, -26607, -16937, 25235, 80, 9499, -13679, -4199, -29362, -19937, 22413, 29835, 6727, 16154, -9012, -32377, -22717, 17437, 27013, 3729, 11339, -12011, -2347, -25670, -18064, 24107, 1011, 8436, 2554, 11015, 19524, 24967, -32063, -23539, -9861, -1380, 8128, 12547, 21062, 30592, -22332, -13817, -4276, 198, 9678, 18201, 30792, -25126, -16685, -12263, -2743, 5787, 19395, 27984, -29094, -23652, -15140, -6656, 7006, 15511, 20965, 29473, -27535, -13905, -5399, 3180, 8482, 17134, 26607, -26321, -17885, -8276, -3872, 4641, 14179, 26854, -29203, -20681, -16325, -6743, 1781, 14377, 23915, 32442, -27650, -19161, -10627, 3068, -29154, -21285, -13385, -6566, 1286, 9178, 24216, 32073, -26611, -18732, -10866, -2287, -10777, -19804, -24712, 31778, 23217, 10145, 1147, -7895, -12311, -21334, -30346, 22070, 13566, 4602, -385, -9429, -17934, -31064, 101, 8883, 17910, 26658, -29853, 101, 8883, 17903, 26672, -29853, -13059, -4565, -30343, -23372, 18424, 24888, -2072, -10946, -19844, -24646, 31970, 10325, 2723, 28128, 16444, -23706, -31243, -1801, -9421, 15996, 4272, 29684, 22076, -30404, -5192, -12564, 8493, 1135, 26291, 22946, -17362, -24735, -3658, -11019, 14118, 27247, 19628, 116, 8881, 17885, 26662, -29834, -21065, -12055, -3275, 13523, 5680, 29052, 23796, -16416, -26251, -7041, -14407, 8945, 3117, 28531, 19130, -27152, -2252, -11676, 15802, 6304, 31340, 17698, -24432, -31765, -4822, -14229, 11179, 30441, 20509, -19592, -24918, -1553, -9432, 9836, 430, 27859, 19994, -22254, -2940, -10283, 12550, 7190, 32644, 23248, -23540, -30898, -7521, -12845, 12042, 2640, 21969, -29381, -20538, -14203, -6842, 1536, 8396, 23994, 32349, -25855, -19006, -10617, -3263, 11269, 20166, 27533, -31737, -24303, -15414, -806, 6490, 14864, 21711, 29083, -28066, -12524, -5688, 2770, 10074, 16410, 25308, -24702, -18338, -10967, -2075, 4259, 19825, 28201, -30487, -23072, 83, 8878, 17901, 26670, -29848, -21084, -12078, -3275, 5737, 14506, 23535, 32297, -24211, -15442, -6427, 2415, 11385, 20159, 29179, -27609, -18563, -9804, -774, 7998, 16994, 25776, -30732, -21956, -13006, -4109, 4784, -273, -9160, -17560, -26955, 30197, 21299, 11897, 3550, -5999, -14768, -23278, -32585, 24539, 15701, 6232, -2152, -11556, -20407, -28851, 27268, 18828, 9985, 583, -7783, -17211, -26047, 31061, 21642, 13264, 4365, -5114, -13421, -22787, -31702, 25454, 16022, 7667, -1223, -10629, -18974, -28444, 28195, 19815, 10422, 1973, -6796, -16329, -24585, 31437, 22591, 14191, 4773, -3592, -12482, -21970, -30280, 25833, 16949, 8554, -797, -9232, -18144, -27531, 29619, 20149, 11734, 2846, -6562, -14911, -24375, 32268, 23882, 14485, 6033, -2811, -12198, -20584, -29991, 26710, 18261, 8845, 393, -8434, -17854, -26209, 29902, 21007, 12637, 3204, -5180, -14074, -23550, -31803, 24196, 97, 8879, 17894, 26673, -29845, -21076, -12062, -3223, 5735, 14522, 23460, 32266, -24193, -15436, -6432, 2348, 11332, 20144, 29153, -27592, 72, 8854, 17863, 26677, -29855, -21077, -12046, -3276, -21682, -30308, -4404, -15610, 8283, 1728, -9694, -1825, -24676, -19873, 20761, 30677, 2723, 10564, -13288, -7461, -32354, -23464, 31516, 6623, 15508, -11490, -2542, -27436, -21630, 20048, 27921, 973, 9865, -15039, -26551, -16690, 23940, 28760, 5965, 13785, -14179, -4286, -32149, -24400, 11066, 2508, 28303, 17235, -24567, -31078, -1136, -10154, 15646, 5058, 28828, 21845, -30177, -5925, -12917, 8793, 1793, 26057, 23245, -16513, -25596, -3387, -10364, 13380, 26886, 20358, -21327, -32426, -6654, -15167, 14724, 7746, 29502, 20989, -18762, 67, 8864, 17900, 26724, -29840, -21019, -12043, -3294, 5756, 14569, 23551, 32312, -24215, -15425, -6482, 2342, 11380, 20209, 29119, -27533, -18617, -9798, -775, 7994, 17012, 25784, -30770, -21975, -12931, -4162, 4859, 13629, 22593, 31362, -25143, -16317, -7341, 1412, 10453, 19271, 28251, -28543, -19489, -10721, -1720, 7042, 16089, 24833, -31714, 5277, 13930, 20787, 31911, -24659, -18060, -15311, -6153, 748, 11364, 20256, 27366, -19012, -10400, -3541, 7655, 14525, 23151, 25907, -32585, -23677, -12930, -6083, 3070, 22192, 28796, -27894, -16659, -9799, -1158, 1599, 8697, 19589, 28230, -30451, -11129, -2174, 4420, 15364, 24524, 31390, -31672, -22706, -15668, -4727, 3909, 10758, 30146, -28518, -19886, -8874, -1904, 7043, 9556, 16390, 25574, -29041, -22440, -13556, 5878, 12700, 21278, 116, 8881, 17885, 26672, -29855, -21066, -12043, -3304, 5741, 14503, 23534, -14436, -6806, -32215, -20491, 19631, 27196, 5932, 13563, -11867, -156, -25542, -17924, 26290, 1076, 8482, -12571, -5204, -30342, -18942, 21486, 28909, -2551, -11041, -19556, -25024, 32026, 23464, 9962, 1406, -8137, -12576, -21068, -30681, 22281, 13765, 4322, -150, -9681, -18243, -30800, 25194, 16692, 12277, 2804, -5829, -19452, -27911, 29107, 23670, 15139, 6644, -6926, -15490, -20979, -29498, 27531, 13839, 5403, -3108, -8552, -17074, -26556, 26321, 17801, 8199, 3856, -4672, -14191, -26800, 29276, 20700, 16350, 6729, -1767, -14379, -23917, -32417, 27732, 19163, 10649, -2983, -11427, -20001, -25465, 31583, 18016, 9581, 1019, -4420, -12947, -22469, 30378, 21890, 12352, 8037, -526, -10072, -22752, -32238, 24813, 20396, 10865, 2353, -10241, -19829, -28310, 31800, 23289, 14782, 1142, -7372, -15883, -21316, -29890, 97, 8879, 17915, 26679, -29844, -21076, -12056, -3296, 5670, 14512, 23525, 32318, -24286, -15430, -6417, 2337, 11364, 69, 8851, 17872, 26636, -29866, -21020, -12122, -3298, 5735, 14524, 23469, 32313, -24215, -15379, -6405, 2364, 11385, 20159, 29173, -27533, -18592, -9795, -781, 8055, 17020, 25788, -30724, -21958, -12951, -4175, 4842, 13695, 22613, 31378, -25145, -16367, -7420, 1452, 10466, 19271, 26671, 19168, 11731, 46, -7328, -14939, -18188, -25821, 32297, 20645, 13290, 5665, -13976, -21524, -28932, 24891, 17507, 9909, 6579, -986, -8326, -19980, -27417, 30519, 10858, 3243, -4165, -15813, -23235, -30807, 31473, 23863, 12368, 4757, -2618, -22462, -29872, 28055, 16578, 8980, 1545, -1887, -9233, -16822, -28341, 29571, 22237, 2382, -5036, -12655, -24112, -31718, 26389, 22913, 15556, 7955, -3509, -11048, -18481, 27157, 19741, 12207, 720, -6895, -10196, -17556, -25182, 28886, 21303, 13925, -5980, -13341, -20949, -32407, 25512, 18145, 14691, 91, 8864, 17839, 26681, -29883, -21016, -12068, -3209, 5669, 14576, 23463, 32276, -24285, -15472, -6492, -29321, -20575, -14110, -6850, 1636, 8406, 23956, 32256, -25783, -19042, -10550, -3239, 11383, 20155, 27548, 32, 8866, 17901, 26669, -29840, -21084, -12049, -3287, 5755, 14569, 23523, 32295, -24224, -15448, -6423, 2350, 11388, 20209, 29169, -27589, -18571, -9817, -777, 7988, 17004, 25788, -30744, -21976, -13006, -4099, 4814, 13619, 22597, 31360, -25135, -16378, -7420, 1416, 10439, 19212, 28237, -28471, -19495, -10722, -1698, 7048, 16014, 24859, -31649, -22831, -13886, -5102, 3911, 12678, 21654, 30486, -26088, -17268, -8247, 542, 9550, 18397, 27383, -29381, -20384, -11422, -2643, 6381, 15152, 24164, -32593, -23575, -14815, -5785, 2989, 11947, 20771, 29795, -26974, -17930, -9104, -142, 8634, 17650, 26406, -30106, -21258, -12303, -3542, 5494, 14263, 23227, 32007, -24452, -15629, -6683, 2081, 11020, 19896, 28819, -27831, -18916, -10037, -1032, 7751, 16756, 25546, -31009, -22269, -13299, -4419, 4544, 13343, 22364, 31134, -25390, -16608, -7609, 1175, 10196, 18973, 27995, -28773, -19752, -10985, -2029, 89, 8878, 17911, 26673, -29916, -21098, -12055, -3288, 5733, 14501, 23531, 32363, -24199, -15426, -6421, 2365, 11312, 20120, 29142, -27533, -18563, -9818, -852, 8055, 84, 8878, 17826, 26677, -29843, -21088, -12047, -3225, 5700, 14496, 23548, 32302, -24276, -15480, -6408, 2346, 11390, 20133, 29106, -27617, -18565, -9806, -795, 8055, 17023, 25782, -30790, -21969, -12941, -4099, 4854, 13611, 22612, 31377, -25192, -16308, -7413, 1425, 10452, 19206, 28235, -28532, -19512, -10742, -1713, 7046, 16000, 24860, -31649, -22882, -13857, -5027, 3928, 12692, 21654, 30554, -26106, -17191, -8221, 532, 9545, 18319, 27294, -29410, -20432, -11407, -2590, 6318, 15226, 24101, -32619, -23582, -14788, -5763, 2979, 12005, 20779, 29822, -26898, -18014, -9106, -207, 8599, 17661, 26400, -30096, -21340, -12361, -3551, 5494, 14255, 23273, 32124, -24472, -15699, -6662, 2066, 11009, 19883, 28903, 105, 8879, 17910, 26733, -29833, -21088, -12043, -3276, 5697, 14509, 67, 8864, 17900, 26724, -29840, -21019, -12043, -3294, 5756, 14569, 23550, 32302, -24193, -15431, -6482, 2338, 11391, 20149, 29175, -27533, -18631, -9739, -827, 7992, 17015, 25780, -30730, -21958, -12984, -4177, 4863, 13628, 22597, 31363, -25149, -16384, -7345, 1477, 10449, 19206, 28251, -28471, -19495, -10749, -1703, 7065, 16074, 24832, -31673, -22881, -13924, 20930, 29499, 5246, 14776, -9557, -967, -32404, -23876, 18343, 26930, 2656, 12215, -3849, -28062, -18580, 22703, 32251, 7995, 8253, -14914, -6402, -30660, -21130, 20138, 5106, 13686, -10628, -1094, -25350, -16858, 17272, 25777, 2499, 11015, -13225, -28283, -19771, 21517, 30984, -9356, -1606, -24845, -19676, 20606, 30393, 3063, 10364, -12940, -7246, -32533, -23237, 31351, 6316, 15797, -11717, -2202, -27216, -21778, 20265, 27759, 750, 10177, -15357, -26279, -16488, 23754, 28956, 5712, 13463, -13880, -4606, -31884, -24134, 18160, 6963, 14453, 102, 8877, 17891, 26660, -29910, -21085, -12049, -3275, 5755, 14525, 23513, 32302, -24215, -15453, 102, 8864, 17902, 26672, -29855, 102, 8872, 17910, 108, 8884, 17910, -5862, -13362, 112, 8884, 17899, 26663, 69, 8883, 17904, 26668, -29834, -21019, -12057, -3293, 5740, 14496, 23524, 32300, -24276, -15445, -6425, 2365, 11363, 20133, 29106, -27590, -18566, -9818, -798, 7990, 17012, 25781, -30795, -21961, -12931, -4178, 4842, 13695, 22613, 31377, -25146, -16382, -7344, 1408, 10374, 19219, 28225, -28540, -19505, -10677, -1704, 7042, 16014, 24837, -31677, -22882, -13860, 67, 8864, 17900, 26724, -29840, -21019, -12057, -3293, 5740, 14569, 23550, 32298, -24213, -15426, -6482, 2402, 11312, 20098, 29181, -27588, -18567, -9799, -777, 7939, 17002, 25784, -30727, -21954, -12930, -4164, 4861, 13620, 22528, 31382, -25149, -16368, -7420, 1430, 10446, 19218, 28252, -28531, -19515, -10724, -1726, 7107, 97, 8869, 17894, 26647, -29851, -21086, -12043, -3225, 5755, 14497, 23525, 32318, -24224, -15447, -6482, 2349, 11381, 20209, 29159, -27616, -18575, -9807, -842, 7990, 17022, 25773, -30721, -21975, -12996, -4172, 4848, 13622, 22612, 31368, -25149, -16369, -7347, 1439, 10447, 19209, 28239, -28471, -19463, -10748, -1725, 7040, 16066, 24846, -31644, -22909, -13869, -5104, 3921, 12695, 21719, 30484, -26029, -7406, -15900, -22873, -29829, 26657, 20146, 13232, 4212, -2757, -9225, -18253, -25221, 17019, 8430, 1464, -5505, -12441, 6907, 14388, 24323, 29431, -28234, -18589, -13709, -5647, 3260, 8818, 16689, 25841, -17491, -9928, -967, 5119, 14053, 21608, 27432, -28952, -21082, -15515, -6607, 1442, 22713, 32356, -25298, -20256, -10263, -2755, 2171, 12202, 17046, 24668, -30954, -9532, -1662, 7966, 97, 8869, 17894, 26652, -29840, -21084, -12063, -3276, 22320, 30150, 4741, 16217, -9213, -1392, -30830, -23466, 16665, 28629, 3217, 10585, -2471, -27444, -20070, 24157, 31510, 6532, 21483, 28936, 5700, 15308, -10024, -435, -31908, -24438, 17869, 27406, 2132, 11654, -3452, -28655, -19129, 23168, 32715, 7513, 8727, -14373, -6929, -30190, -20655, 19602, 4572, 14096, -11162, -1663, -24875, -17386, 16723, 26261, 3049, 10538, -12703, -27669, -20229, 22060, 31613, 6383, 15859, -15575, -8073, -31305, -21792, 18474, 28017, 12969, -10314, -1224, -9746, -16731, -27802, 28728, 22250, 11160, 2156, -4827, -15376, -24352, -31374, 23086, 14568, 7601, -3479, -10434, -19013, -30022, 28540, 19582, 8938, 1967, -7048, -18122, -24653, 31921, 20855, 13858, 5362, -5722, -12747, -23805, -32315, 26241, 15197, 6151, -306, -11392, -20412, -27368, 27594, 18574, 11590, 582, -7948, -14965, -26038, 32535, 24023, 12953, 5997, -3060, -13602, -20577, -29608, 24848, 18386, 9363, -1702, 8653, 795, 25680, 18835, -21811, -29665, -3738, -11636, 14294, 6417, 31302, -6799, -14457, -24380, -29416, 28226, 18641, 13760, 5654, -3247, -8814, -16696, -25834, 17494, 9886, 922, -5105, -14011, -21630, -27435, 28999, 20312, 28091, 2807, 10111, -15253, -7426, -24594, -17351, 22887, 30706, 5360, 12596, -4553, -29510, -22020, 17959, 25471, 431, 16103, -9427, -1923, -26898, -19552, 20588, 3408, 11181, -14098, -6867, -32149, -24409, 24017, 31286, 5978, 13721, -11556, -28902, -21410, 19101, 26582, 1116, 8516, -8301, -830, -26288, -18876, 21662, 29120, 11776, -13489, -5755, -31010, -23802, 16385, 67, 8864, 17900, 26724, -29840, -21019, -12063, -3294, 5756, 14569, 23551, 32312, -24215, -15425, -6482, 2350, 11380, 20209, 29171, -27600, -18592, -9796, -775, 7993, 17003, 25849, -30793, -21893, -12977, -4174, 4849, 13618, 22604, 31360, -25098, -16367, -7355, 1414, 10435, 19205, 28233, -28534, -19519, -10677, -1701, 7052, 16093, 24911, -31677, -22887, -13881, -5113, 3920, 12698, 21697, 30489, -26090, 103, 8868, 17910, 26646, -29833, -21088, -12044, -3322, 5740, 14472, 23529, 32319, -24219, -15454, -6432, 2364, 11312, 20130, 29178, -27588, -18591, -9799, -782, 8055, 17018, 25788, -30790, -21970, -12945, -4168, 4858, 13695, 22593, 31367, -25130, -16378, -7338, 1477, 10447, 19209, 28225, -28515, -19517, -10742, -1728, 7044, 16084, 24838, -31650, -22890, -13934, -5088, 3931, 12698, 21723, 30491, -26023, -17235, -8248, 538, 9567, 18328, 27356, -29410, -20445, -11414, 65, 8877, 17904, 26662, -29851, -21087, -12033, -3225, 5742, 14508, 23550, 32296, -24220, -15452, -6432, 2344, 11312, 20152, 29180, -27616, -18563, -9806, -770, 7971, 17003, 105, 8879, 17905, 26666, -29853, -21075, -12046, -3276, 5670, 14501, 23531, 32312, -24200, -15432, -6402, 2347, 11377, 20133, 29175, 105, 8879, 17905, 26666, -29853, -21075, -12046, -3276, 5670, 14506, 23531, 32296, -24220, -15448, 69, 8883, 17904, 26668, -29834, -21019, -12063, -3294, 5756, 14525, 23523, 32293, -24213, -15379, -6405, 2364, 11381, 20131, 29106, -27598, -18576, -9739, -777, 7988, 17004, 25776, -30731, -21963, -12945, -4099, 4856, 13613, 22607, 31372, -25214, -16384, -7355, 1414, 10446, 19202, -26026, -18293, -8248, -3571, 4425, 14273, 19095, 26966, -29601, -23911, -15929, -7140, 15189, 22939, 31940, -27902, -18944, -11108, -5181, 3586, 11591, 17349, 26308, -31480, -10231, -380, 7627, 12301, 22349, 30097, -30508, -20718, 69, 8883, 17904, 26668, -29834, -21019, -12063, -3294, 5756, 14525, 23523, 32293, -24213, -15379, -6405, 2364, 11381, 20131, 29106, -27598, -18576, -9739, -777, 7988, 17004, 25776, -30731, -21963, -12945, 105, 8879, 17910, 26662, -29834, -21077, -12057, -3285, 5672, 14508, 23544, 32313, -24221, -15425, 67, 8864, 17900, 26724, -29840, -21019, -12055, -3279, 5741, 14523, 23544, 32290, -24216, -15448, -6482, 2348, 11391, 20132, 29180, -27609, -18586, -9812, -842, 7988, 17015, 25789, -30721, -21893, -13007, -4099, 4813, 13616, 22607, 31372, -25138, -16382, -7312, 1431, 10439, 19204, 28237, -28533, -19509, -10744, -1721, 7117, 16089, 24846, -31677, -22831, -13887, -5093, 3905, 12673, 21714, 30488, -26033, -17257, -8300, 13976, 5243, 29495, 24255, -16981, -25794, -6610, -14855, 8381, 3702, 28017, 18681, -26695, -2757, -12236, 16356, 6843, 30762, 18233, -23811, -32323, -4243, -13787, 10733, 29872, 21095, -20127, -25371, -1103, -9885, 9259, 1008, 28379, 19479, -21671, -2325, -10864, 13137, 7696, 32208, 22674, -22938, -31485, -7983, -12396, 11603, 2071, 22485, -19832, -28607, -183, -9505, 14734, 1885, 25165, 16863, -21365, -30121, -5867, 13508, 5000, 29009, 23563, -17526, 105, 8885, 17895, 26670, 112, 8883, 17899, 26656, -29855, 99, 8884, 17904, 26673, -32601, -23954, -15044, -5934, 2985, 11620, 20517, 29689, -26966, -18334, -9424, -288, 8614, 69, 8883, 17904, 26668, -29834, -21019, -12059, -3275, 5741, 14504, 23550, 32290, -24222, -15446, -6482, 2310, 11345, 20097, 29106, -27591, -18585, -9798, -776, 17349, 24838, 1618, 11150, -14129, -4593, -27823, 19715, 28616, 2182, 9537, -14769, -7999, -25193, -16810, 23327, 30207, 5770, 13120, -5091, -29050, 97, 8885, 17910, 26673, -29861, -21065, -12059, -3279, 5740, 116, 8882, 17906, 116, 8882, 17894, 116, 8882, 17899, 26663, 69, 8883, 17904, 26668, -29834, -21019, -12043, -3294, 5756, 14525, 23523, 32293, -24213, -15379, -6417, 2363, 11364, 20131, 29179, -27599, -18591, -9823, -769, 7992, 17014, 25849, -30722, -21958, -12952, -4164, 46, 8872, 17900, 26679, -29855, -21086, -12044, -3290, 5756, 14496, 23525, 32293, -24193, -15389, 46, 8853, 17904, 26658, -29849, -21088, -12060, -3290, 5739, 14498, 73, 8879, 17899, 26679, -29843, -21084, -12054, -3282, 5746, 14496, 23524, 32300, -24276, -15452, -6432, 2363, 11381, 20150, 29152, -27598, -18592, -9796, -775, 7993, 16952, -6066, -13694, -21029, -32760, 25420, 17795, 14537, 6921, 89, 8878, 17911, 26673, -29916, -21098, -12087, -3320, 5701, 14469, 23499, 32363, 32, 8866, 17901, 26669, -29846, -21088, -12059, -3277, 5735, 14523, 23466, 32313, -24215, -15428, -6405, 2342, 11362, 20148, 29153, -27533, -18571, -9739, -776, 7986, 17007, 25788, -30744, -21893, -12950, -4168, 4844, 13612, 22601, 31374, -25140, -16317, -7349, 1411, 10374, 19219, 28224, -28532, -19574, -10742, -1717, 7048, 16064, 24859, -31714, -22831, -13854, -5089, 3921, 12692, 21701, 30482, -26088, -17268, -8246, 543, 9565, 18313, 27355, -29345, -20428, -11415, -2649, 6307, 15141, 24162, -32605, -23575, -14788, -5849, 32, 8866, 17901, 26669, -29846, -21088, -12059, -3277, 5735, 14523, 23466, 32317, -24215, -15425, -6403, 2342, 11391, 20159, 29106, 3048, 10619, 20015, 25594, -32583, -22940, -9412, -1814, 7603, 13089, 20502, 30193, -21851, -14234, -4829, 741, 10169, 17786, 31281, -24645, -17219, -11654, -2245, 5361, 18852, 28465, -29660, -24074, -14682, -7066, 6463, 16120, 21382, 28937, 32, 8864, 17900, 26663, -29916, -21084, -12060, -3288, 5758, 14508, 23466, 32355, -24209, -15432, -6404, 2365, 11381, 20159, 29158, -27533, -18571, -9806, -781, 7993, 17004, 25849, -30733, -21976, -12996, -10310, -2713, -28099, -16411, 23742, 24741, 4302, 12826, 21849, 30857, -25659, -17122, -16320, -7289, 1737, 10343, 19236, 28389, -20061, -11508, -2450, 6624, -12423, -4611, -30035, -22657, 17459, 25320, 8108, 15422, -9946, -2055, -27457, -20098, 28277, 3318, 10674, -14794, -7366, -32275, -16731, 23422, 30829, 5880, 13216, -12242, -29422, -21553, 18572, 25935, 521, 8389, -8727, -18096, -25689, -770, -11976, 12845, 32, 8882, 17894, 26664, -29916, -21076, -12043, -3225, 5734, 14502, 23550, 32363, -24193, -15432, -6402, 2367, 11391, 20131, 29158, -27594, -18576, -9739, -780, 7982, 16952, 25773, -30734, -21954, -12996, -4210, 4817, 13584, 22637, 31405, -25117, -16317, 32, 8866, 17901, 26669, -29846, -21088, -12059, -3277, 5735, 14523, 23460, 32363, -24228, -15455, -6421, 2350, 11363, 20148, 29106, -27610, -18588, -9807, -777, 7971, 17021, 25849, -30738, -21965, -12935, -4099, 4861, 13616, 22606, 31375, -25145, -16384, -7344, 1418, 10452, 19273, -7051, -14617, -24141, -29571, 28529, 18918, 13494, 5984, -3538, -8971, -16464, -26000, 17785, 32, 8872, 17905, 26723, -29846, -21078, -12046, -3225, 5755, 14524, 23546, 32315, -24221, -15425, -6406, 2346, 11380, 20209, 29168, -27606, -18636, 24713, 16926, 9550, 2200, -5154, -13051, -20416, -27776, 30337, -22334, -30172, -4739, -16211, 9192, 1340, 30828, 23480, -16662, -28627, -3217, -10528, -11215, -2370, -28164, -17370, 24373, 31154, 1272, 10019, -15753, -4932, 5832, 13374, 21373, 32417, -25093, -17560, -14750, -6748, 236, 11824, 19822, 26791, -18451, -10967, -3975, 8107, 15091, 22587, 26431, -32073, -24073, -12500, -5506, 2493, 21735, 29237, -28317, -17217, -9218, -1730, 1075, -22664, -31310, -7426, -12484, 11381, 2749, 30719, 1693, 9305, 17159, 28379, 69, 8883, 17904, 26668, -29834, -21019, -12057, -3293, 5740, 14496, 23524, 32300, -24276, -15427, -6430, 2362, 11383, 20152, 29180, -27533, -18590, -9808, -796, 7972, 17009, 25782, -30732, -21976, 116, 8864, 17893, 26672, 69, 8883, 17904, 26668, -29834, -21019, -12057, -3293, 5740, 14496, 23524, 32300, -24276, -15431, -6417, 2344, 11363, 20203, 29106, 84, 8883, 17915, 26666, -29846, -21086, -12122, -3277, 5735, 14569, 23545, 32302, -24222, -15447, -6482, 2346, 11366, 20148, 29180, -27609, -18642, -9739, 32, 8886, 17899, 26679, -29844, -21019, -12061, -3265, 5756, 14523, 23531, 32363, -24219, -15453, -6424, 2336, 11306, 20209, -24850, -17406, -9381, -2422, 5583, 13085, 20040, 28036, -30516, -23036, -15104, -25535, -16699, -9835, -3001, 5899, 12752, 19655, 28427, -30135, -23348, -14462, -7602, 15619, 24459, 31387, -27378, -20479, -11567, -4736, 2113, 11093, 17856, 24735, -31932, -8676, -1845, 7059, 13909, 20753, 29656, 117, 8872, 17894, 30923, 23053, 15689, 30226, 21705, 13191, 117, 8885, 101, 8879, 108, 8864, 17905, 26679, -29872, -21078, -12045, -3292, 5728, 69, 8883, 17904, 26668, -29834, -21019, -12059, -3275, 5741, 14504, 23550, 32290, -24222, -15446, -6482, 2346, 11366, 20148, 29180, -27609, -18599, -9808, -798, 7990, 99, 8878, 17903, 26733, -29851, -21077, -12062, -3275, 5735, 14496, 23534, 32357, -24198, -15448, -6432, 2347, 11385, 20159, 29173, 24207, 31865, 6970, 14054, -10820, -3281, -29141, -21016, 18614, 26231, 1321, 8431, -95, -25305, -18387, 22507, 29353, 4207, 12089, -13579, -5710, -30854, -24008, 16829, 7330, 14962, -9933, -2822, -27721, -20112, 19505, 27622, 1744, 9227, 83, 8868, 17900, 26663, -29843, -21077, -12063, -3225, 5741, 14527, 23535, 32293, -24200, -15426, -6482, 2345, 11362, 20158, 29183, -27533, -18569, -9804, -779, 7999, 17021, 6514, 15264, 23792, 28986, -28057, -19295, 71, 8878, 17910, 26723, -29851, -21019, -12043, -3278, 5739, 14506, 23535, 32312, -24193, -15379, -6404, 2346, 11363, 20129, 29181, -27587, -18585, -9808, -842, 7985, 17015, 25771, -30790, -21976, -12935, -4173, 4858, 13594, 22614, 31364, -25140, -16361, -7419, 1477, 6463, 15298, 23683, 29002, -28132, -19263, -13949, -5563, 3843, 8581, 17041, 26434, -18418, -9515, -62, 4180, 13582, 22482, 26768, -29352, -20904, -16178, -6765, 1615, 23324, 32149, -24955, -19630, -11234, -2347, 2999, 11333, 16681, 25571, -31558, -9951, -1432, 7374, 12709, 21119, 30564, -30217, -21853, -12428, -8144, 750, 10156, 30832, -25287, -16473, -12034, 20706, 85, 8879, 17891, 26657, -29848, -21088, -12122, -3277, 5735, 14569, 23545, 32302, -24222, -15447, -6482, 2331, 11381, 20157, 29175, -27613, -18565, -9817, -798, 8055, 17021, 25775, -30721, -21963, -12952, -4121, 4798, 83, 8868, 17910, 26679, -29843, -21077, -12063, -3225, 5757, 14521, 23466, 32297, -24194, -15454, -6417, 2347, 11379, 20144, 29153, -27609, -18636, -9817, -781, 7988, 17021, 25776, -30740, -21954, -12946, -4109, 2927, 10657, 20200, 25407, -32667, -22878, -9236, -1945, 7528, 13218, 20720, 30059, -21919, -14164, -4626, 559, 10032, 17820, 31443, -24813, -17324, -11618, -2085, 5133, 18783, 28545, -29475, -24319, -14773, -7028, 6611, 15897, 21359, 29089, -26901, -13528, 78, 8878, 17826, 26662, -29828, -21071, -12044, -3290, 5672, 14496, 23524, 32301, -24221, -15379, -6424, 2336, 11362, 20209, 29175, -27611, -18575, -9797, -798, 8045, 16952, -17017, -24766, -2002, -10791, 13977, 4191, 27905, 67, 8878, 17911, 26671, -29856, -21077, -12127, -3277, 5672, 14507, 23551, 32290, -24224, -15447, -6482, 2346, 11366, 20148, 29180, -27609, -18636, -9819, -775, 7972, 17004, 25757, -30725, -21969, -12931, -4109, 110, 8864, 17903, 26662, 30808, 23199, 15823, 4108, -3251, -10869, -22325, -29944, 28239, 22837, 31733, 7351, 12669, 392, 9061, 17468, 27108, -30037, -21408, -11926, -3336, 6115, 14688, 23092, 32745, -24405, -15774, -6299, 2273, 11693, 20351, 28727, -27156, -18689, -10130, -718, 7919, 17319, 25942, -31184, -21532, -13130, -4552, 4981, 13553, 22937, 31576, -25594, -15910, -7467, 1038, -17950, -25817, -949, -11866, 13047, 5152, 26979, 19086, -20499, -32469, -7555, -14417, 6382, -32208, -24378, -14459, -5543, 2307, 12176, 21146, 29020, -27555, -17699, -9841, -946, 9005, 16855, 25785, -29861, -20986, -13105, -3200, 5716, 13582, 23509, 32397, -25274, 114, 8868, 17892, 26662, -29834, -21065, -12061, -3275, 110, 8884, 17902, 26671, 99, 8878, 17903, 26733, -29851, -21077, -12062, -3275, 5735, 14496, 23534, 32357, -24198, -15448, -6432, 2347, 11385, 20159, 29173, -27523, -18595, -9829, -827, 7939, 16985, 25749, -30762, -22012, -12978, -4200, 4824, 13594, 22642, 31411, -25113, -16335, 6800, 14438, 24357, 29433, -28253, -18640, -13792, -5641, 3251, 8824, 16694, 25840, -17474, -9928, -966, 5113, 14001, 21613, 27432, -28952, -21023, -15517, -6612, 1519, 22755, 32365, -25311, -20246, -10309, -2713, 2082, 12270, 17115, 24642, -30958, -9512, -1643, 8025, 12829, 20949, 29907, -30091, -22223, -13075, -7251, 377, 9271, 31734, -24902, -17290, -11486, -2336, 5540, 11122, 20017, 28135, -32577, -23028, -15077, 6337, 16329, 69, 8883, 17904, 26668, -29834, -21019, -12049, -3287, 5672, 14464, 23524, 32312, -24200, -15444, -6430, 2339, 11346, 20131, 29181, -27598, -18576, -9802, -777, 7972, 17004, 25739, -30721, -21960, -12935, -4172, 4840, 13626, 22610, 68, 8868, 17910, 26658, -29843, -21079, -12043, -3203, 65, 8869, 17857, 26668, -29848, -21078, -12056, -3266, 1401, 10141, 16631, 27930, -29106, -22389, -10789, -2541, -26828, -18992, -11590, -167, 7187, 12153, 3484, 27336, 18216, -23463, -32113, -56, 65, 8876, 17891, 26681, -29845, -21077, -12089, -3293, 5755, 17596, 26188, 271, 11506, -12394, -5810, -27630, -18476, -29379, -20531, -14194, -6831, 1565, 8385, 23950, 29028, 21396, 13527, 6409, -1467, -9083, -24126, -32242, 67, 8873, 17891, 26673, -29840, -21081, -12055, -3288, 5755, 14525, -6044, -13687, -21045, -32750, 25414, 17808, 14546, 6913, -447, -12134, -23595, -32475, -6533, -13402, 10465, 3600, 29560, 20656, -18960, -25807, -1927, -8783, 12425, 4707, 30010, 22764, -17499, -25235, -8184, -15386, 9900, 2151, 27436, 26602, 17676, 8781, 3978, -4918, -13818, -18619, -27520, 29157, 24363, 70, 8877, 17911, 26673, -29834, -21060, 13444, 5754, 28962, 23780, -16460, 24605, 17135, 9642, 2173, 72, 8868, 17915, 26681, -29851, -21067, 115, 8835, 17865, 26634, -29838, -21082, -9991, -1505, -25217, -20324, 21462, 29980, -22777, -31263, -7518, -12440, 11320, 2794, 30635, 21629, -20177, -24591, -863, 73, 8883, 17901, 26669, -29865, -21078, -12045, -3275, 5739, 14508, 31439, 22572, 16239, 4791, 76, 8868, 17891, 26663, -29850, -21078, -12054, -3277, 76, 8872, 17892, 26662, -29865, -21071, -12044, -3294, 5741, 14525, 77, 8864, 17899, 26671, -29866, -21072, 77, 8868, 17894, 26666, -29851, -21113, -12044, -3282, 5744, 77, 8872, 17902, 26671, -29855, -21077, -12056, -3282, 5737, 14501, 23495, 32302, -24216, -15452, -6417, -11496, -3622, -26958, -17547, 22565, 32497, 929, 1359, 10156, 16610, 27911, -29079, -22337, 77, 8878, 17888, 26666, -29848, -21088, -12091, -3288, 5754, 14508, -5191, -13990, -20972, -31807, 24729, 17986, 15110, 6354, -16999, -24710, -2042, -10782, 14002, -31756, -24294, -14772, -5232, 2248, 11802, 21348, 79, 8870, 17911, 26673, -29827, 79, 8881, 17895, 26669, -29860, 80, 8877, 17891, 26682, -29844, -21084, -12048, -3294, 5734, 80, 8884, 17888, 26637, -29851, -21071, -12049, -3279, 5741, 31329, 22679, 16327, 4669, -3752, -10348, 82, 8884, 17888, 26666, -29849, -21078, -12056, 83, 8876, 17891, 26658, -29840, -21078, 83, 8885, 17891, 26673, -29840, -21116, -12042, -3273, 83, 8884, 17906, 26662, -29834, -21066, -12055, -3287, 5729, 14506, 84, 8864, 17906, 26665, -29845, -21060, 17190, 25042, 1664, 11106, -14317, -4391, -27769, -20400, 16505, 25219, 1479, 10267, -13487, -4696, -28466, -19688, 86, 8884, 17900, 26660, -29848, -21088, 89, 8864, 17898, 26668, -29845, 2401, 11160, 19668, 24863, -32167, -23419, 89, 8868, 17891, 26667, -29847, -21078, -12060, -3282, 31407, 22616, 16129, 4852, -3710, -10429, -21991 };
  }
  
  private ApplicationInfo ˋ(String paramString)
  {
    try
    {
      paramString = this.ॱˋ.getPackageManager().getApplicationInfo(paramString, 0);
      return paramString;
    }
    catch (Exception paramString)
    {
      String str = ˋ('\000', 16, 0).intern();
      StringBuilder localStringBuilder = new StringBuilder();
      localStringBuilder.append(ˋ('廊', 34, 2960).intern());
      localStringBuilder.append(paramString.getLocalizedMessage());
      LogUtils.LogError(str, localStringBuilder.toString());
      return null;
    }
    catch (PackageManager.NameNotFoundException paramString)
    {
      for (;;) {}
    }
  }
  
  private static String ˋ(char paramChar, int paramInt1, int paramInt2)
  {
    char[] arrayOfChar = new char[paramInt1];
    int i = 0;
    for (;;)
    {
      int j;
      if (i < paramInt1) {
        j = 92;
      } else {
        j = 85;
      }
      if (j != 92) {
        return new String(arrayOfChar);
      }
      arrayOfChar[i] = ((char)(int)(ˋˋ[(paramInt2 + i)] ^ i * ˊˊ ^ paramChar));
      i += 1;
    }
  }
  
  private JSONObject ˋ(JSONObject paramJSONObject, boolean paramBoolean)
  {
    JSONObject localJSONObject = new JSONObject();
    if (!paramBoolean) {}
    try
    {
      localJSONObject.put(ˋ('\000', 3, 2895).intern(), g.ॱ().ʼ());
      try
      {
        int i = this.ʻॱ;
        if (!paramBoolean) {
          this.ʻॱ += 1;
        }
        long l1 = y.ˏ();
        long l2 = paramJSONObject.optLong(LocalEventConsts.EVENT_KEY_TIMESTAMP);
        if (l2 != 0L)
        {
          localJSONObject.put(ˋ('碸', 3, 2898).intern(), l1);
          l1 = l2;
        }
        localJSONObject.put(ˋ('癡', 3, 2901).intern(), this.ᐝॱ);
        localJSONObject.put(LocalEventConsts.EVENT_KEY_TIMESTAMP, l1);
        localJSONObject.put(ˋ('\000', 2, 2904).intern(), y.ˋ());
        if (!paramBoolean) {
          localJSONObject.put(ˋ('\000', 2, 2906).intern(), i);
        }
        if (paramBoolean) {
          break label252;
        }
        localJSONObject.put(ˋ('\000', 9, 2908).intern(), ah.ˋ().ˎ());
      }
      finally {}
    }
    catch (JSONException localJSONException)
    {
      label252:
      for (;;) {}
    }
    LogUtils.LogError(ˋ('\000', 16, 0).intern(), ˋ('\000', 24, 2917).intern(), localThrowable);
    paramJSONObject.remove(LocalEventConsts.EVENT_KEY_TIMESTAMP);
    return localJSONObject;
  }
  
  private void ˋ(String paramString, JSONObject paramJSONObject, boolean paramBoolean)
  {
    ˎ(paramString, paramJSONObject, null, paramBoolean);
  }
  
  public static q ˎ()
  {
    try
    {
      if (ॱ == null) {
        ॱ = new q();
      }
      return ॱ;
    }
    finally {}
  }
  
  private static List<AdAction> ˎ(JSONObject paramJSONObject)
    throws JSONException
  {
    ArrayList localArrayList = new ArrayList();
    paramJSONObject = paramJSONObject.getJSONArray(ˋ('䎤', 7, 2227).intern());
    int i = 0;
    while (i < paramJSONObject.length())
    {
      localArrayList.add(new ad(paramJSONObject.getJSONObject(i)));
      i += 1;
    }
    return localArrayList;
  }
  
  private void ˎ(Context paramContext)
  {
    paramContext.registerReceiver(new BroadcastReceiver()new IntentFilter
    {
      public final void onReceive(Context paramAnonymousContext, Intent paramAnonymousIntent)
      {
        y.ˊ(paramAnonymousIntent);
      }
    }, new IntentFilter(ˋ(56085, 37, 1263).intern()));
  }
  
  public static void ˎ(Context paramContext, Intent paramIntent)
  {
    int i;
    if (paramIntent != null) {
      i = 39;
    } else {
      i = 34;
    }
    if (i != 39) {
      return;
    }
    try
    {
      w.ˊ();
      if (w.ॱ(paramContext)) {
        return;
      }
      localObject = paramIntent.getStringExtra(ˋ('\000', 8, 3366).intern());
      w.ˊ();
      if (localObject == null) {
        break label551;
      }
      i = 41;
    }
    catch (Throwable paramContext)
    {
      Object localObject;
      Iterator localIterator;
      boolean bool;
      int j;
      ResolveInfo localResolveInfo2;
      LogUtils.LogError(ˋ('\000', 16, 0).intern(), ˋ('\000', 33, 3475).intern());
      LogUtils.LogError(ˋ('\000', 16, 0).intern(), ˋ('\000', 8, 3508).intern(), paramContext);
      return;
    }
    localObject = ˋ('\000', 4, 3374).intern();
    label78:
    w.ॱ(paramContext, (String)localObject);
    localIterator = paramContext.getPackageManager().queryBroadcastReceivers(new Intent(ˋ('\000', 36, 3378).intern()), 0).iterator();
    for (;;)
    {
      label118:
      bool = localIterator.hasNext();
      j = 1;
      if (bool) {
        i = 1;
      } else {
        i = 0;
      }
      if (i != 1) {
        return;
      }
      i = ˌ + 87;
      ˎˏ = i % 128;
      if (i % 2 != 0) {
        i = 0;
      } else {
        i = 1;
      }
      if (i != 1)
      {
        ResolveInfo localResolveInfo1 = (ResolveInfo)localIterator.next();
        localObject = localResolveInfo1;
        try
        {
          bool = localResolveInfo1.activityInfo.packageName.equals(paramContext.getPackageName());
          if (bool) {
            i = 0;
          } else {
            i = 1;
          }
          if (i == 1) {}
        }
        catch (Throwable localThrowable)
        {
          break label428;
        }
      }
    }
    localResolveInfo2 = (ResolveInfo)localIterator.next();
    localObject = localResolveInfo2;
    if (localResolveInfo2.activityInfo.packageName.equals(paramContext.getPackageName())) {
      i = j;
    }
    for (;;)
    {
      localObject = localResolveInfo2;
      bool = ˋ('\000', 36, 3378).intern().equals(paramIntent.getAction());
      if (bool) {
        i = 91;
      } else {
        i = 3;
      }
      if (i != 91) {
        break label118;
      }
      i = ˌ + 101;
      ˎˏ = i % 128;
      localObject = localResolveInfo2;
      bool = InstallBroadcastReceiver.class.getName().equals(localResolveInfo2.activityInfo.name);
      if (!bool) {
        i = 8;
      } else {
        i = 5;
      }
      if (i != 8) {
        break label118;
      }
      i = ˎˏ + 113;
      ˌ = i % 128;
      localObject = localResolveInfo2;
      ((BroadcastReceiver)Class.forName(localResolveInfo2.activityInfo.name).newInstance()).onReceive(paramContext, paramIntent);
      break label118;
      label428:
      String str = ˋ('\000', 16, 0).intern();
      StringBuilder localStringBuilder = new StringBuilder();
      localStringBuilder.append(ˋ('᫕', 61, 3414).intern());
      localStringBuilder.append(((ResolveInfo)localObject).activityInfo.name);
      LogUtils.LogError(str, localStringBuilder.toString(), localResolveInfo2);
      break label118;
      label551:
      i = 91;
      if (i == 91) {
        break;
      }
      break label78;
      i = 0;
      if (i == 0) {
        break label118;
      }
    }
  }
  
  /* Error */
  private void ˎ(boolean paramBoolean)
  {
    // Byte code:
    //   0: aload_0
    //   1: monitorenter
    //   2: aload_0
    //   3: invokevirtual 3383	com/soomla/traceback/i/q:ˏ	()Z
    //   6: ifne +321 -> 327
    //   9: iconst_0
    //   10: istore_2
    //   11: goto +3 -> 14
    //   14: iload_2
    //   15: bipush 70
    //   17: if_icmpeq +179 -> 196
    //   20: aload_0
    //   21: getfield 125	com/soomla/traceback/i/q:ˋ	Z
    //   24: ifeq +309 -> 333
    //   27: bipush 76
    //   29: istore_2
    //   30: goto +3 -> 33
    //   33: iload_2
    //   34: bipush 76
    //   36: if_icmpeq +32 -> 68
    //   39: iconst_0
    //   40: bipush 16
    //   42: iconst_0
    //   43: invokestatic 103	com/soomla/traceback/i/q:ˋ	(CII)Ljava/lang/String;
    //   46: invokevirtual 107	java/lang/String:intern	()Ljava/lang/String;
    //   49: sipush 2473
    //   52: bipush 60
    //   54: bipush 53
    //   56: invokestatic 103	com/soomla/traceback/i/q:ˋ	(CII)Ljava/lang/String;
    //   59: invokevirtual 107	java/lang/String:intern	()Ljava/lang/String;
    //   62: invokestatic 394	com/soomla/traceback/LogUtils:ExtLogError	(Ljava/lang/String;Ljava/lang/String;)V
    //   65: aload_0
    //   66: monitorexit
    //   67: return
    //   68: iload_1
    //   69: ifne +28 -> 97
    //   72: aload_0
    //   73: ldc_w 3384
    //   76: bipush 11
    //   78: bipush 113
    //   80: invokestatic 103	com/soomla/traceback/i/q:ˋ	(CII)Ljava/lang/String;
    //   83: invokevirtual 107	java/lang/String:intern	()Ljava/lang/String;
    //   86: new 284	org/json/JSONObject
    //   89: dup
    //   90: invokespecial 285	org/json/JSONObject:<init>	()V
    //   93: iconst_1
    //   94: invokespecial 3386	com/soomla/traceback/i/q:ˋ	(Ljava/lang/String;Lorg/json/JSONObject;Z)V
    //   97: aload_0
    //   98: iconst_1
    //   99: putfield 129	com/soomla/traceback/i/q:ʼ	Z
    //   102: aload_0
    //   103: getfield 197	com/soomla/traceback/i/q:ॱˋ	Landroid/content/Context;
    //   106: invokestatic 3391	com/soomla/traceback/i/ac:ˏ	(Landroid/content/Context;)Lcom/soomla/traceback/i/ac;
    //   109: invokevirtual 3393	com/soomla/traceback/i/ac:ॱ	()V
    //   112: aload_0
    //   113: getfield 138	com/soomla/traceback/i/q:ˋॱ	Ljava/util/ArrayList;
    //   116: invokeinterface 277 1 0
    //   121: astore_3
    //   122: aload_3
    //   123: invokeinterface 282 1 0
    //   128: ifne +211 -> 339
    //   131: iconst_1
    //   132: istore_2
    //   133: goto +3 -> 136
    //   136: iload_2
    //   137: ifeq +42 -> 179
    //   140: aload_0
    //   141: getfield 138	com/soomla/traceback/i/q:ˋॱ	Ljava/util/ArrayList;
    //   144: invokeinterface 3396 1 0
    //   149: aload_0
    //   150: aconst_null
    //   151: putfield 138	com/soomla/traceback/i/q:ˋॱ	Ljava/util/ArrayList;
    //   154: aload_0
    //   155: getfield 3398	com/soomla/traceback/i/q:ʻ	Lcom/soomla/traceback/i/n;
    //   158: invokevirtual 3402	com/soomla/traceback/i/n:ˎ	()V
    //   161: invokestatic 3406	com/soomla/traceback/i/af:ˋ	()V
    //   164: aload_0
    //   165: getfield 147	com/soomla/traceback/i/q:ʾ	Lcom/soomla/traceback/i/aq;
    //   168: invokevirtual 3409	com/soomla/traceback/i/aq:ˋ	()V
    //   171: aload_0
    //   172: aconst_null
    //   173: putfield 147	com/soomla/traceback/i/q:ʾ	Lcom/soomla/traceback/i/aq;
    //   176: aload_0
    //   177: monitorexit
    //   178: return
    //   179: aload_3
    //   180: invokeinterface 342 1 0
    //   185: checkcast 417	com/soomla/traceback/TracebackListener
    //   188: invokeinterface 3412 1 0
    //   193: goto -71 -> 122
    //   196: getstatic 327	com/soomla/traceback/i/q:ˌ	I
    //   199: bipush 45
    //   201: iadd
    //   202: istore_2
    //   203: iload_2
    //   204: sipush 128
    //   207: irem
    //   208: putstatic 325	com/soomla/traceback/i/q:ˎˏ	I
    //   211: iload_2
    //   212: iconst_2
    //   213: irem
    //   214: ifne +8 -> 222
    //   217: iconst_0
    //   218: istore_2
    //   219: goto +5 -> 224
    //   222: iconst_1
    //   223: istore_2
    //   224: iload_2
    //   225: iconst_1
    //   226: if_icmpeq +32 -> 258
    //   229: iconst_0
    //   230: bipush 16
    //   232: iconst_0
    //   233: invokestatic 103	com/soomla/traceback/i/q:ˋ	(CII)Ljava/lang/String;
    //   236: invokevirtual 107	java/lang/String:intern	()Ljava/lang/String;
    //   239: ldc_w 3413
    //   242: bipush 37
    //   244: bipush 16
    //   246: invokestatic 103	com/soomla/traceback/i/q:ˋ	(CII)Ljava/lang/String;
    //   249: invokevirtual 107	java/lang/String:intern	()Ljava/lang/String;
    //   252: invokestatic 394	com/soomla/traceback/LogUtils:ExtLogError	(Ljava/lang/String;Ljava/lang/String;)V
    //   255: aload_0
    //   256: monitorexit
    //   257: return
    //   258: iconst_0
    //   259: bipush 16
    //   261: iconst_0
    //   262: invokestatic 103	com/soomla/traceback/i/q:ˋ	(CII)Ljava/lang/String;
    //   265: invokevirtual 107	java/lang/String:intern	()Ljava/lang/String;
    //   268: ldc_w 3413
    //   271: bipush 37
    //   273: bipush 16
    //   275: invokestatic 103	com/soomla/traceback/i/q:ˋ	(CII)Ljava/lang/String;
    //   278: invokevirtual 107	java/lang/String:intern	()Ljava/lang/String;
    //   281: invokestatic 394	com/soomla/traceback/LogUtils:ExtLogError	(Ljava/lang/String;Ljava/lang/String;)V
    //   284: aload_0
    //   285: monitorexit
    //   286: return
    //   287: astore_3
    //   288: goto +35 -> 323
    //   291: astore_3
    //   292: iconst_0
    //   293: bipush 16
    //   295: iconst_0
    //   296: invokestatic 103	com/soomla/traceback/i/q:ˋ	(CII)Ljava/lang/String;
    //   299: invokevirtual 107	java/lang/String:intern	()Ljava/lang/String;
    //   302: ldc_w 3414
    //   305: bipush 19
    //   307: bipush 124
    //   309: invokestatic 103	com/soomla/traceback/i/q:ˋ	(CII)Ljava/lang/String;
    //   312: invokevirtual 107	java/lang/String:intern	()Ljava/lang/String;
    //   315: aload_3
    //   316: iconst_1
    //   317: invokestatic 3419	com/soomla/traceback/i/h:ॱ	(Ljava/lang/String;Ljava/lang/String;Ljava/lang/Throwable;Z)V
    //   320: aload_0
    //   321: monitorexit
    //   322: return
    //   323: aload_0
    //   324: monitorexit
    //   325: aload_3
    //   326: athrow
    //   327: bipush 70
    //   329: istore_2
    //   330: goto -316 -> 14
    //   333: bipush 6
    //   335: istore_2
    //   336: goto -303 -> 33
    //   339: iconst_0
    //   340: istore_2
    //   341: goto -205 -> 136
    // Local variable table:
    //   start	length	slot	name	signature
    //   0	344	0	this	q
    //   0	344	1	paramBoolean	boolean
    //   10	331	2	i	int
    //   121	59	3	localIterator	Iterator
    //   287	1	3	localObject	Object
    //   291	35	3	localException	Exception
    // Exception table:
    //   from	to	target	type
    //   2	9	287	finally
    //   20	27	287	finally
    //   39	65	287	finally
    //   72	97	287	finally
    //   97	122	287	finally
    //   122	131	287	finally
    //   140	176	287	finally
    //   179	193	287	finally
    //   196	211	287	finally
    //   229	255	287	finally
    //   258	284	287	finally
    //   292	320	287	finally
    //   2	9	291	java/lang/Exception
    //   20	27	291	java/lang/Exception
    //   39	65	291	java/lang/Exception
    //   72	97	291	java/lang/Exception
    //   97	122	291	java/lang/Exception
    //   122	131	291	java/lang/Exception
    //   140	176	291	java/lang/Exception
    //   179	193	291	java/lang/Exception
    //   229	255	291	java/lang/Exception
    //   258	284	291	java/lang/Exception
  }
  
  private void ˏ(final Activity paramActivity, String paramString, boolean paramBoolean1, final boolean paramBoolean2, final boolean paramBoolean3)
  {
    final String str1 = g.ॱ().ʼ();
    g.ॱ().ᐝ(paramString);
    int i;
    if (paramString == null) {
      i = 64;
    } else {
      i = 74;
    }
    if (i != 64)
    {
      String str2;
      StringBuilder localStringBuilder;
      if (paramString.equals(ˋ('\000', 17, 749).intern()))
      {
        str2 = ˋ('\000', 16, 0).intern();
        localStringBuilder = new StringBuilder();
        localStringBuilder.append(ˋ('\000', 40, 766).intern());
        localStringBuilder.append(paramString);
        localStringBuilder.append(ˋ('栁', 77, 806).intern());
        LogUtils.ExtLogError(str2, localStringBuilder.toString());
      }
      else if (!paramString.matches(ˋ('\000', 15, 883).intern()))
      {
        str2 = ˋ('\000', 16, 0).intern();
        localStringBuilder = new StringBuilder();
        localStringBuilder.append(ˋ(36146, 15, 898).intern());
        localStringBuilder.append(paramString);
        localStringBuilder.append(ˋ('\000', 126, 913).intern());
        LogUtils.ExtLogError(str2, localStringBuilder.toString());
      }
      else
      {
        str2 = ˋ('\000', 16, 0).intern();
        localStringBuilder = new StringBuilder();
        localStringBuilder.append(ˋ('\000', 24, 1039).intern());
        localStringBuilder.append(paramString);
        LogUtils.ExtLogInfo(str2, localStringBuilder.toString());
        LogUtils.ExtLogInfo(ˋ('\000', 16, 0).intern(), ˋ('\000', 100, 1063).intern());
      }
    }
    else
    {
      LogUtils.ExtLogError(ˋ('\000', 16, 0).intern(), ˋ(63052, 93, 656).intern());
    }
    if (paramBoolean1)
    {
      ॱᐝ();
      new Handler(Looper.getMainLooper()).post(new SafeRunnable()
      {
        private static int ʻ = 0;
        private static char ʼ = '扨';
        private static char ʽ = '顸';
        private static char ˊॱ = '捻';
        private static int ॱˊ = 1;
        private static char ᐝ = '퓨';
        
        private static String ˎ(String paramAnonymousString)
        {
          paramAnonymousString = (char[])paramAnonymousString.toCharArray();
          char[] arrayOfChar1 = new char[paramAnonymousString.length];
          char[] arrayOfChar2 = new char[2];
          int i = 0;
          for (;;)
          {
            if (i < paramAnonymousString.length) {
              j = 1;
            } else {
              j = 0;
            }
            if (j != 1) {
              return new String(arrayOfChar1, 1, arrayOfChar1[0]);
            }
            int j = ʻ + 43;
            ॱˊ = j % 128;
            arrayOfChar2[0] = paramAnonymousString[i];
            j = i + 1;
            arrayOfChar2[1] = paramAnonymousString[j];
            a.ˋ(arrayOfChar2, ᐝ, ʽ, ʼ, ˊॱ);
            arrayOfChar1[i] = arrayOfChar2[0];
            arrayOfChar1[j] = arrayOfChar2[1];
            i += 2;
          }
        }
        
        public final void safeRun()
        {
          boolean bool = q.ˋ(q.this);
          int j = 0;
          int i;
          if (bool) {
            i = 1;
          } else {
            i = 0;
          }
          if (i == 0)
          {
            i = ʻ + 123;
            ॱˊ = i % 128;
            if (i % 2 == 0) {}
            q.ˊ(q.this, paramActivity);
            q.ˊ(q.this);
          }
          q localQ1 = q.this;
          String str2 = ˎ("ಚ婥鼇浌ᑚ䧢댹").intern();
          q localQ2 = q.this;
          if (!paramBoolean2) {
            i = 79;
          } else {
            i = 9;
          }
          String str1;
          if (i != 9)
          {
            str1 = null;
          }
          else
          {
            i = ॱˊ;
            int k = 85;
            i += 85;
            ʻ = i % 128;
            if (i % 2 == 0) {
              i = 45;
            } else {
              i = 24;
            }
            if (i != 24)
            {
              i = j;
              if (str1 == null) {
                i = 1;
              }
              if (i == 0) {
                break label216;
              }
            }
            else
            {
              if (str1 == null) {
                i = k;
              } else {
                i = 61;
              }
              if (i == 61) {
                break label216;
              }
            }
            str1 = ˎ("偖퇓팧䉜螅").intern();
            break label222;
            label216:
            str1 = str1;
          }
          label222:
          localQ1.ˎ(str2, q.ˊ(localQ2, str1), null, true);
          if (!paramBoolean3) {
            return;
          }
          q.this.ˊ(ˎ("떮坵鼇浌릟␝耍뱴蒽つ偟貗㏇ᥬ").intern(), new JSONObject());
        }
      });
      return;
    }
  }
  
  private void ˏ(String paramString1, String paramString2, Activity paramActivity)
  {
    localObject1 = ˋ('\000', 16, 0).intern();
    Object localObject2 = new StringBuilder();
    ((StringBuilder)localObject2).append(ˋ('\000', 25, 2321).intern());
    ((StringBuilder)localObject2).append(paramString2);
    LogUtils.LogDebug((String)localObject1, ((StringBuilder)localObject2).toString());
    try
    {
      localObject1 = (TracebackListener)Class.forName(paramString2).newInstance();
      localObject2 = ((TracebackListener)localObject1).getSdkVersion();
      if (ˋ(59402, 8, 2346).intern().equals(localObject2)) {
        return;
      }
      if (ˏ((TracebackListener)localObject1, (String)localObject2)) {
        break label934;
      }
      i = 0;
    }
    catch (Throwable paramString1)
    {
      paramActivity = ˋ('\000', 16, 0).intern();
      localObject1 = new StringBuilder();
      ((StringBuilder)localObject1).append(ˋ('ᚍ', 31, 2721).intern());
      ((StringBuilder)localObject1).append(paramString2);
      h.ॱ(paramActivity, ((StringBuilder)localObject1).toString(), paramString1, true);
      return;
      paramString1 = ˋ('\000', 16, 0).intern();
      paramActivity = new StringBuilder();
      paramActivity.append(ˋ(43147, 12, 2699).intern());
      paramActivity.append(paramString2);
      paramActivity.append(ˋ(54289, 10, 2711).intern());
      LogUtils.LogDebug(paramString1, paramActivity.toString());
      return;
    }
    catch (ClassNotFoundException paramString1)
    {
      for (;;)
      {
        continue;
        int i = 1;
        continue;
        i = 0;
        continue;
        paramString1 = paramActivity;
      }
    }
    if (i != 1)
    {
      localObject2 = new StringBuilder();
      ((StringBuilder)localObject2).append(ˋ(47369, 5, 2575).intern());
      ((StringBuilder)localObject2).append(paramString1);
      ((StringBuilder)localObject2).append(ˋ('\000', 36, 2580).intern());
      ((StringBuilder)localObject2).append(paramString1);
      ((StringBuilder)localObject2).append(ˋ('\000', 40, 2616).intern());
      y.ˏ(paramActivity, ((StringBuilder)localObject2).toString());
      paramActivity = ˋ('\000', 16, 0).intern();
      localObject2 = new StringBuilder();
      ((StringBuilder)localObject2).append(paramString1);
      ((StringBuilder)localObject2).append(ˋ(58453, 13, 2656).intern());
      ((StringBuilder)localObject2).append(((TracebackListener)localObject1).getSdkVersion());
      ((StringBuilder)localObject2).append(ˋ('\000', 21, 2669).intern());
      ((StringBuilder)localObject2).append(paramString2);
      ((StringBuilder)localObject2).append(ˋ('悩', 9, 2690).intern());
      ((StringBuilder)localObject2).append(((TracebackListener)localObject1).getListenerVersion());
      h.ॱ(paramActivity, ((StringBuilder)localObject2).toString(), null, true);
      paramActivity = ˋ('\000', 16, 0).intern();
      localObject1 = new StringBuilder();
      ((StringBuilder)localObject1).append(ˋ('ႏ', 16, 2528).intern());
      ((StringBuilder)localObject1).append(paramString1);
      ((StringBuilder)localObject1).append(ˋ(53081, 31, 2544).intern());
      LogUtils.ExtLogError(paramActivity, ((StringBuilder)localObject1).toString());
      return;
    }
    if (!ˊ((TracebackListener)localObject1))
    {
      i = 1;
      if (i != 0)
      {
        localObject2 = new StringBuilder();
        ((StringBuilder)localObject2).append(ˋ('\000', 12, 2354).intern());
        ((StringBuilder)localObject2).append(paramString1);
        ((StringBuilder)localObject2).append(ˋ('\000', 74, 2366).intern());
        y.ˏ(paramActivity, ((StringBuilder)localObject2).toString());
        paramActivity = ˋ('\000', 16, 0).intern();
        localObject2 = new StringBuilder();
        ((StringBuilder)localObject2).append(paramString1);
        ((StringBuilder)localObject2).append(ˋ('\000', 19, 2440).intern());
        ((StringBuilder)localObject2).append(((TracebackListener)localObject1).getListenerVersion());
        ((StringBuilder)localObject2).append(ˋ('ை', 34, 2459).intern());
        ((StringBuilder)localObject2).append(((TracebackListener)localObject1).getMinAgentVersion());
        ((StringBuilder)localObject2).append(ˋ('\000', 29, 2493).intern());
        ((StringBuilder)localObject2).append(ˋ(55176, 5, 2522).intern());
        ((StringBuilder)localObject2).append(ˋ('悌', 1, 2527).intern());
        h.ॱ(paramActivity, ((StringBuilder)localObject2).toString(), null, true);
        paramActivity = ˋ('\000', 16, 0).intern();
        localObject1 = new StringBuilder();
        ((StringBuilder)localObject1).append(ˋ('ႏ', 16, 2528).intern());
        ((StringBuilder)localObject1).append(paramString1);
        ((StringBuilder)localObject1).append(ˋ(53081, 31, 2544).intern());
        LogUtils.ExtLogError(paramActivity, ((StringBuilder)localObject1).toString());
        return;
      }
      i = ˎˏ + 91;
      ˌ = i % 128;
      if (paramActivity == null) {
        i = 16;
      } else {
        i = 37;
      }
      if (i == 37) {
        break label946;
      }
      paramString1 = this.ॱˋ;
      ((TracebackListener)localObject1).initialize(paramString1);
      this.ˋॱ.add(localObject1);
    }
  }
  
  private static boolean ˏ(TracebackListener paramTracebackListener, String paramString)
  {
    if (!ˋ(42813, 7, 2752).intern().equals(paramString)) {
      i = 14;
    } else {
      i = 56;
    }
    if (i != 14) {
      return true;
    }
    int i = ˌ + 117;
    ˎˏ = i % 128;
    if (!TextUtils.isEmpty(paramString)) {
      i = 9;
    } else {
      i = 89;
    }
    if (i != 89)
    {
      if (y.ˎ(paramString, paramTracebackListener.getMinSdkVersion()) >= 0) {
        i = 0;
      } else {
        i = 1;
      }
      if (i != 0) {
        return false;
      }
      i = ˎˏ + 55;
      ˌ = i % 128;
      if (i % 2 == 0) {
        i = 91;
      } else {
        i = 45;
      }
      if (i != 45)
      {
        if (y.ˎ(paramString, paramTracebackListener.getMaxSdkVersion()) <= 0) {
          i = 1;
        } else {
          i = 0;
        }
        if (i != 0) {
          return true;
        }
      }
      else
      {
        if (y.ˎ(paramString, paramTracebackListener.getMaxSdkVersion()) <= 0) {
          i = 1;
        } else {
          i = 0;
        }
        if (i != 0) {
          return true;
        }
      }
    }
    return false;
  }
  
  private static au ॱ(String paramString, JSONObject paramJSONObject1, JSONObject paramJSONObject2, JSONObject paramJSONObject3)
  {
    JSONObject localJSONObject1 = paramJSONObject2;
    Object localObject;
    if (paramJSONObject2 == null)
    {
      localJSONObject1 = new JSONObject();
      paramJSONObject2 = ˋ('\000', 16, 0).intern();
      localObject = new StringBuilder();
      ((StringBuilder)localObject).append(ˋ('\000', 25, 3212).intern());
      ((StringBuilder)localObject).append(paramString);
      LogUtils.LogDebug(paramJSONObject2, ((StringBuilder)localObject).toString());
    }
    for (;;)
    {
      try
      {
        localObject = y.ˏ(paramJSONObject1, true, paramString.equals(ˋ(48627, 7, 3237).intern()));
        if (localObject == null)
        {
          i = 10;
          if (i != 88)
          {
            LogUtils.LogError(ˋ('\000', 16, 0).intern(), ˋ('\000', 30, 3244).intern());
            return null;
          }
          JSONObject localJSONObject2 = new JSONObject();
          localJSONObject2.put(ˋ('\000', 4, 3274).intern(), paramString);
          y.ˎ(localJSONObject2, localJSONObject1);
          paramString = ˋ('砬', 9, 3278).intern();
          if (paramJSONObject3 != null) {
            i = 61;
          } else {
            i = 13;
          }
          if (i != 13)
          {
            i = ˌ + 115;
            ˎˏ = i % 128;
            if (i % 2 != 0) {
              i = 81;
            } else {
              i = 49;
            }
            if (i != 49)
            {
              paramString = paramJSONObject3.optString(LocalEventConsts.EVENT_KEY_INTEGRATION);
              paramJSONObject1 = LocalEventConsts.EVENT_KEY_IV;
              paramJSONObject2 = paramJSONObject3.optString(LocalEventConsts.EVENT_KEY_IV, null);
              localJSONObject2.put(paramJSONObject1, paramJSONObject2);
            }
            else
            {
              paramString = paramJSONObject3.optString(LocalEventConsts.EVENT_KEY_INTEGRATION);
              paramJSONObject1 = LocalEventConsts.EVENT_KEY_IV;
              paramJSONObject2 = paramJSONObject3.optString(LocalEventConsts.EVENT_KEY_IV, null);
              continue;
            }
          }
          boolean bool = TextUtils.isEmpty(paramString);
          if (bool) {
            i = 1;
          } else {
            i = 0;
          }
          if (i == 1)
          {
            i = ˌ + 113;
            ˎˏ = i % 128;
            if (i % 2 != 0) {
              i = 75;
            } else {
              i = 93;
            }
            if (i != 93) {
              paramString = ˋ('奛', 4, 3287).intern();
            } else {
              paramString = ˋ('奛', 4, 3287).intern();
            }
          }
          localJSONObject2.put(LocalEventConsts.EVENT_KEY_INTG, paramString);
          if (localJSONObject2.has(LocalEventConsts.EVENT_KEY_PLGN)) {
            break label545;
          }
          i = 0;
          if (i != 1) {
            localJSONObject2.put(LocalEventConsts.EVENT_KEY_PLGN, paramString);
          }
          y.ˎ(localJSONObject2, (JSONObject)localObject);
          paramString = new au(ao.ˊ(localJSONObject2), false);
          return paramString;
        }
      }
      catch (JSONException paramString)
      {
        paramJSONObject1 = ˋ('\000', 16, 0).intern();
        paramJSONObject2 = new StringBuilder();
        paramJSONObject2.append(ˋ('ǋ', 38, 3291).intern());
        paramJSONObject2.append(paramString.getLocalizedMessage());
        LogUtils.LogError(paramJSONObject1, paramJSONObject2.toString());
        return null;
      }
      int i = 88;
      continue;
      label545:
      i = 1;
    }
  }
  
  private JSONObject ॱ(String paramString)
  {
    JSONObject localJSONObject = new JSONObject();
    boolean bool = TextUtils.isEmpty(this.ˊˋ.ˏ(ˋ('\000', 14, 1300).intern()));
    int i;
    if (!bool) {
      i = 15;
    } else {
      i = 82;
    }
    Object localObject;
    if (i == 82)
    {
      i = ˌ + 37;
      ˎˏ = i % 128;
      if (i % 2 == 0) {
        i = 0;
      } else {
        i = 1;
      }
      if (i != 1) {}
      for (localObject = this.ˊˋ;; localObject = this.ˊˋ)
      {
        ((as)localObject).ˊ(ˋ('\000', 14, 1300).intern(), ˋ('\000', 5, 1314).intern());
        break;
      }
    }
    long l1 = ˏ(this.ॱˋ.getPackageName());
    long l2 = ʽ(this.ॱˋ.getPackageName());
    if (l1 <= 0L) {
      i = 9;
    } else {
      i = 13;
    }
    if (i == 13)
    {
      i = ˌ + 121;
      ˎˏ = i % 128;
      if (i % 2 == 0) {
        i = 47;
      } else {
        i = 3;
      }
      if (i != 47) {}
      for (;;)
      {
        try
        {
          localObject = ˋ('\000', 3, 1319).intern();
          localJSONObject.put((String)localObject, l1);
        }
        catch (JSONException paramString)
        {
          label283:
          LogUtils.LogError(ˋ('\000', 16, 0).intern(), ˋ('\000', 51, 1331).intern(), paramString);
        }
        localObject = ˋ('\000', 3, 1319).intern();
        continue;
        localJSONObject.put(ˋ('\000', 3, 1322).intern(), l2);
        break label392;
        localJSONObject.put(ˋ(59772, 2, 1325).intern(), true);
      }
    }
    for (;;)
    {
      localJSONObject.put(ˋ('\000', 4, 1327).intern(), paramString);
      w.ˊ(this.ॱˋ, localJSONObject);
      y.ˎ(localJSONObject, ॱˎ());
      return localJSONObject;
      if (l2 <= 0L) {
        i = 0;
      } else {
        i = 1;
      }
      if (i == 1) {
        break;
      }
      label392:
      if (!bool) {
        i = 1;
      } else {
        i = 0;
      }
      if (i == 0) {
        break label283;
      }
    }
  }
  
  /* Error */
  private void ॱ(Application paramApplication, Activity paramActivity, String paramString1, String paramString2, boolean paramBoolean)
  {
    // Byte code:
    //   0: aload_0
    //   1: invokevirtual 3383	com/soomla/traceback/i/q:ˏ	()Z
    //   4: ifeq +10 -> 14
    //   7: bipush 81
    //   9: istore 6
    //   11: goto +7 -> 18
    //   14: bipush 30
    //   16: istore 6
    //   18: iload 6
    //   20: bipush 30
    //   22: if_icmpeq +48 -> 70
    //   25: getstatic 327	com/soomla/traceback/i/q:ˌ	I
    //   28: bipush 117
    //   30: iadd
    //   31: istore 6
    //   33: iload 6
    //   35: sipush 128
    //   38: irem
    //   39: putstatic 325	com/soomla/traceback/i/q:ˎˏ	I
    //   42: iconst_0
    //   43: bipush 16
    //   45: iconst_0
    //   46: invokestatic 103	com/soomla/traceback/i/q:ˋ	(CII)Ljava/lang/String;
    //   49: invokevirtual 107	java/lang/String:intern	()Ljava/lang/String;
    //   52: sipush 13456
    //   55: bipush 48
    //   57: sipush 198
    //   60: invokestatic 103	com/soomla/traceback/i/q:ˋ	(CII)Ljava/lang/String;
    //   63: invokevirtual 107	java/lang/String:intern	()Ljava/lang/String;
    //   66: invokestatic 394	com/soomla/traceback/LogUtils:ExtLogError	(Ljava/lang/String;Ljava/lang/String;)V
    //   69: return
    //   70: aload_0
    //   71: getfield 125	com/soomla/traceback/i/q:ˋ	Z
    //   74: ifeq +9 -> 83
    //   77: iconst_1
    //   78: istore 6
    //   80: goto +6 -> 86
    //   83: iconst_0
    //   84: istore 6
    //   86: iload 6
    //   88: iconst_1
    //   89: if_icmpeq +574 -> 663
    //   92: iconst_0
    //   93: bipush 16
    //   95: iconst_0
    //   96: invokestatic 103	com/soomla/traceback/i/q:ˋ	(CII)Ljava/lang/String;
    //   99: invokevirtual 107	java/lang/String:intern	()Ljava/lang/String;
    //   102: iconst_0
    //   103: bipush 31
    //   105: sipush 285
    //   108: invokestatic 103	com/soomla/traceback/i/q:ˋ	(CII)Ljava/lang/String;
    //   111: invokevirtual 107	java/lang/String:intern	()Ljava/lang/String;
    //   114: invokestatic 245	com/soomla/traceback/LogUtils:LogDebug	(Ljava/lang/String;Ljava/lang/String;)V
    //   117: aload_0
    //   118: iload 5
    //   120: putfield 131	com/soomla/traceback/i/q:ᐝ	Z
    //   123: iload 5
    //   125: ifeq +571 -> 696
    //   128: iconst_0
    //   129: istore 6
    //   131: goto +3 -> 134
    //   134: iload 6
    //   136: iconst_1
    //   137: if_icmpeq +30 -> 167
    //   140: iconst_0
    //   141: bipush 16
    //   143: iconst_0
    //   144: invokestatic 103	com/soomla/traceback/i/q:ˋ	(CII)Ljava/lang/String;
    //   147: invokevirtual 107	java/lang/String:intern	()Ljava/lang/String;
    //   150: ldc_w 3549
    //   153: bipush 94
    //   155: sipush 316
    //   158: invokestatic 103	com/soomla/traceback/i/q:ˋ	(CII)Ljava/lang/String;
    //   161: invokevirtual 107	java/lang/String:intern	()Ljava/lang/String;
    //   164: invokestatic 394	com/soomla/traceback/LogUtils:ExtLogError	(Ljava/lang/String;Ljava/lang/String;)V
    //   167: iconst_0
    //   168: bipush 20
    //   170: sipush 410
    //   173: invokestatic 103	com/soomla/traceback/i/q:ˋ	(CII)Ljava/lang/String;
    //   176: invokevirtual 107	java/lang/String:intern	()Ljava/lang/String;
    //   179: invokestatic 3373	java/lang/Class:forName	(Ljava/lang/String;)Ljava/lang/Class;
    //   182: pop
    //   183: invokestatic 302	com/soomla/traceback/i/g:ॱ	()Lcom/soomla/traceback/i/g;
    //   186: aload_3
    //   187: invokevirtual 3551	com/soomla/traceback/i/g:ˋ	(Ljava/lang/String;)V
    //   190: aload_1
    //   191: invokevirtual 3557	android/app/Application:getApplicationContext	()Landroid/content/Context;
    //   194: astore_3
    //   195: aload_0
    //   196: aload_3
    //   197: putfield 197	com/soomla/traceback/i/q:ॱˋ	Landroid/content/Context;
    //   200: invokestatic 3560	com/soomla/traceback/i/q:ॱˊ	()Lcom/soomla/traceback/i/q$a;
    //   203: pop
    //   204: aload_0
    //   205: new 3531	com/soomla/traceback/i/as
    //   208: dup
    //   209: invokestatic 302	com/soomla/traceback/i/g:ॱ	()Lcom/soomla/traceback/i/g;
    //   212: invokevirtual 3562	com/soomla/traceback/i/g:ᐝ	()Ljava/lang/String;
    //   215: new 100	java/lang/String
    //   218: dup
    //   219: bipush 12
    //   221: newarray char
    //   223: dup
    //   224: iconst_0
    //   225: ldc_w 3563
    //   228: castore
    //   229: dup
    //   230: iconst_1
    //   231: ldc_w 3564
    //   234: castore
    //   235: dup
    //   236: iconst_2
    //   237: ldc_w 2930
    //   240: castore
    //   241: dup
    //   242: iconst_3
    //   243: ldc_w 3565
    //   246: castore
    //   247: dup
    //   248: iconst_4
    //   249: ldc_w 3118
    //   252: castore
    //   253: dup
    //   254: iconst_5
    //   255: ldc_w 3566
    //   258: castore
    //   259: dup
    //   260: bipush 6
    //   262: ldc_w 3567
    //   265: castore
    //   266: dup
    //   267: bipush 7
    //   269: ldc_w 3118
    //   272: castore
    //   273: dup
    //   274: bipush 8
    //   276: ldc_w 854
    //   279: castore
    //   280: dup
    //   281: bipush 9
    //   283: ldc_w 3568
    //   286: castore
    //   287: dup
    //   288: bipush 10
    //   290: ldc_w 2930
    //   293: castore
    //   294: dup
    //   295: bipush 11
    //   297: ldc_w 572
    //   300: castore
    //   301: invokespecial 3248	java/lang/String:<init>	([C)V
    //   304: invokespecial 3570	com/soomla/traceback/i/as:<init>	(Ljava/lang/String;Ljava/lang/String;)V
    //   307: putfield 3529	com/soomla/traceback/i/q:ˊˋ	Lcom/soomla/traceback/i/as;
    //   310: aload_0
    //   311: new 355	com/soomla/traceback/i/ao
    //   314: dup
    //   315: iconst_0
    //   316: bipush 8
    //   318: sipush 430
    //   321: invokestatic 103	com/soomla/traceback/i/q:ˋ	(CII)Ljava/lang/String;
    //   324: invokevirtual 107	java/lang/String:intern	()Ljava/lang/String;
    //   327: ldc_w 3571
    //   330: bipush 6
    //   332: sipush 438
    //   335: invokestatic 103	com/soomla/traceback/i/q:ˋ	(CII)Ljava/lang/String;
    //   338: invokevirtual 107	java/lang/String:intern	()Ljava/lang/String;
    //   341: aload_0
    //   342: getfield 3529	com/soomla/traceback/i/q:ˊˋ	Lcom/soomla/traceback/i/as;
    //   345: invokespecial 3574	com/soomla/traceback/i/ao:<init>	(Ljava/lang/String;Ljava/lang/String;Lcom/soomla/traceback/i/as;)V
    //   348: putfield 151	com/soomla/traceback/i/q:ˈ	Lcom/soomla/traceback/i/ao;
    //   351: aload_0
    //   352: new 3576	com/soomla/traceback/i/ap
    //   355: dup
    //   356: invokespecial 3577	com/soomla/traceback/i/ap:<init>	()V
    //   359: putfield 149	com/soomla/traceback/i/q:ˉ	Lcom/soomla/traceback/i/ap;
    //   362: aload_0
    //   363: new 3408	com/soomla/traceback/i/aq
    //   366: dup
    //   367: aload_3
    //   368: invokespecial 3579	com/soomla/traceback/i/aq:<init>	(Landroid/content/Context;)V
    //   371: putfield 147	com/soomla/traceback/i/q:ʾ	Lcom/soomla/traceback/i/aq;
    //   374: iconst_0
    //   375: bipush 16
    //   377: iconst_0
    //   378: invokestatic 103	com/soomla/traceback/i/q:ˋ	(CII)Ljava/lang/String;
    //   381: invokevirtual 107	java/lang/String:intern	()Ljava/lang/String;
    //   384: astore 7
    //   386: new 223	java/lang/StringBuilder
    //   389: dup
    //   390: invokespecial 224	java/lang/StringBuilder:<init>	()V
    //   393: astore 8
    //   395: aload 8
    //   397: ldc_w 3580
    //   400: bipush 34
    //   402: sipush 444
    //   405: invokestatic 103	com/soomla/traceback/i/q:ˋ	(CII)Ljava/lang/String;
    //   408: invokevirtual 107	java/lang/String:intern	()Ljava/lang/String;
    //   411: invokevirtual 228	java/lang/StringBuilder:append	(Ljava/lang/String;)Ljava/lang/StringBuilder;
    //   414: pop
    //   415: aload 8
    //   417: invokestatic 302	com/soomla/traceback/i/g:ॱ	()Lcom/soomla/traceback/i/g;
    //   420: invokevirtual 3582	com/soomla/traceback/i/g:ˏ	()Ljava/lang/String;
    //   423: invokevirtual 228	java/lang/StringBuilder:append	(Ljava/lang/String;)Ljava/lang/StringBuilder;
    //   426: pop
    //   427: aload 7
    //   429: aload 8
    //   431: invokevirtual 234	java/lang/StringBuilder:toString	()Ljava/lang/String;
    //   434: invokestatic 245	com/soomla/traceback/LogUtils:LogDebug	(Ljava/lang/String;Ljava/lang/String;)V
    //   437: aload_2
    //   438: ifnull +264 -> 702
    //   441: iconst_1
    //   442: istore 6
    //   444: goto +261 -> 705
    //   447: aload_0
    //   448: aload_2
    //   449: aload 4
    //   451: iconst_1
    //   452: iconst_0
    //   453: iload 5
    //   455: invokespecial 3584	com/soomla/traceback/i/q:ˏ	(Landroid/app/Activity;Ljava/lang/String;ZZZ)V
    //   458: aload_2
    //   459: ifnonnull +9 -> 468
    //   462: iconst_4
    //   463: istore 6
    //   465: goto +7 -> 472
    //   468: bipush 63
    //   470: istore 6
    //   472: iload 6
    //   474: iconst_4
    //   475: if_icmpeq +9 -> 484
    //   478: iconst_0
    //   479: istore 5
    //   481: goto +23 -> 504
    //   484: getstatic 325	com/soomla/traceback/i/q:ˎˏ	I
    //   487: bipush 37
    //   489: iadd
    //   490: istore 6
    //   492: iload 6
    //   494: sipush 128
    //   497: irem
    //   498: putstatic 327	com/soomla/traceback/i/q:ˌ	I
    //   501: iconst_1
    //   502: istore 5
    //   504: aload_0
    //   505: iload 5
    //   507: putfield 153	com/soomla/traceback/i/q:ˊᐝ	Z
    //   510: invokestatic 3327	com/soomla/traceback/i/w:ˊ	()Lcom/soomla/traceback/i/w$d;
    //   513: aload_3
    //   514: invokevirtual 3586	com/soomla/traceback/i/w:ˊ	(Landroid/content/Context;)V
    //   517: aload_0
    //   518: aload_1
    //   519: aload_2
    //   520: invokestatic 3589	com/soomla/traceback/i/n:ˎ	(Landroid/app/Application;Landroid/app/Activity;)Lcom/soomla/traceback/i/n;
    //   523: putfield 3398	com/soomla/traceback/i/q:ʻ	Lcom/soomla/traceback/i/n;
    //   526: aload_0
    //   527: invokestatic 3593	java/lang/Thread:getDefaultUncaughtExceptionHandler	()Ljava/lang/Thread$UncaughtExceptionHandler;
    //   530: putfield 3527	com/soomla/traceback/i/q:ˊॱ	Ljava/lang/Thread$UncaughtExceptionHandler;
    //   533: new 16	com/soomla/traceback/i/q$2
    //   536: dup
    //   537: aload_0
    //   538: invokespecial 3594	com/soomla/traceback/i/q$2:<init>	(Lcom/soomla/traceback/i/q;)V
    //   541: invokestatic 3598	java/lang/Thread:setDefaultUncaughtExceptionHandler	(Ljava/lang/Thread$UncaughtExceptionHandler;)V
    //   544: invokestatic 3282	com/soomla/traceback/i/ah:ˋ	()Lcom/soomla/traceback/i/ah;
    //   547: invokevirtual 3600	com/soomla/traceback/i/ah:ˏ	()V
    //   550: aload_0
    //   551: getfield 158	com/soomla/traceback/i/q:ˋˊ	Lcom/soomla/traceback/i/ax;
    //   554: aload_3
    //   555: invokevirtual 3601	com/soomla/traceback/i/ax:ˊ	(Landroid/content/Context;)V
    //   558: invokestatic 3603	com/soomla/traceback/i/q:ʾ	()V
    //   561: aload_0
    //   562: aload_3
    //   563: invokespecial 3605	com/soomla/traceback/i/q:ˎ	(Landroid/content/Context;)V
    //   566: aload_3
    //   567: getstatic 3608	com/soomla/traceback/LocalEventConsts:EVENT_NETWORK_CONNECTED	Ljava/lang/String;
    //   570: new 30	com/soomla/traceback/i/q$8
    //   573: dup
    //   574: aload_0
    //   575: invokespecial 3609	com/soomla/traceback/i/q$8:<init>	(Lcom/soomla/traceback/i/q;)V
    //   578: invokestatic 3612	com/soomla/traceback/i/y:ˎ	(Landroid/content/Context;Ljava/lang/String;Lcom/soomla/traceback/LocalEvent;)V
    //   581: aload_3
    //   582: getstatic 3615	com/soomla/traceback/LocalEventConsts:EVENT_APP_TO_FOREGROUND	Ljava/lang/String;
    //   585: new 8	com/soomla/traceback/i/q$10
    //   588: dup
    //   589: aload_0
    //   590: invokespecial 3616	com/soomla/traceback/i/q$10:<init>	(Lcom/soomla/traceback/i/q;)V
    //   593: invokestatic 3612	com/soomla/traceback/i/y:ˎ	(Landroid/content/Context;Ljava/lang/String;Lcom/soomla/traceback/LocalEvent;)V
    //   596: aload_0
    //   597: new 189	com/soomla/traceback/i/m
    //   600: dup
    //   601: invokespecial 3617	com/soomla/traceback/i/m:<init>	()V
    //   604: putfield 187	com/soomla/traceback/i/q:ˊ	Lcom/soomla/traceback/i/m;
    //   607: aload_0
    //   608: getfield 187	com/soomla/traceback/i/q:ˊ	Lcom/soomla/traceback/i/m;
    //   611: invokevirtual 3618	com/soomla/traceback/i/m:ॱ	()V
    //   614: aload_0
    //   615: invokespecial 3620	com/soomla/traceback/i/q:ʻॱ	()V
    //   618: aload_0
    //   619: invokespecial 3622	com/soomla/traceback/i/q:ᐝॱ	()V
    //   622: aload_0
    //   623: invokespecial 3624	com/soomla/traceback/i/q:ˉ	()V
    //   626: aload_0
    //   627: iconst_1
    //   628: putfield 125	com/soomla/traceback/i/q:ˋ	Z
    //   631: return
    //   632: astore_1
    //   633: iconst_0
    //   634: bipush 16
    //   636: iconst_0
    //   637: invokestatic 103	com/soomla/traceback/i/q:ˋ	(CII)Ljava/lang/String;
    //   640: invokevirtual 107	java/lang/String:intern	()Ljava/lang/String;
    //   643: sipush 11135
    //   646: bipush 35
    //   648: sipush 478
    //   651: invokestatic 103	com/soomla/traceback/i/q:ˋ	(CII)Ljava/lang/String;
    //   654: invokevirtual 107	java/lang/String:intern	()Ljava/lang/String;
    //   657: aload_1
    //   658: iconst_1
    //   659: invokestatic 3419	com/soomla/traceback/i/h:ॱ	(Ljava/lang/String;Ljava/lang/String;Ljava/lang/Throwable;Z)V
    //   662: return
    //   663: iconst_0
    //   664: bipush 16
    //   666: iconst_0
    //   667: invokestatic 103	com/soomla/traceback/i/q:ˋ	(CII)Ljava/lang/String;
    //   670: invokevirtual 107	java/lang/String:intern	()Ljava/lang/String;
    //   673: ldc_w 3625
    //   676: bipush 39
    //   678: sipush 246
    //   681: invokestatic 103	com/soomla/traceback/i/q:ˋ	(CII)Ljava/lang/String;
    //   684: invokevirtual 107	java/lang/String:intern	()Ljava/lang/String;
    //   687: invokestatic 245	com/soomla/traceback/LogUtils:LogDebug	(Ljava/lang/String;Ljava/lang/String;)V
    //   690: return
    //   691: astore 7
    //   693: goto -510 -> 183
    //   696: iconst_1
    //   697: istore 6
    //   699: goto -565 -> 134
    //   702: iconst_0
    //   703: istore 6
    //   705: iload 6
    //   707: iconst_1
    //   708: if_icmpeq +9 -> 717
    //   711: iconst_0
    //   712: istore 5
    //   714: goto -267 -> 447
    //   717: iconst_1
    //   718: istore 5
    //   720: goto -273 -> 447
    // Local variable table:
    //   start	length	slot	name	signature
    //   0	723	0	this	q
    //   0	723	1	paramApplication	Application
    //   0	723	2	paramActivity	Activity
    //   0	723	3	paramString1	String
    //   0	723	4	paramString2	String
    //   0	723	5	paramBoolean	boolean
    //   9	700	6	i	int
    //   384	44	7	str	String
    //   691	1	7	localThrowable	Throwable
    //   393	37	8	localStringBuilder	StringBuilder
    // Exception table:
    //   from	to	target	type
    //   92	123	632	java/lang/Exception
    //   140	167	632	java/lang/Exception
    //   167	183	632	java/lang/Exception
    //   183	437	632	java/lang/Exception
    //   447	458	632	java/lang/Exception
    //   504	631	632	java/lang/Exception
    //   167	183	691	java/lang/Throwable
  }
  
  static a ॱˊ()
  {
    try
    {
      if (ॱ.ˏॱ == null)
      {
        ॱ.ˏॱ = new a();
        ॱ.ˏॱ.start();
      }
      a localA = ॱ.ˏॱ;
      return localA;
    }
    finally {}
  }
  
  private JSONObject ॱˎ()
  {
    JSONObject localJSONObject1 = new JSONObject();
    JSONObject localJSONObject2 = new JSONObject();
    try
    {
      Iterator localIterator = this.ˋॱ.iterator();
      for (;;)
      {
        boolean bool = localIterator.hasNext();
        if (bool) {
          i = 79;
        } else {
          i = 18;
        }
        if (i == 18) {
          break;
        }
        int i = ˎˏ + 35;
        ˌ = i % 128;
        TracebackListener localTracebackListener = (TracebackListener)localIterator.next();
        JSONObject localJSONObject3 = new JSONObject();
        localJSONObject3.put(LocalEventConsts.EVENT_KEY_IV, localTracebackListener.getListenerVersion());
        localJSONObject3.put(LocalEventConsts.EVENT_KEY_SIV, localTracebackListener.getSdkVersion());
        localJSONObject2.put(localTracebackListener.getListenerName(), localJSONObject3);
      }
      localJSONObject1.put(ˋ('۫', 4, 2759).intern(), localJSONObject2);
      return localJSONObject1;
    }
    catch (JSONException localJSONException)
    {
      LogUtils.LogError(ˋ('\000', 16, 0).intern(), ˋ('\000', 28, 2763).intern(), localJSONException);
    }
    return localJSONObject1;
  }
  
  private void ॱᐝ()
  {
    Object localObject = this.ˊˋ;
    int i = 0;
    localObject = ((as)localObject).ˏ(ˋ('\000', 10, 1163).intern());
    if (!TextUtils.isEmpty((CharSequence)localObject)) {
      i = 1;
    }
    if (i != 1) {
      this.ᐝॱ = 1;
    } else {
      this.ᐝॱ = (Integer.parseInt((String)localObject) + 1);
    }
    this.ʻॱ = 1;
  }
  
  private void ᐝॱ()
  {
    try
    {
      if (this.ʿ == null)
      {
        this.ʿ = new Thread(new SafeRunnable()
        {
          private static char ˎ = '眱';
          
          private static String ˏ(char paramAnonymousChar, int paramAnonymousInt, String paramAnonymousString1, String paramAnonymousString2, String paramAnonymousString3)
          {
            paramAnonymousString3 = (char[])paramAnonymousString3.toCharArray();
            paramAnonymousString2 = (char[])paramAnonymousString2.toCharArray();
            paramAnonymousString1 = (char[])((char[])paramAnonymousString1.toCharArray()).clone();
            paramAnonymousString2 = (char[])paramAnonymousString2.clone();
            paramAnonymousString1[0] = ((char)(paramAnonymousChar ^ paramAnonymousString1[0]));
            paramAnonymousString2[2] = ((char)(paramAnonymousString2[2] + (char)paramAnonymousInt));
            char c = paramAnonymousString3.length;
            char[] arrayOfChar = new char[c];
            paramAnonymousChar = '\000';
            for (;;)
            {
              if (paramAnonymousChar < c) {
                paramAnonymousInt = 1;
              } else {
                paramAnonymousInt = 0;
              }
              if (paramAnonymousInt != 1) {
                return new String(arrayOfChar);
              }
              b.ˋ(paramAnonymousString1, paramAnonymousString2, paramAnonymousChar);
              arrayOfChar[paramAnonymousChar] = ((char)(int)(paramAnonymousString3[paramAnonymousChar] ^ paramAnonymousString1[((paramAnonymousChar + '\003') % 4)] ^ ˎ));
              paramAnonymousChar += '\001';
            }
          }
          
          /* Error */
          public final void safeRun()
          {
            // Byte code:
            //   0: ldc 52
            //   2: iconst_0
            //   3: ldc 54
            //   5: ldc 56
            //   7: ldc 58
            //   9: invokestatic 60	com/soomla/traceback/i/q$15:ˏ	(CILjava/lang/String;Ljava/lang/String;Ljava/lang/String;)Ljava/lang/String;
            //   12: invokevirtual 64	java/lang/String:intern	()Ljava/lang/String;
            //   15: sipush 23836
            //   18: iconst_0
            //   19: ldc 66
            //   21: ldc 56
            //   23: ldc 68
            //   25: invokestatic 60	com/soomla/traceback/i/q$15:ˏ	(CILjava/lang/String;Ljava/lang/String;Ljava/lang/String;)Ljava/lang/String;
            //   28: invokevirtual 64	java/lang/String:intern	()Ljava/lang/String;
            //   31: invokestatic 74	com/soomla/traceback/LogUtils:LogDebug	(Ljava/lang/String;Ljava/lang/String;)V
            //   34: invokestatic 80	java/lang/Thread:currentThread	()Ljava/lang/Thread;
            //   37: invokevirtual 84	java/lang/Thread:isInterrupted	()Z
            //   40: ifne +187 -> 227
            //   43: aload_0
            //   44: getfield 22	com/soomla/traceback/i/q$15:ˋ	Lcom/soomla/traceback/i/q;
            //   47: astore_3
            //   48: aload_3
            //   49: monitorenter
            //   50: aload_0
            //   51: getfield 22	com/soomla/traceback/i/q$15:ˋ	Lcom/soomla/traceback/i/q;
            //   54: invokevirtual 89	java/lang/Object:wait	()V
            //   57: aload_0
            //   58: getfield 22	com/soomla/traceback/i/q$15:ˋ	Lcom/soomla/traceback/i/q;
            //   61: invokestatic 93	com/soomla/traceback/i/q:ʻ	(Lcom/soomla/traceback/i/q;)Landroid/os/Handler;
            //   64: ifnonnull +32 -> 96
            //   67: aload_0
            //   68: getfield 22	com/soomla/traceback/i/q$15:ˋ	Lcom/soomla/traceback/i/q;
            //   71: invokestatic 97	com/soomla/traceback/i/q:ॱˊ	()Lcom/soomla/traceback/i/q$a;
            //   74: invokevirtual 103	com/soomla/traceback/i/q$a:ˊ	()Landroid/os/Handler;
            //   77: invokestatic 106	com/soomla/traceback/i/q:ˎ	(Lcom/soomla/traceback/i/q;Landroid/os/Handler;)Landroid/os/Handler;
            //   80: pop
            //   81: aload_0
            //   82: getfield 22	com/soomla/traceback/i/q$15:ˋ	Lcom/soomla/traceback/i/q;
            //   85: invokestatic 93	com/soomla/traceback/i/q:ʻ	(Lcom/soomla/traceback/i/q;)Landroid/os/Handler;
            //   88: ifnonnull +8 -> 96
            //   91: aload_3
            //   92: monitorexit
            //   93: goto -59 -> 34
            //   96: aload_0
            //   97: getfield 22	com/soomla/traceback/i/q$15:ˋ	Lcom/soomla/traceback/i/q;
            //   100: invokestatic 93	com/soomla/traceback/i/q:ʻ	(Lcom/soomla/traceback/i/q;)Landroid/os/Handler;
            //   103: aconst_null
            //   104: invokevirtual 112	android/os/Handler:removeCallbacksAndMessages	(Ljava/lang/Object;)V
            //   107: aload_0
            //   108: getfield 22	com/soomla/traceback/i/q$15:ˋ	Lcom/soomla/traceback/i/q;
            //   111: invokestatic 93	com/soomla/traceback/i/q:ʻ	(Lcom/soomla/traceback/i/q;)Landroid/os/Handler;
            //   114: astore 4
            //   116: new 11	com/soomla/traceback/i/q$15$5
            //   119: dup
            //   120: aload_0
            //   121: invokespecial 115	com/soomla/traceback/i/q$15$5:<init>	(Lcom/soomla/traceback/i/q$15;)V
            //   124: astore 5
            //   126: aload_0
            //   127: getfield 22	com/soomla/traceback/i/q$15:ˋ	Lcom/soomla/traceback/i/q;
            //   130: invokestatic 119	com/soomla/traceback/i/q:ˊॱ	(Lcom/soomla/traceback/i/q;)Z
            //   133: ifeq +99 -> 232
            //   136: aload_0
            //   137: getfield 22	com/soomla/traceback/i/q$15:ˋ	Lcom/soomla/traceback/i/q;
            //   140: invokestatic 123	com/soomla/traceback/i/q:ʽ	(Lcom/soomla/traceback/i/q;)I
            //   143: i2l
            //   144: lstore_1
            //   145: goto +3 -> 148
            //   148: aload 4
            //   150: aload 5
            //   152: lload_1
            //   153: invokevirtual 127	android/os/Handler:postDelayed	(Ljava/lang/Runnable;J)Z
            //   156: pop
            //   157: aload_3
            //   158: monitorexit
            //   159: goto -125 -> 34
            //   162: astore 4
            //   164: aload_3
            //   165: monitorexit
            //   166: aload 4
            //   168: athrow
            //   169: ldc 52
            //   171: iconst_0
            //   172: ldc 54
            //   174: ldc 56
            //   176: ldc 58
            //   178: invokestatic 60	com/soomla/traceback/i/q$15:ˏ	(CILjava/lang/String;Ljava/lang/String;Ljava/lang/String;)Ljava/lang/String;
            //   181: invokevirtual 64	java/lang/String:intern	()Ljava/lang/String;
            //   184: iconst_0
            //   185: ldc -128
            //   187: ldc -126
            //   189: ldc 56
            //   191: ldc -124
            //   193: invokestatic 60	com/soomla/traceback/i/q$15:ˏ	(CILjava/lang/String;Ljava/lang/String;Ljava/lang/String;)Ljava/lang/String;
            //   196: invokevirtual 64	java/lang/String:intern	()Ljava/lang/String;
            //   199: invokestatic 135	com/soomla/traceback/LogUtils:LogError	(Ljava/lang/String;Ljava/lang/String;)V
            //   202: aload_0
            //   203: getfield 22	com/soomla/traceback/i/q$15:ˋ	Lcom/soomla/traceback/i/q;
            //   206: astore_3
            //   207: aload_3
            //   208: monitorenter
            //   209: aload_0
            //   210: getfield 22	com/soomla/traceback/i/q$15:ˋ	Lcom/soomla/traceback/i/q;
            //   213: invokestatic 139	com/soomla/traceback/i/q:ˏॱ	(Lcom/soomla/traceback/i/q;)Ljava/lang/Thread;
            //   216: pop
            //   217: aload_3
            //   218: monitorexit
            //   219: return
            //   220: astore 4
            //   222: aload_3
            //   223: monitorexit
            //   224: aload 4
            //   226: athrow
            //   227: return
            //   228: astore_3
            //   229: goto -60 -> 169
            //   232: lconst_0
            //   233: lstore_1
            //   234: goto -86 -> 148
            // Local variable table:
            //   start	length	slot	name	signature
            //   0	237	0	this	15
            //   144	90	1	l	long
            //   228	1	3	localInterruptedException	InterruptedException
            //   114	35	4	localHandler	Handler
            //   162	5	4	localObject1	Object
            //   220	5	4	localObject2	Object
            //   124	27	5	local5	5
            // Exception table:
            //   from	to	target	type
            //   50	93	162	finally
            //   96	145	162	finally
            //   148	159	162	finally
            //   209	219	220	finally
            //   43	50	228	java/lang/InterruptedException
            //   164	169	228	java/lang/InterruptedException
          }
        });
        this.ʿ.start();
      }
      return;
    }
    finally
    {
      localObject = finally;
      throw localObject;
    }
  }
  
  public void addTags(List<String> paramList)
  {
    for (;;)
    {
      try
      {
        boolean bool = ˏ();
        if (!bool) {
          i = 52;
        } else {
          i = 76;
        }
        if (i != 52)
        {
          i = ˌ + 67;
          ˎˏ = i % 128;
          if (i % 2 == 0) {
            i = 96;
          } else {
            i = 27;
          }
          if (i != 96)
          {
            LogUtils.ExtLogError(ˋ('\000', 16, 0).intern(), ˋ('\000', 46, 1382).intern());
            return;
          }
          LogUtils.ExtLogError(ˋ('\000', 16, 0).intern(), ˋ('\000', 46, 1382).intern());
          return;
        }
        if (this.ˋ)
        {
          i = 1;
          if (i != 0)
          {
            ArrayList localArrayList = new ArrayList();
            localObject1 = paramList.iterator();
            bool = ((Iterator)localObject1).hasNext();
            if (!bool) {
              i = 9;
            } else {
              i = 36;
            }
            if (i != 9)
            {
              i = ˎˏ + 35;
              ˌ = i % 128;
              localObject2 = (String)((Iterator)localObject1).next();
              if (((String)localObject2).length() > 50)
              {
                String str = ˋ('\000', 16, 0).intern();
                StringBuilder localStringBuilder = new StringBuilder();
                localStringBuilder.append(ˋ(58199, 17, 1485).intern());
                localStringBuilder.append((String)localObject2);
                localStringBuilder.append(ˋ('᫕', 38, 1502).intern());
                LogUtils.ExtLogError(str, localStringBuilder.toString());
                continue;
              }
              localArrayList.add(localObject2);
              continue;
            }
            localObject1 = ˋ('\000', 8, 1540).intern();
            if (localArrayList.size() <= 0) {
              break;
            }
            ˋ((String)localObject1, ˊ(localArrayList), true);
            return;
          }
          LogUtils.ExtLogError(ˋ('\000', 16, 0).intern(), ˋ('\000', 57, 1428).intern());
          return;
        }
      }
      catch (Exception localException)
      {
        Object localObject1 = ˋ('\000', 16, 0).intern();
        Object localObject2 = new StringBuilder();
        ((StringBuilder)localObject2).append(ˋ('坵', 18, 1548).intern());
        ((StringBuilder)localObject2).append(paramList);
        h.ॱ((String)localObject1, ((StringBuilder)localObject2).toString(), localException, true);
        return;
      }
      int i = 0;
    }
  }
  
  public void getGAIDWithFallbackAsync(final Context paramContext, final UidReadyCallback paramUidReadyCallback)
  {
    new Thread(new SafeRunnable()
    {
      public final void safeRun()
      {
        final String str = y.ˎ(paramContext);
        new Handler(Looper.getMainLooper()).post(new SafeRunnable()
        {
          public final void safeRun()
          {
            q.3.this.ˊ.onUidReady(str);
          }
        });
      }
    }).start();
  }
  
  public void getUserAdActions(final UserAdActionsCallback paramUserAdActionsCallback)
  {
    for (;;)
    {
      try
      {
        if (!ˏ())
        {
          i = 77;
          Object localObject;
          if (i != 77)
          {
            localObject = ˋ('\000', 57, 1759).intern();
            LogUtils.ExtLogError(ˋ('\000', 16, 0).intern(), (String)localObject);
            paramUserAdActionsCallback.onAdActionsFailed((String)localObject);
            return;
          }
          boolean bool = this.ˋ;
          if (bool) {
            i = 0;
          } else {
            i = 1;
          }
          if (i != 0)
          {
            i = ˌ + 49;
            ˎˏ = i % 128;
            if (i % 2 == 0) {
              i = 91;
            } else {
              i = 33;
            }
            if (i != 91)
            {
              localObject = ˋ('\000', 66, 1816).intern();
              LogUtils.ExtLogError(ˋ('\000', 16, 0).intern(), (String)localObject);
              paramUserAdActionsCallback.onAdActionsFailed((String)localObject);
              return;
            }
            localObject = ˋ('\000', 66, 1816).intern();
            LogUtils.ExtLogError(ˋ('\000', 16, 0).intern(), (String)localObject);
            paramUserAdActionsCallback.onAdActionsFailed((String)localObject);
            return;
          }
          bool = this.ॱᐝ;
          if (!bool) {
            i = 0;
          } else {
            i = 1;
          }
          if (i != 0)
          {
            i = ˌ + 9;
            ˎˏ = i % 128;
            localObject = ˋ('\000', 25, 1882).intern();
            LogUtils.ExtLogError(ˋ('\000', 16, 0).intern(), (String)localObject);
            paramUserAdActionsCallback.onAdActionsFailed((String)localObject);
            return;
          }
          this.ॱᐝ = true;
          try
          {
            long l = this.ˊ.ॱˊ();
            localObject = ˋ('\000', 19, 1907).intern();
            localObject = this.ˊˋ.ˏ((String)localObject);
            if (localObject == null) {
              break label495;
            }
            if (y.ˏ() - Long.parseLong((String)localObject) < l) {
              break label490;
            }
          }
          catch (Exception localException1)
          {
            h.ॱ(ˋ('\000', 16, 0).intern(), ˋ('\000', 40, 1940).intern(), localException1, true);
            y.ॱ(ˋ(39486, 32, 1980).intern(), new l()
            {
              private static int ʽ = 0;
              private static int ˊॱ = 1;
              private static char ˋ = '㒂';
              private static char ˏ = '佁';
              private static char ॱ = '㨃';
              private static char ᐝ = '熀';
              
              private static String ˎ(String paramAnonymousString)
              {
                int i = ˊॱ + 13;
                ʽ = i % 128;
                if (i % 2 != 0) {
                  i = 86;
                } else {
                  i = 39;
                }
                if (i != 86) {
                  paramAnonymousString = paramAnonymousString.toCharArray();
                } else {
                  paramAnonymousString = paramAnonymousString.toCharArray();
                }
                paramAnonymousString = (char[])paramAnonymousString;
                char[] arrayOfChar1 = new char[paramAnonymousString.length];
                char[] arrayOfChar2 = new char[2];
                i = 0;
                for (;;)
                {
                  if (i < paramAnonymousString.length) {
                    j = 1;
                  } else {
                    j = 0;
                  }
                  if (j != 1) {
                    return new String(arrayOfChar1, 1, arrayOfChar1[0]);
                  }
                  int j = ʽ + 69;
                  ˊॱ = j % 128;
                  arrayOfChar2[0] = paramAnonymousString[i];
                  j = i + 1;
                  arrayOfChar2[1] = paramAnonymousString[j];
                  a.ˋ(arrayOfChar2, ॱ, ˋ, ˏ, ᐝ);
                  arrayOfChar1[i] = arrayOfChar2[0];
                  arrayOfChar1[j] = arrayOfChar2[1];
                  i += 2;
                }
              }
              
              public final void ˊ(av paramAnonymousAv)
              {
                q.ˎ(q.this);
                int i;
                if (paramAnonymousAv != null) {
                  i = 0;
                } else {
                  i = 1;
                }
                if (i != 0) {
                  i = -1;
                } else {
                  i = paramAnonymousAv.ॱ().ˎ();
                }
                paramAnonymousAv = new StringBuilder();
                paramAnonymousAv.append(ˎ("贀ᮣ誏㐉磉긧ꦧ蘿紋簬ອ‴方빺棂ꂬ製漳腲ᯡ魰⛉馂ﶗ⇟喝帚?䫽擛殅೹").intern());
                paramAnonymousAv.append(i);
                paramAnonymousAv = paramAnonymousAv.toString();
                LogUtils.LogError(ˎ("扛⌫맨巛髖஢똰颅ㅚ쉈灝㑍쉈⍊噋").intern(), paramAnonymousAv);
                paramUserAdActionsCallback.onAdActionsFailed(paramAnonymousAv);
              }
              
              public final void ˏ(JSONObject paramAnonymousJSONObject)
              {
                try
                {
                  localObject = ˎ("扛⌫맨巛髖஢똰颅ㅚ쉈灝㑍쉈⍊噋").intern();
                  StringBuilder localStringBuilder = new StringBuilder();
                  localStringBuilder.append(ˎ("徨銞뛽혇雱泷䳎⧾爁ꜥ箛㴠崙?ꌒ雱?␊ꑓ方빺棂ꂬ製漳腲َ殅೹").intern());
                  localStringBuilder.append(paramAnonymousJSONObject.toString());
                  LogUtils.LogDebug((String)localObject, localStringBuilder.toString());
                  localObject = q.ˋ(paramAnonymousJSONObject);
                  q.this.ˋ(ˎ("㢂빺棂ꂬ製漳腲ꨀᄆ㪬鎮탺鿊ꇃᵿ").intern(), paramAnonymousJSONObject.toString(), ˎ("㠢빺棂ꂬ製漳腲ꨀᄆ빃ꆸ஡爋㜡ㆼ蚽查").intern());
                  q.ˎ(q.this);
                  paramUserAdActionsCallback.onAdActionsReceived((List)localObject);
                  return;
                }
                catch (Exception paramAnonymousJSONObject)
                {
                  Object localObject = new StringBuilder();
                  ((StringBuilder)localObject).append(ˎ("贀ᮣ誏㐉倜䩓霱ᮡ櫌ອ‴方빺棂ꂬ製漳腲ᯡ魰⛉馂ﶗ⇟喝帚?䫽擛殅೹").intern());
                  ((StringBuilder)localObject).append(paramAnonymousJSONObject.getLocalizedMessage());
                  paramAnonymousJSONObject = ((StringBuilder)localObject).toString();
                  LogUtils.LogError(ˎ("扛⌫맨巛髖஢똰颅ㅚ쉈灝㑍쉈⍊噋").intern(), paramAnonymousJSONObject);
                  paramUserAdActionsCallback.onAdActionsFailed(paramAnonymousJSONObject);
                }
              }
            });
            return;
          }
          if (i == 0)
          {
            localObject = ˋ('\000', 14, 1926).intern();
            localObject = ˎ(new JSONObject(this.ˊˋ.ˏ((String)localObject)));
            this.ॱᐝ = false;
            paramUserAdActionsCallback.onAdActionsReceived((List)localObject);
            return;
          }
        }
        i = 42;
      }
      catch (Exception localException2)
      {
        h.ॱ(ˋ('\000', 16, 0).intern(), ˋ('\000', 29, 2012).intern(), localException2, true);
        paramUserAdActionsCallback.onAdActionsFailed(ˋ('\000', 14, 2041).intern());
        return;
      }
      continue;
      label490:
      int i = 0;
      continue;
      label495:
      i = 1;
    }
  }
  
  public void initialize(Activity paramActivity, String paramString1, String paramString2)
  {
    initialize(paramActivity, paramString1, paramString2, false);
  }
  
  public void initialize(Activity paramActivity, String paramString1, String paramString2, boolean paramBoolean)
  {
    ॱ(paramActivity.getApplication(), paramActivity, paramString1, paramString2, paramBoolean);
  }
  
  public void initialize(Application paramApplication, String paramString1, String paramString2)
  {
    initialize(paramApplication, paramString1, paramString2, false);
  }
  
  public void initialize(Application paramApplication, String paramString1, String paramString2, boolean paramBoolean)
  {
    ॱ(paramApplication, null, paramString1, paramString2, paramBoolean);
  }
  
  public void onCrossPromotionAdClicked(Object paramObject, Advertising.AdType paramAdType, String paramString)
  {
    ʼॱ();
    i.ˊ(paramObject, paramAdType, paramString);
  }
  
  public void onCrossPromotionAdClosed(Object paramObject, Advertising.AdType paramAdType, String paramString)
  {
    ʼॱ();
    i.ˎ(paramObject, paramAdType, paramString);
  }
  
  public void onCrossPromotionAdDisplayed(Object paramObject, Advertising.AdType paramAdType, String paramString)
  {
    ʼॱ();
    i.ˏ(paramObject, paramAdType, paramString);
  }
  
  public void onInAppPurchaseCompleted(String paramString1, double paramDouble, String paramString2)
  {
    int i;
    if (!ˏ()) {
      i = 3;
    } else {
      i = 17;
    }
    if (i != 3)
    {
      i = ˌ + 81;
      ˎˏ = i % 128;
      LogUtils.ExtLogError(ˋ('\000', 16, 0).intern(), ˋ('㛛', 64, 2114).intern());
      return;
    }
    JSONObject localJSONObject = new JSONObject();
    try
    {
      localJSONObject.put(ˋ('\000', 4, 2178).intern(), paramString1);
      localJSONObject.put(ˋ('\000', 5, 2182).intern(), paramDouble);
      localJSONObject.put(ˋ('\000', 4, 2187).intern(), paramString2);
      ˋ(ˋ(32974, 13, 2191).intern(), localJSONObject, true);
      return;
    }
    catch (JSONException paramString1)
    {
      LogUtils.LogError(ˋ('\000', 16, 0).intern(), ˋ('\000', 23, 2204).intern(), paramString1);
    }
  }
  
  public void overrideCountryCode(String paramString)
  {
    int i;
    if (ˏ()) {
      i = 1;
    } else {
      i = 0;
    }
    if (i != 0)
    {
      LogUtils.ExtLogError(ˋ('\000', 16, 0).intern(), ˋ('\000', 59, 2055).intern());
      return;
    }
    g.ॱ().ॱ(paramString);
  }
  
  public void removeTags(List<String> paramList)
  {
    for (;;)
    {
      try
      {
        if (!ˏ())
        {
          i = 71;
          if (i != 39)
          {
            if (!this.ˋ) {
              break label263;
            }
            i = 92;
            if (i != 91)
            {
              String str1 = ˋ('↿', 11, 1675).intern();
              if ((paramList == null) || (paramList.size() <= 0)) {
                break;
              }
              ˎ(str1, ˊ(paramList), null, true);
              return;
            }
            LogUtils.ExtLogError(ˋ('\000', 16, 0).intern(), ˋ(64330, 60, 1615).intern());
            return;
          }
          i = ˌ + 79;
          ˎˏ = i % 128;
          if (i % 2 == 0) {
            i = 1;
          } else {
            i = 0;
          }
          if (i != 1)
          {
            LogUtils.ExtLogError(ˋ('\000', 16, 0).intern(), ˋ('厨', 49, 1566).intern());
            return;
          }
          LogUtils.ExtLogError(ˋ('\000', 16, 0).intern(), ˋ('厨', 49, 1566).intern());
          return;
        }
      }
      catch (Exception localException)
      {
        String str2 = ˋ('\000', 16, 0).intern();
        StringBuilder localStringBuilder = new StringBuilder();
        localStringBuilder.append(ˋ(58676, 20, 1686).intern());
        localStringBuilder.append(paramList);
        h.ॱ(str2, localStringBuilder.toString(), localException, true);
        return;
      }
      int i = 39;
      continue;
      label263:
      i = 91;
    }
  }
  
  public void setAdListener(AdListener paramAdListener)
  {
    if (ˏ()) {
      i = 56;
    } else {
      i = 88;
    }
    if (i != 56)
    {
      this.ˋˊ.ˊ(paramAdListener);
      return;
    }
    int i = ˌ + 103;
    ˎˏ = i % 128;
    LogUtils.ExtLogError(ˋ('\000', 16, 0).intern(), ˋ('伛', 53, 1706).intern());
  }
  
  public void setUserConsent(boolean paramBoolean)
  {
    g.ॱ().ˏ(paramBoolean);
  }
  
  public void setUserId(String paramString)
  {
    for (;;)
    {
      try
      {
        if (!ˏ())
        {
          i = 1;
          if (i != 0)
          {
            bool1 = this.ˋ;
            if (bool1) {
              i = 27;
            } else {
              i = 75;
            }
            if (i != 75)
            {
              if (paramString != null) {
                i = 0;
              } else {
                i = 1;
              }
              if (i != 0)
              {
                i = ˎˏ + 113;
                ˌ = i % 128;
                String str1 = g.ॱ().ʼ();
                if (str1 != null) {
                  i = 2;
                } else {
                  i = 14;
                }
                if (i != 14) {
                  break label459;
                }
              }
              if (paramString == null) {
                i = 44;
              } else {
                i = 23;
              }
              if (i == 44) {
                break label464;
              }
              i = ˎˏ + 49;
              ˌ = i % 128;
              if (i % 2 != 0) {
                i = 6;
              } else {
                i = 5;
              }
              if (i != 6)
              {
                if (!paramString.equals(g.ॱ().ʼ())) {
                  break label435;
                }
                i = 81;
                break label438;
              }
              if (!paramString.equals(g.ॱ().ʼ())) {
                break label447;
              }
              i = 18;
              break label450;
              boolean bool2 = this.ʻ.ˏ();
              if (bool1) {
                break label469;
              }
              i = 1;
              break label471;
              if (bool2) {
                ˋ(ˋ('\000', 11, 624).intern(), new JSONObject(), true);
              }
              ˏ(null, paramString, bool1, true, bool2);
              return;
            }
            LogUtils.ExtLogError(ˋ('\000', 16, 0).intern(), ˋ('ᓄ', 62, 562).intern());
            return;
          }
          i = ˌ + 107;
          ˎˏ = i % 128;
          if (i % 2 == 0) {
            i = 53;
          } else {
            i = 34;
          }
          if (i != 34)
          {
            LogUtils.ExtLogError(ˋ('\000', 16, 0).intern(), ˋ('\000', 49, 513).intern());
            return;
          }
          LogUtils.ExtLogError(ˋ('\000', 16, 0).intern(), ˋ('\000', 49, 513).intern());
          return;
        }
      }
      catch (Exception localException)
      {
        String str2 = ˋ('\000', 16, 0).intern();
        StringBuilder localStringBuilder = new StringBuilder();
        localStringBuilder.append(ˋ(51161, 21, 635).intern());
        localStringBuilder.append(paramString);
        h.ॱ(str2, localStringBuilder.toString(), localException, true);
        return;
      }
      int i = 0;
      continue;
      label435:
      i = 95;
      label438:
      if (i != 81)
      {
        break label459;
        label447:
        i = 7;
        label450:
        if (i == 7)
        {
          label459:
          bool1 = true;
          continue;
        }
      }
      label464:
      boolean bool1 = false;
      continue;
      label469:
      i = 0;
      label471:
      if (i == 0) {}
    }
  }
  
  public void shutdown()
  {
    try
    {
      ˎ(false);
      return;
    }
    finally
    {
      localObject = finally;
      throw localObject;
    }
  }
  
  public final int ʻ()
  {
    ApplicationInfo localApplicationInfo = ˋ(ˋ('\000', 19, 2941).intern());
    int i;
    if (localApplicationInfo != null) {
      i = 85;
    } else {
      i = 83;
    }
    if (i != 85) {
      return -1;
    }
    return localApplicationInfo.uid;
  }
  
  public final JSONObject ʼ()
  {
    return ˋ(new JSONObject(), false);
  }
  
  public final boolean ʽ()
  {
    return this.ʽ;
  }
  
  public final Context ˊ()
  {
    return this.ॱˋ;
  }
  
  public final String ˊ(String paramString)
  {
    return this.ˊˋ.ˏ(paramString);
  }
  
  public final void ˊ(String paramString1, String paramString2, String paramString3, String paramString4, JSONObject paramJSONObject)
  {
    JSONObject localJSONObject = new JSONObject();
    try
    {
      localJSONObject.put(ˋ('\000', 5, 143).intern(), paramString1);
      localJSONObject.put(ˋ('\000', 5, 148).intern(), paramString2);
      localJSONObject.put(ˋ(52376, 6, 153).intern(), paramString3);
      boolean bool = TextUtils.isEmpty(paramString4);
      int i;
      if (bool) {
        i = 1;
      } else {
        i = 0;
      }
      if (i == 0)
      {
        i = ˎˏ + 19;
        ˌ = i % 128;
        if (i % 2 != 0) {
          i = 85;
        } else {
          i = 96;
        }
        if (i != 85) {}
        for (paramString1 = ˋ(63373, 5, 159).intern();; paramString1 = ˋ(63373, 5, 159).intern())
        {
          localJSONObject.put(paramString1, paramString4);
          break;
        }
      }
      y.ˎ(localJSONObject, ॱˎ());
      if (paramJSONObject == null) {
        i = 0;
      } else {
        i = 1;
      }
      if (i == 1)
      {
        i = ˌ + 13;
        ˎˏ = i % 128;
        y.ˎ(localJSONObject, paramJSONObject);
      }
    }
    catch (JSONException paramString1)
    {
      LogUtils.LogError(ˋ('\000', 16, 0).intern(), ˋ('⠐', 26, 164).intern(), paramString1);
    }
    ˋ(ˋ('\000', 8, 190).intern(), localJSONObject, true);
  }
  
  public final void ˊ(String paramString, JSONObject paramJSONObject)
  {
    ˎ(paramString, paramJSONObject, null, true);
  }
  
  public final void ˊ(boolean paramBoolean)
  {
    if (ˏ()) {
      i = 19;
    } else {
      i = 29;
    }
    int j = 1;
    if (i != 29)
    {
      i = ˌ + 15;
      ˎˏ = i % 128;
      if (i % 2 == 0) {}
      LogUtils.ExtLogError(ˋ('\000', 16, 0).intern(), ˋ('\000', 51, 1173).intern());
      return;
    }
    int i = j;
    if (this.ˋ) {
      i = 0;
    }
    if (i != 0)
    {
      this.ʽ = paramBoolean;
      return;
    }
    LogUtils.ExtLogError(ˋ('\000', 16, 0).intern(), ˋ('冏', 39, 1224).intern());
  }
  
  public final as ˊॱ()
  {
    return this.ˊˋ;
  }
  
  public final ap ˋ()
  {
    return this.ˉ;
  }
  
  public final void ˋ(ai.2 param2)
  {
    this.ˋˊ.ॱ(param2);
  }
  
  public final void ˋ(String paramString1, String paramString2, String paramString3)
  {
    this.ˊˋ.ˊ(paramString1, paramString2);
    this.ˊˋ.ˊ(paramString3, Long.toString(y.ˏ()));
  }
  
  public final n ˋॱ()
  {
    return this.ʻ;
  }
  
  public final void ˎ(final String paramString, final JSONObject paramJSONObject1, final JSONObject paramJSONObject2, boolean paramBoolean)
  {
    if (ˏ()) {
      return;
    }
    int i;
    if (this.ᐝ) {
      i = 59;
    } else {
      i = 28;
    }
    if (i != 59)
    {
      if (!ˋ('\000', 8, 190).intern().equals(paramString)) {
        i = 1;
      } else {
        i = 0;
      }
      if (i == 0)
      {
        double d3 = Math.random();
        double d2 = 100.0D;
        double d1 = d2;
        if (!this.ᐝ)
        {
          d1 = d2;
          if (this.ˊ != null) {
            d1 = this.ˊ.ˎ();
          }
        }
        if (d3 * 100.0D >= d1)
        {
          paramJSONObject1 = ˋ('\000', 16, 0).intern();
          paramJSONObject2 = new StringBuilder();
          paramJSONObject2.append(ˋ(40618, 11, 2854).intern());
          paramJSONObject2.append(paramString);
          paramJSONObject2.append(ˋ(40033, 30, 2865).intern());
          LogUtils.LogDebug(paramJSONObject1, paramJSONObject2.toString());
          return;
        }
      }
    }
    String str = ˋ('\000', 16, 0).intern();
    StringBuilder localStringBuilder = new StringBuilder();
    localStringBuilder.append(ˋ('\000', 22, 2814).intern());
    localStringBuilder.append(paramString);
    localStringBuilder.append(ˋ('\000', 18, 2836).intern());
    localStringBuilder.append(paramJSONObject1.toString());
    LogUtils.LogDebug(str, localStringBuilder.toString());
    paramString = new SafeRunnable()
    {
      private static int ʻ = 0;
      private static int ʼ = 41;
      private static boolean ʽ = true;
      private static boolean ˊॱ = true;
      private static int ˋॱ = 1;
      private static char[] ᐝ = { 124, 120, 118, 117, 106, 73, 125, 155, 138, 140, 142, 139, 148, 162, 146, 151, 144, 157, 152, 156, 141, 159, 160, 145, 150, 99, 81, 110, 82, 108, 158, 149, 80, 87, 153, 74, 136, 114 };
      
      private static String ॱ(String paramAnonymousString)
      {
        int i = ʻ + 105;
        ˋॱ = i % 128;
        if (i % 2 == 0) {
          i = 73;
        } else {
          i = 28;
        }
        if (i != 28) {
          paramAnonymousString = paramAnonymousString.getBytes("ISO-8859-1");
        } else {
          paramAnonymousString = paramAnonymousString.getBytes("ISO-8859-1");
        }
        paramAnonymousString = (byte[])paramAnonymousString;
        char[] arrayOfChar1 = ᐝ;
        int k = ʼ;
        boolean bool = ˊॱ;
        int j = 0;
        if (bool) {
          i = 1;
        } else {
          i = 0;
        }
        if (i != 1)
        {
          if (ʽ) {
            i = 74;
          } else {
            i = 13;
          }
          if (i != 74)
          {
            i = null.length;
            paramAnonymousString = new char[i];
            if (i < 0) {
              i = 55;
            } else {
              i = 28;
            }
            if (i != 28) {
              throw new NullPointerException();
            }
            return new String(paramAnonymousString);
          }
          i = ʻ + 125;
          ˋॱ = i % 128;
          if (i % 2 != 0) {}
          i = null.length;
          paramAnonymousString = new char[i];
          if (i < 0) {
            i = 0;
          } else {
            i = 1;
          }
          if (i != 1)
          {
            i = ˋॱ + 17;
            ʻ = i % 128;
            throw new NullPointerException();
          }
          return new String(paramAnonymousString);
        }
        int m = paramAnonymousString.length;
        char[] arrayOfChar2 = new char[m];
        i = j;
        for (;;)
        {
          if (i < m) {
            j = 83;
          } else {
            j = 54;
          }
          if (j == 54) {
            break;
          }
          arrayOfChar2[i] = ((char)(arrayOfChar1[(paramAnonymousString[(m - 1 - i)] + Byte.MAX_VALUE)] - k));
          i += 1;
        }
        return new String(arrayOfChar2);
      }
      
      public final void safeRun()
      {
        Object localObject1 = ॱ("").intern();
        Object localObject2 = new StringBuilder();
        ((StringBuilder)localObject2).append(ॱ("").intern());
        ((StringBuilder)localObject2).append(paramString);
        LogUtils.LogDebug((String)localObject1, ((StringBuilder)localObject2).toString());
        localObject1 = q.ˎ(paramString, this.ˊ, paramJSONObject1, paramJSONObject2);
        if (localObject1 == null) {
          i = 11;
        } else {
          i = 19;
        }
        if (i != 11)
        {
          if (!paramString.equals(ॱ("¥¥£").intern())) {
            i = 96;
          } else {
            i = 35;
          }
          String str;
          StringBuilder localStringBuilder;
          if (i != 35)
          {
            i = ʻ + 33;
            ˋॱ = i % 128;
            int j = 0;
            if (i % 2 == 0) {
              i = 1;
            } else {
              i = 0;
            }
            if (i != 0)
            {
              if (paramString.equals(ॱ("¥¥£").intern())) {
                i = 54;
              } else {
                i = 8;
              }
              if (i != 8) {
                break label294;
              }
            }
            else
            {
              i = j;
              if (paramString.equals(ॱ("¥¥£").intern())) {
                i = 1;
              }
              if (i == 1) {
                break label294;
              }
            }
            if (!paramString.equals(ॱ("¥£").intern())) {
              break label381;
            }
            localObject2 = q.this.ˊॱ();
            str = ॱ("¦¢").intern();
            localStringBuilder = new StringBuilder();
            localStringBuilder.append(q.ˋॱ(q.this));
            ((as)localObject2).ˊ(str, localStringBuilder.toString());
            break label381;
          }
          try
          {
            label294:
            ((au)localObject1).ˏ().put(ॱ("££").intern(), q.ॱˊ(q.this).size());
          }
          catch (Exception localException)
          {
            str = ॱ("").intern();
            localStringBuilder = new StringBuilder();
            localStringBuilder.append(ॱ("£  ").intern());
            localStringBuilder.append(localException.getLocalizedMessage());
            LogUtils.LogError(str, localStringBuilder.toString());
          }
          label381:
          q.ˏ(q.this).add(localObject1);
          q.ͺ(q.this);
          return;
        }
        int i = ˋॱ + 19;
        ʻ = i % 128;
        if (i % 2 == 0) {}
        LogUtils.LogError(ॱ("").intern(), ॱ("¤££¢ ¡ ").intern());
      }
    };
    if (paramBoolean) {
      i = 14;
    } else {
      i = 92;
    }
    if (i == 92)
    {
      i = ˎˏ + 5;
      ˌ = i % 128;
      if (y.ˎ()) {
        i = 18;
      } else {
        i = 35;
      }
      if (i == 18) {}
    }
    else
    {
      new Thread(paramString).start();
      return;
    }
    paramString.run();
  }
  
  public final boolean ˎ(String paramString)
  {
    return ˋ(paramString) != null;
  }
  
  public final long ˏ(String paramString)
  {
    try
    {
      long l = this.ॱˋ.getPackageManager().getPackageInfo(paramString, 0).firstInstallTime;
      return l;
    }
    catch (Throwable paramString)
    {
      for (;;) {}
    }
    return 0L;
  }
  
  public final void ˏ(String paramString, JSONObject paramJSONObject1, JSONObject paramJSONObject2)
  {
    ˎ(paramString, paramJSONObject1, paramJSONObject2, true);
  }
  
  public final boolean ˏ()
  {
    try
    {
      boolean bool = this.ʼ;
      return bool;
    }
    finally
    {
      localObject = finally;
      throw localObject;
    }
  }
  
  public final void ˏॱ()
  {
    try
    {
      this.ˊᐝ = true;
      ˋ(ˋ('\000', 11, 624).intern(), new JSONObject(), false);
      try
      {
        if (this.ॱˎ != null) {
          this.ॱˎ.removeCallbacksAndMessages(null);
        }
        ˉ();
        return;
      }
      finally {}
      return;
    }
    catch (Exception localException)
    {
      h.ॱ(ˋ('\000', 16, 0).intern(), ˋ(33397, 24, 3342).intern(), localException, false);
    }
  }
  
  public final void ͺ()
  {
    if (this.ˊᐝ)
    {
      ʻॱ();
      ᐝॱ();
      ˊ(ˋ(47510, 13, 3329).intern(), new JSONObject());
    }
    this.ˊᐝ = false;
  }
  
  public final aq ॱ()
  {
    return this.ʾ;
  }
  
  public final void ॱ(ap.5 param5)
  {
    this.ˊ.ˏ(param5);
  }
  
  public final void ॱ(String paramString1, Map<String, String> paramMap, String paramString2)
  {
    if (paramMap == null) {
      return;
    }
    String str = Integer.toHexString(paramMap.hashCode());
    Object localObject = this.ˊˋ;
    StringBuilder localStringBuilder = new StringBuilder();
    localStringBuilder.append(ˋ('䵥', 14, 2234).intern());
    localStringBuilder.append(paramString1);
    localObject = ((as)localObject).ˏ(localStringBuilder.toString());
    int i;
    if (TextUtils.isEmpty((CharSequence)localObject)) {
      i = 7;
    } else {
      i = 89;
    }
    if ((i == 89) && (((String)localObject).equals(str))) {
      return;
    }
    localObject = this.ˊˋ;
    localStringBuilder = new StringBuilder();
    localStringBuilder.append(ˋ('䵥', 14, 2234).intern());
    localStringBuilder.append(paramString1);
    ((as)localObject).ˊ(localStringBuilder.toString(), str);
    ˋ(ˋ('\000', 9, 2248).intern(), ˊ(paramString1, paramMap, paramString2), true);
  }
  
  public final boolean ॱ(long paramLong, String paramString)
  {
    paramString = this.ˊˋ.ˏ(paramString);
    return (paramString == null) || (y.ˏ() - Long.parseLong(paramString) >= paramLong);
  }
  
  public final m ॱˋ()
  {
    return this.ˊ;
  }
  
  public final void ᐝ()
  {
    ʿ();
  }
  
  static final class a
    extends Thread
  {
    private Handler ˏ;
    
    a() {}
    
    public final void run()
    {
      Looper.prepare();
      this.ˏ = new Handler();
      Looper.loop();
    }
    
    public final Handler ˊ()
    {
      return this.ˏ;
    }
  }
}
