package com.a.ll;

import android.content.Context;
import android.content.Intent;
import android.content.Intent.ShortcutIconResource;
import android.content.pm.PackageInfo;
import android.content.pm.PackageManager;
import android.content.pm.ProviderInfo;
import java.util.Iterator;
import java.util.List;
import java.util.regex.Pattern;

public class ax
{
  public static String A()
  {
    char[] arrayOfChar = new char[28];
    int i = (char)'é';
    arrayOfChar[0] = i;
    arrayOfChar[1] = ((char)'­');
    arrayOfChar[2] = ((char)'');
    arrayOfChar[3] = ((char)'Ð');
    arrayOfChar[4] = ((char)'Ý');
    arrayOfChar[5] = ((char)'¾');
    arrayOfChar[6] = ((char)'ê');
    arrayOfChar[7] = ((char)'ø');
    arrayOfChar[8] = ((char)'');
    arrayOfChar[9] = ((char)'');
    arrayOfChar[10] = ((char)'');
    arrayOfChar[11] = ((char)'ä');
    arrayOfChar[12] = ((char)'±');
    arrayOfChar[13] = ((char)'¡');
    arrayOfChar[14] = ((char)'ã');
    arrayOfChar[15] = ((char)'í');
    arrayOfChar[16] = ((char)'ü');
    arrayOfChar[17] = ((char)'');
    arrayOfChar[18] = ((char)'Ò');
    arrayOfChar[19] = ((char)'Ë');
    arrayOfChar[20] = ((char)'õ');
    arrayOfChar[21] = i;
    arrayOfChar[22] = ((char)'');
    arrayOfChar[23] = ((char)'ó');
    arrayOfChar[24] = ((char)'»');
    arrayOfChar[25] = ((char)'');
    arrayOfChar[26] = ((char)'·');
    arrayOfChar[27] = ((char)'ë');
    return String.valueOf(new char[] { (char)(arrayOfChar[0] ^ 0x88), (char)(arrayOfChar[1] ^ 0xC3), (char)('㏴' / arrayOfChar[2]), (char)('岠' / arrayOfChar[3]), (char)(arrayOfChar[4] ^ 0xB2), (char)(arrayOfChar[5] ^ 0xD7), (char)(arrayOfChar[6] ^ 0x8E), (char)(-arrayOfChar[7] + 294), (char)('㨾' / arrayOfChar[8]), (char)(arrayOfChar[9] ^ 0xFF), (char)(arrayOfChar[10] ^ 0xEE), (char)(arrayOfChar[11] ^ 0x81), (char)(-arrayOfChar[12] + 287), (char)(arrayOfChar[13] ^ 0xD5), (char)(arrayOfChar[14] ^ 0xCD), (char)(-arrayOfChar[15] + 336), (char)(-arrayOfChar[16] + 349), (char)('䃌' / arrayOfChar[17]), (char)(arrayOfChar[18] ^ 0xB7), (char)('冭' / arrayOfChar[19]), (char)(arrayOfChar[20] ^ 0x9A), (char)(-arrayOfChar[21] + 347), (char)('㳹' / arrayOfChar[22]), (char)(arrayOfChar[23] ^ 0xDD), (char)('㒘' / arrayOfChar[24]), (char)(arrayOfChar[25] ^ 0xC8), (char)(arrayOfChar[26] ^ 0xFA), (char)('㽗' / arrayOfChar[27]) });
  }
  
  public static String B()
  {
    char[] arrayOfChar = new char[17];
    arrayOfChar[0] = ((char)'ý');
    arrayOfChar[1] = ((char)'ô');
    arrayOfChar[2] = ((char)'');
    arrayOfChar[3] = ((char)'ë');
    arrayOfChar[4] = ((char)'');
    arrayOfChar[5] = ((char)'Ø');
    arrayOfChar[6] = ((char)'×');
    arrayOfChar[7] = ((char)'');
    arrayOfChar[8] = ((char)'');
    arrayOfChar[9] = ((char)'ä');
    arrayOfChar[10] = ((char)'­');
    arrayOfChar[11] = ((char)'È');
    arrayOfChar[12] = ((char)'');
    arrayOfChar[13] = ((char)'');
    arrayOfChar[14] = ((char)'Ç');
    arrayOfChar[15] = ((char)'²');
    arrayOfChar[16] = ((char)' ');
    return String.valueOf(new char[] { (char)('檼' / arrayOfChar[0]), (char)(arrayOfChar[1] ^ 0x95), (char)('䐙' / arrayOfChar[2]), (char)(-arrayOfChar[3] + 345), (char)(-arrayOfChar[4] + 243), (char)(-arrayOfChar[5] + 320), (char)(arrayOfChar[6] ^ 0xB2), (char)(arrayOfChar[7] ^ 0xF0), (char)(-arrayOfChar[8] + 219), (char)('彌' / arrayOfChar[9]), (char)(-arrayOfChar[10] + 276), (char)('㳰' / arrayOfChar[11]), (char)(arrayOfChar[12] ^ 0xF8), (char)('㤎' / arrayOfChar[13]), (char)(arrayOfChar[14] ^ 0xA2), (char)(arrayOfChar[15] ^ 0x8F), (char)(-arrayOfChar[16] + 221) });
  }
  
  public static String C()
  {
    char[] arrayOfChar = new char[10];
    arrayOfChar[0] = ((char)'ä');
    arrayOfChar[1] = ((char)'ò');
    arrayOfChar[2] = ((char)'¨');
    arrayOfChar[3] = ((char)'Æ');
    arrayOfChar[4] = ((char)'Å');
    arrayOfChar[5] = ((char)'ê');
    arrayOfChar[6] = ((char)'¼');
    arrayOfChar[7] = ((char)'Ê');
    arrayOfChar[8] = ((char)'ñ');
    arrayOfChar[9] = ((char)'±');
    return String.valueOf(new char[] { (char)(arrayOfChar[0] ^ 0x87), (char)(arrayOfChar[1] ^ 0x9D), (char)(0xC6 ^ arrayOfChar[2]), (char)(arrayOfChar[3] ^ 0xB2), (char)(-arrayOfChar[4] + 298), (char)('撌' / arrayOfChar[5]), (char)(-arrayOfChar[6] + 304), (char)('ⷄ' / arrayOfChar[7]), (char)(arrayOfChar[8] ^ 0xDE), (char)('ⁿ' / arrayOfChar[9]) });
  }
  
  public static String D()
  {
    char[] arrayOfChar = new char[31];
    arrayOfChar[0] = ((char)'¢');
    arrayOfChar[1] = ((char)'ô');
    arrayOfChar[2] = ((char)'ï');
    arrayOfChar[3] = ((char)'ñ');
    arrayOfChar[4] = ((char)'¸');
    arrayOfChar[5] = ((char)'ã');
    arrayOfChar[6] = ((char)'');
    arrayOfChar[7] = ((char)'¤');
    arrayOfChar[8] = ((char)'Ý');
    arrayOfChar[9] = ((char)'');
    arrayOfChar[10] = ((char)'');
    arrayOfChar[11] = ((char)'Ú');
    arrayOfChar[12] = ((char)'´');
    arrayOfChar[13] = ((char)'Þ');
    arrayOfChar[14] = ((char)'ø');
    int i = (char)127;
    arrayOfChar[15] = i;
    arrayOfChar[16] = ((char)'Ì');
    arrayOfChar[17] = ((char)'Ë');
    arrayOfChar[18] = ((char)'');
    arrayOfChar[19] = ((char)'ÿ');
    arrayOfChar[20] = ((char)'À');
    arrayOfChar[21] = ((char)'');
    arrayOfChar[22] = ((char)'');
    arrayOfChar[23] = ((char)'©');
    arrayOfChar[24] = ((char)' ');
    arrayOfChar[25] = ((char)'Î');
    int j = (char)'ª';
    arrayOfChar[26] = j;
    arrayOfChar[27] = i;
    arrayOfChar[28] = ((char)'¯');
    arrayOfChar[29] = j;
    arrayOfChar[30] = ((char)'');
    return String.valueOf(new char[] { (char)(arrayOfChar[0] ^ 0x8C), (char)(arrayOfChar[1] ^ 0x87), (char)(-arrayOfChar[2] + 340), (char)('洴' / arrayOfChar[3]), (char)(-arrayOfChar[4] + 300), (char)('崛' / arrayOfChar[5]), (char)(-arrayOfChar[6] + 251), (char)(arrayOfChar[7] ^ 0xC3), (char)('捇' / arrayOfChar[8]), (char)(arrayOfChar[9] ^ 0xB0), (char)('㛼' / arrayOfChar[10]), (char)('劚' / arrayOfChar[11]), (char)('勸' / arrayOfChar[12]), (char)(arrayOfChar[13] ^ 0xB1), (char)('湰' / arrayOfChar[14]), (char)(-arrayOfChar[15] + 232), (char)(arrayOfChar[16] ^ 0xB8), (char)(arrayOfChar[17] ^ 0xAE), (char)(arrayOfChar[18] ^ 0xE8), (char)(arrayOfChar[19] ^ 0xC0), (char)(-arrayOfChar[20] + 302), (char)(-arrayOfChar[21] + 241), (char)(arrayOfChar[22] ^ 0xEA), (char)(-arrayOfChar[23] + 274), (char)('㿀' / arrayOfChar[24]), (char)(-arrayOfChar[25] + 327), (char)(-arrayOfChar[26] + 231), (char)(-arrayOfChar[27] + 243), (char)('䷮' / arrayOfChar[28]), (char)('䶲' / arrayOfChar[29]), (char)('㑹' / arrayOfChar[30]) });
  }
  
  public static String E()
  {
    char[] arrayOfChar = new char[7];
    arrayOfChar[0] = ((char)'');
    arrayOfChar[1] = ((char)'Í');
    arrayOfChar[2] = ((char)'þ');
    arrayOfChar[3] = ((char)'â');
    arrayOfChar[4] = ((char)'');
    arrayOfChar[5] = ((char)'Î');
    arrayOfChar[6] = ((char)'À');
    return String.valueOf(new char[] { (char)('䌐' / arrayOfChar[0]), (char)(arrayOfChar[1] ^ 0xA4), (char)('猘' / arrayOfChar[2]), (char)('彘' / arrayOfChar[3]), (char)(-arrayOfChar[4] + 231), (char)(-arrayOfChar[5] + 267), (char)('⽀' / arrayOfChar[6]) });
  }
  
  public static String F()
  {
    char[] arrayOfChar = new char[20];
    arrayOfChar[0] = ((char)'¢');
    arrayOfChar[1] = ((char)'À');
    arrayOfChar[2] = ((char)'â');
    int i = (char)'ÿ';
    arrayOfChar[3] = i;
    arrayOfChar[4] = ((char)'¿');
    arrayOfChar[5] = ((char)'Ù');
    int j = (char)'Ý';
    arrayOfChar[6] = j;
    arrayOfChar[7] = ((char)'');
    arrayOfChar[8] = ((char)'î');
    arrayOfChar[9] = ((char)'Â');
    arrayOfChar[10] = ((char)'È');
    int k = (char)'ì';
    arrayOfChar[11] = k;
    arrayOfChar[12] = ((char)'·');
    arrayOfChar[13] = i;
    arrayOfChar[14] = ((char)'ù');
    arrayOfChar[15] = ((char)'Ö');
    arrayOfChar[16] = ((char)'Ò');
    arrayOfChar[17] = j;
    arrayOfChar[18] = ((char)'Ê');
    arrayOfChar[19] = k;
    return String.valueOf(new char[] { (char)(-arrayOfChar[0] + 266), (char)(arrayOfChar[1] ^ 0xA1), (char)('斆' / arrayOfChar[2]), (char)('劭' / arrayOfChar[3]), (char)('䶘' / arrayOfChar[4]), (char)('刹' / arrayOfChar[5]), (char)('扪' / arrayOfChar[6]), (char)('䠌' / arrayOfChar[7]), (char)(-arrayOfChar[8] + 337), (char)('墪' / arrayOfChar[9]), (char)('媠' / arrayOfChar[10]), (char)(-arrayOfChar[11] + 286), (char)('ᛠ' / arrayOfChar[12]), (char)('㳃' / arrayOfChar[13]), (char)(arrayOfChar[14] ^ 0xC4), (char)(-arrayOfChar[15] + 246), (char)(-arrayOfChar[16] + 326), (char)('扪' / arrayOfChar[17]), (char)(arrayOfChar[18] ^ 0xBF), (char)(arrayOfChar[19] ^ 0x89) });
  }
  
  public static String G()
  {
    char[] arrayOfChar = new char[44];
    arrayOfChar[0] = ((char)'');
    arrayOfChar[1] = ((char)'');
    arrayOfChar[2] = ((char)'');
    int i = (char)'¦';
    arrayOfChar[3] = i;
    arrayOfChar[4] = ((char)'Ò');
    arrayOfChar[5] = ((char)'ô');
    int j = (char)'Ì';
    arrayOfChar[6] = j;
    arrayOfChar[7] = ((char)'');
    arrayOfChar[8] = ((char)'½');
    arrayOfChar[9] = ((char)'');
    arrayOfChar[10] = ((char)'è');
    int k = (char)'';
    arrayOfChar[11] = k;
    arrayOfChar[12] = ((char)'');
    arrayOfChar[13] = ((char)'Ö');
    int m = (char)127;
    arrayOfChar[14] = m;
    arrayOfChar[15] = ((char)'');
    arrayOfChar[16] = ((char)'');
    arrayOfChar[17] = ((char)'È');
    arrayOfChar[18] = ((char)'ß');
    arrayOfChar[19] = ((char)'ê');
    arrayOfChar[20] = ((char)'Ç');
    arrayOfChar[21] = m;
    arrayOfChar[22] = j;
    arrayOfChar[23] = ((char)'Ä');
    arrayOfChar[24] = ((char)'í');
    arrayOfChar[25] = k;
    arrayOfChar[26] = ((char)'');
    arrayOfChar[27] = ((char)'');
    arrayOfChar[28] = ((char)'Ê');
    j = (char)'Å';
    arrayOfChar[29] = j;
    arrayOfChar[30] = ((char)'æ');
    arrayOfChar[31] = i;
    arrayOfChar[32] = ((char)'¥');
    arrayOfChar[33] = ((char)'£');
    arrayOfChar[34] = ((char)'ó');
    arrayOfChar[35] = ((char)'î');
    arrayOfChar[36] = ((char)'¤');
    arrayOfChar[37] = ((char)'®');
    arrayOfChar[38] = ((char)'Ë');
    arrayOfChar[39] = ((char)'Ã');
    arrayOfChar[40] = ((char)'');
    arrayOfChar[41] = ((char)'µ');
    arrayOfChar[42] = j;
    arrayOfChar[43] = ((char)'ï');
    return String.valueOf(new char[] { (char)(-arrayOfChar[0] + 242), (char)('㦫' / arrayOfChar[1]), (char)(-arrayOfChar[2] + 246), (char)(-arrayOfChar[3] + 212), (char)(-arrayOfChar[4] + 307), (char)('棘' / arrayOfChar[5]), (char)(arrayOfChar[6] ^ 0xA8), (char)(arrayOfChar[7] ^ 0xF9), (char)('凳' / arrayOfChar[8]), (char)('㓩' / arrayOfChar[9]), (char)('媠' / arrayOfChar[10]), (char)(arrayOfChar[11] ^ 0xBC), (char)(arrayOfChar[12] ^ 0xE6), (char)(arrayOfChar[13] ^ 0xB7), (char)(arrayOfChar[14] ^ 0xA), (char)('䀆' / arrayOfChar[15]), (char)('㌌' / arrayOfChar[16]), (char)('兀' / arrayOfChar[17]), (char)('埻' / arrayOfChar[18]), (char)(arrayOfChar[19] ^ 0x98), (char)(arrayOfChar[20] ^ 0xE9), (char)(arrayOfChar[21] ^ 0x1E), (char)(arrayOfChar[22] ^ 0xAF), (char)(arrayOfChar[23] ^ 0xB0), (char)(-arrayOfChar[24] + 342), (char)(-arrayOfChar[25] + 257), (char)('䆾' / arrayOfChar[26]), (char)(-arrayOfChar[27] + 191), (char)(arrayOfChar[28] ^ 0x83), (char)(-arrayOfChar[29] + 275), (char)('䪒' / arrayOfChar[30]), (char)(-arrayOfChar[31] + 250), (char)(-arrayOfChar[32] + 230), (char)('つ' / arrayOfChar[33]), (char)(arrayOfChar[34] ^ 0xBF), (char)('塒' / arrayOfChar[35]), (char)(arrayOfChar[36] ^ 0xF7), (char)('ヰ' / arrayOfChar[37]), (char)(-arrayOfChar[38] + 282), (char)(arrayOfChar[39] ^ 0x91), (char)(-arrayOfChar[40] + 224), (char)(arrayOfChar[41] ^ 0xF6), (char)(-arrayOfChar[42] + 282), (char)(arrayOfChar[43] ^ 0xBB) });
  }
  
  public static String H()
  {
    char[] arrayOfChar = new char[36];
    arrayOfChar[0] = ((char)'Ø');
    arrayOfChar[1] = ((char)'');
    arrayOfChar[2] = ((char)'½');
    arrayOfChar[3] = ((char)'');
    arrayOfChar[4] = ((char)'ß');
    arrayOfChar[5] = ((char)'³');
    arrayOfChar[6] = ((char)'');
    arrayOfChar[7] = ((char)'¢');
    arrayOfChar[8] = ((char)'');
    arrayOfChar[9] = ((char)'');
    arrayOfChar[10] = ((char)'¿');
    arrayOfChar[11] = ((char)'õ');
    arrayOfChar[12] = ((char)'');
    arrayOfChar[13] = ((char)'¾');
    arrayOfChar[14] = ((char)'¶');
    arrayOfChar[15] = ((char)'');
    arrayOfChar[16] = ((char)'Ã');
    arrayOfChar[17] = ((char)'¥');
    arrayOfChar[18] = ((char)'');
    arrayOfChar[19] = ((char)'²');
    arrayOfChar[20] = ((char)'Þ');
    arrayOfChar[21] = ((char)'');
    arrayOfChar[22] = ((char)'Ô');
    arrayOfChar[23] = ((char)'¤');
    arrayOfChar[24] = ((char)'÷');
    arrayOfChar[25] = ((char)'ç');
    arrayOfChar[26] = ((char)'');
    int i = (char)'Õ';
    arrayOfChar[27] = i;
    arrayOfChar[28] = ((char)'ñ');
    arrayOfChar[29] = ((char)'');
    arrayOfChar[30] = ((char)'×');
    arrayOfChar[31] = i;
    i = (char)'ª';
    arrayOfChar[32] = i;
    arrayOfChar[33] = i;
    i = (char)'«';
    arrayOfChar[34] = i;
    arrayOfChar[35] = i;
    return String.valueOf(new char[] { (char)(-arrayOfChar[0] + 313), (char)(-arrayOfChar[1] + 256), (char)('䧔' / arrayOfChar[2]), (char)(arrayOfChar[3] ^ 0xE9), (char)(arrayOfChar[4] ^ 0xB0), (char)(arrayOfChar[5] ^ 0xDA), (char)(arrayOfChar[6] ^ 0xEF), (char)(arrayOfChar[7] ^ 0x8C), (char)(-arrayOfChar[8] + 256), (char)(arrayOfChar[9] ^ 0xF8), (char)('嚌' / arrayOfChar[10]), (char)(arrayOfChar[11] ^ 0x90), (char)('㹎' / arrayOfChar[12]), (char)(arrayOfChar[13] ^ 0xCA), (char)(-arrayOfChar[14] + 228), (char)(arrayOfChar[15] ^ 0xE8), (char)('孨' / arrayOfChar[16]), (char)(-arrayOfChar[17] + 281), (char)(-arrayOfChar[18] + 252), (char)(-arrayOfChar[19] + 275), (char)(arrayOfChar[20] ^ 0xF0), (char)('䈉' / arrayOfChar[21]), (char)(arrayOfChar[22] ^ 0xBC), (char)(arrayOfChar[23] ^ 0xCB), (char)(arrayOfChar[24] ^ 0x85), (char)(-arrayOfChar[25] + 347), (char)(arrayOfChar[26] ^ 0xEF), (char)('慙' / arrayOfChar[27]), (char)(arrayOfChar[28] ^ 0x85), (char)('ᦲ' / arrayOfChar[29]), (char)(arrayOfChar[30] ^ 0x9E), (char)('䃦' / arrayOfChar[31]), (char)('㟈' / arrayOfChar[32]), (char)(-arrayOfChar[33] + 239), (char)(arrayOfChar[34] ^ 0xE5), (char)(-arrayOfChar[35] + 255) });
  }
  
  public static String I()
  {
    char[] arrayOfChar = new char[34];
    arrayOfChar[0] = ((char)'Â');
    arrayOfChar[1] = ((char)'');
    arrayOfChar[2] = ((char)'');
    arrayOfChar[3] = ((char)'');
    arrayOfChar[4] = ((char)'Õ');
    arrayOfChar[5] = ((char)'ñ');
    arrayOfChar[6] = ((char)'');
    arrayOfChar[7] = ((char)'');
    arrayOfChar[8] = ((char)'ý');
    arrayOfChar[9] = ((char)'Ê');
    arrayOfChar[10] = ((char)'Î');
    arrayOfChar[11] = ((char)'Ö');
    arrayOfChar[12] = ((char)'È');
    arrayOfChar[13] = ((char)'ü');
    arrayOfChar[14] = ((char)'²');
    arrayOfChar[15] = ((char)'÷');
    arrayOfChar[16] = ((char)'');
    arrayOfChar[17] = ((char)'');
    arrayOfChar[18] = ((char)'ß');
    arrayOfChar[19] = ((char)'Þ');
    arrayOfChar[20] = ((char)'ç');
    arrayOfChar[21] = ((char)'Å');
    arrayOfChar[22] = ((char)'');
    arrayOfChar[23] = ((char)'Ç');
    arrayOfChar[24] = ((char)'¼');
    arrayOfChar[25] = ((char)'');
    arrayOfChar[26] = ((char)'');
    arrayOfChar[27] = ((char)'');
    arrayOfChar[28] = ((char)'Ù');
    arrayOfChar[29] = ((char)'±');
    arrayOfChar[30] = ((char)'ª');
    arrayOfChar[31] = ((char)'');
    arrayOfChar[32] = ((char)'þ');
    arrayOfChar[33] = ((char)'');
    return String.valueOf(new char[] { (char)(arrayOfChar[0] ^ 0xA3), (char)(-arrayOfChar[1] + 253), (char)('㯄' / arrayOfChar[2]), (char)(arrayOfChar[3] ^ 0xF6), (char)(arrayOfChar[4] ^ 0xBA), (char)(arrayOfChar[5] ^ 0x98), (char)('㵔' / arrayOfChar[6]), (char)(-arrayOfChar[7] + 193), (char)(-arrayOfChar[8] + 358), (char)('囌' / arrayOfChar[9]), (char)(-arrayOfChar[10] + 322), (char)(-arrayOfChar[11] + 315), (char)(-arrayOfChar[12] + 310), (char)('爰' / arrayOfChar[13]), (char)(-arrayOfChar[14] + 224), (char)(arrayOfChar[15] ^ 0x92), (char)('㱸' / arrayOfChar[16]), (char)('䆴' / arrayOfChar[17]), (char)(arrayOfChar[18] ^ 0xAD), (char)(-arrayOfChar[19] + 319), (char)(arrayOfChar[20] ^ 0xC9), (char)('塿' / arrayOfChar[21]), (char)('㽠' / arrayOfChar[22]), (char)('噉' / arrayOfChar[23]), (char)(-arrayOfChar[24] + 302), (char)(-arrayOfChar[25] + 266), (char)(-arrayOfChar[26] + 251), (char)('䐙' / arrayOfChar[27]), (char)(arrayOfChar[28] ^ 0xAD), (char)(arrayOfChar[29] ^ 0x9F), (char)(-arrayOfChar[30] + 248), (char)('▔' / arrayOfChar[31]), (char)(arrayOfChar[32] ^ 0xB3), (char)('␞' / arrayOfChar[33]) });
  }
  
  public static String J()
  {
    char[] arrayOfChar = new char[9];
    arrayOfChar[0] = ((char)'');
    arrayOfChar[1] = ((char)'£');
    arrayOfChar[2] = ((char)'¨');
    int i = (char)'';
    arrayOfChar[3] = i;
    arrayOfChar[4] = ((char)'Í');
    arrayOfChar[5] = ((char)'');
    arrayOfChar[6] = i;
    arrayOfChar[7] = ((char)'É');
    arrayOfChar[8] = ((char)'ñ');
    return String.valueOf(new char[] { (char)(arrayOfChar[0] ^ 0xF4), (char)('䩿' / arrayOfChar[1]), (char)(-arrayOfChar[2] + 280), (char)(arrayOfChar[3] ^ 0xFB), (char)(-arrayOfChar[4] + 310), (char)(-arrayOfChar[5] + 229), (char)(arrayOfChar[6] ^ 0xF6), (char)(-arrayOfChar[7] + 317), (char)(-arrayOfChar[8] + 342) });
  }
  
  public static String K()
  {
    char[] arrayOfChar = new char[43];
    arrayOfChar[0] = ((char)'Ã');
    arrayOfChar[1] = ((char)'Ý');
    arrayOfChar[2] = ((char)'');
    int i = (char)'Þ';
    arrayOfChar[3] = i;
    arrayOfChar[4] = ((char)'ã');
    arrayOfChar[5] = ((char)'Å');
    arrayOfChar[6] = ((char)'Ü');
    arrayOfChar[7] = ((char)'Ñ');
    arrayOfChar[8] = ((char)'Ê');
    arrayOfChar[9] = ((char)'Á');
    arrayOfChar[10] = ((char)'¥');
    arrayOfChar[11] = ((char)'Ì');
    arrayOfChar[12] = ((char)'À');
    arrayOfChar[13] = ((char)'é');
    int j = (char)'¶';
    arrayOfChar[14] = j;
    arrayOfChar[15] = ((char)'');
    arrayOfChar[16] = ((char)'ä');
    arrayOfChar[17] = ((char)'');
    arrayOfChar[18] = ((char)'«');
    arrayOfChar[19] = ((char)'ú');
    arrayOfChar[20] = ((char)'à');
    int k = (char)'É';
    arrayOfChar[21] = k;
    arrayOfChar[22] = ((char)'');
    arrayOfChar[23] = k;
    arrayOfChar[24] = ((char)'');
    arrayOfChar[25] = ((char)'è');
    arrayOfChar[26] = ((char)'');
    arrayOfChar[27] = ((char)'ì');
    arrayOfChar[28] = i;
    arrayOfChar[29] = ((char)'Ð');
    arrayOfChar[30] = ((char)'');
    arrayOfChar[31] = ((char)'Í');
    arrayOfChar[32] = ((char)'×');
    arrayOfChar[33] = ((char)'ñ');
    arrayOfChar[34] = ((char)'¯');
    arrayOfChar[35] = ((char)'ë');
    arrayOfChar[36] = j;
    arrayOfChar[37] = ((char)'û');
    arrayOfChar[38] = ((char)'´');
    arrayOfChar[39] = ((char)'­');
    arrayOfChar[40] = ((char)'Ø');
    arrayOfChar[41] = ((char)'Õ');
    arrayOfChar[42] = ((char)'æ');
    return String.valueOf(new char[] { (char)(arrayOfChar[0] ^ 0xA2), (char)(-arrayOfChar[1] + 331), (char)('㚰' / arrayOfChar[2]), (char)('拜' / arrayOfChar[3]), (char)('扭' / arrayOfChar[4]), (char)(arrayOfChar[5] ^ 0xAC), (char)('嗰' / arrayOfChar[6]), (char)(-arrayOfChar[7] + 255), (char)(arrayOfChar[8] ^ 0xA3), (char)(-arrayOfChar[9] + 303), (char)(-arrayOfChar[10] + 281), (char)('偼' / arrayOfChar[11]), (char)(arrayOfChar[12] ^ 0xAE), (char)(-arrayOfChar[13] + 349), (char)(-arrayOfChar[14] + 228), (char)(arrayOfChar[15] ^ 0xF1), (char)('櫠' / arrayOfChar[16]), (char)(-arrayOfChar[17] + 271), (char)(arrayOfChar[18] ^ 0xD9), (char)('庺' / arrayOfChar[19]), (char)(-arrayOfChar[20] + 270), (char)(arrayOfChar[21] ^ 0xBA), (char)(-arrayOfChar[22] + 249), (char)('圧' / arrayOfChar[23]), (char)(arrayOfChar[24] ^ 0xFF), (char)(-arrayOfChar[25] + 348), (char)(arrayOfChar[26] ^ 0xF4), (char)('毜' / arrayOfChar[27]), (char)('撘' / arrayOfChar[28]), (char)(-arrayOfChar[29] + 254), (char)('➣' / arrayOfChar[30]), (char)(arrayOfChar[31] ^ 0x8E), (char)('䉙' / arrayOfChar[32]), (char)('䥮' / arrayOfChar[33]), (char)('䃱' / arrayOfChar[34]), (char)(-arrayOfChar[35] + 317), (char)('ㄎ' / arrayOfChar[36]), (char)(arrayOfChar[37] ^ 0xA8), (char)('㞌' / arrayOfChar[38]), (char)(-arrayOfChar[39] + 258), (char)(arrayOfChar[40] ^ 0x8A), (char)('㞿' / arrayOfChar[41]), (char)(-arrayOfChar[42] + 299) });
  }
  
  public static String L()
  {
    char[] arrayOfChar = new char[25];
    arrayOfChar[0] = ((char)'');
    arrayOfChar[1] = ((char)'â');
    arrayOfChar[2] = ((char)'ø');
    int i = (char)'';
    arrayOfChar[3] = i;
    arrayOfChar[4] = ((char)'Ú');
    arrayOfChar[5] = ((char)'ª');
    arrayOfChar[6] = ((char)'ð');
    arrayOfChar[7] = ((char)'ç');
    arrayOfChar[8] = ((char)'¬');
    arrayOfChar[9] = ((char)'Õ');
    arrayOfChar[10] = ((char)'');
    int j = (char)'ú';
    arrayOfChar[11] = j;
    arrayOfChar[12] = ((char)'ÿ');
    arrayOfChar[13] = ((char)'');
    arrayOfChar[14] = ((char)'³');
    arrayOfChar[15] = ((char)'Ô');
    arrayOfChar[16] = ((char)'ß');
    arrayOfChar[17] = ((char)'');
    arrayOfChar[18] = ((char)'È');
    arrayOfChar[19] = ((char)'æ');
    arrayOfChar[20] = ((char)'´');
    arrayOfChar[21] = i;
    arrayOfChar[22] = ((char)'');
    arrayOfChar[23] = ((char)'¥');
    arrayOfChar[24] = j;
    return String.valueOf(new char[] { (char)('ᰈ' / arrayOfChar[0]), (char)('└' / arrayOfChar[1]), (char)(arrayOfChar[2] ^ 0x94), (char)(arrayOfChar[3] ^ 0xFA), (char)(arrayOfChar[4] ^ 0xAF), (char)('䤌' / arrayOfChar[5]), (char)('峐' / arrayOfChar[6]), (char)(-arrayOfChar[7] + 335), (char)(-arrayOfChar[8] + 273), (char)(arrayOfChar[9] ^ 0xA7), (char)(-arrayOfChar[10] + 195), (char)(-arrayOfChar[11] + 292), (char)(arrayOfChar[12] ^ 0xAD), (char)(-arrayOfChar[13] + 208), (char)('⵳' / arrayOfChar[14]), (char)('㡐' / arrayOfChar[15]), (char)('勁' / arrayOfChar[16]), (char)(-arrayOfChar[17] + 231), (char)('㗨' / arrayOfChar[18]), (char)('䭸' / arrayOfChar[19]), (char)(arrayOfChar[20] ^ 0xE0), (char)('ⰳ' / arrayOfChar[21]), (char)(-arrayOfChar[22] + 229), (char)(arrayOfChar[23] ^ 0xE2), (char)('儎' / arrayOfChar[24]) });
  }
  
  public static String M()
  {
    char[] arrayOfChar = new char[26];
    arrayOfChar[0] = ((char)'à');
    arrayOfChar[1] = ((char)'ñ');
    arrayOfChar[2] = ((char)'¢');
    arrayOfChar[3] = ((char)'¤');
    arrayOfChar[4] = ((char)'Ù');
    arrayOfChar[5] = ((char)'');
    arrayOfChar[6] = ((char)'ë');
    arrayOfChar[7] = ((char)'æ');
    arrayOfChar[8] = ((char)'«');
    arrayOfChar[9] = ((char)'');
    arrayOfChar[10] = ((char)'ö');
    arrayOfChar[11] = ((char)'');
    arrayOfChar[12] = ((char)'¹');
    arrayOfChar[13] = ((char)'â');
    arrayOfChar[14] = ((char)'­');
    arrayOfChar[15] = ((char)127);
    int i = (char)'±';
    arrayOfChar[16] = i;
    arrayOfChar[17] = ((char)'Ï');
    arrayOfChar[18] = i;
    arrayOfChar[19] = ((char)'Û');
    arrayOfChar[20] = ((char)'õ');
    arrayOfChar[21] = ((char)'¸');
    arrayOfChar[22] = ((char)'ä');
    arrayOfChar[23] = ((char)'ç');
    arrayOfChar[24] = ((char)'ÿ');
    arrayOfChar[25] = ((char)'');
    return String.valueOf(new char[] { (char)('⡀' / arrayOfChar[0]), (char)('➊' / arrayOfChar[1]), (char)('䑘' / arrayOfChar[2]), (char)(arrayOfChar[3] ^ 0xC5), (char)('挭' / arrayOfChar[4]), (char)('㝮' / arrayOfChar[5]), (char)('嫡' / arrayOfChar[6]), (char)(arrayOfChar[7] ^ 0x8E), (char)(arrayOfChar[8] ^ 0xCE), (char)('䐢' / arrayOfChar[9]), (char)('ⰴ' / arrayOfChar[10]), (char)('ᡈ' / arrayOfChar[11]), (char)('㻟' / arrayOfChar[12]), (char)('䡤' / arrayOfChar[13]), (char)(-arrayOfChar[14] + 246), (char)('⦬' / arrayOfChar[15]), (char)(arrayOfChar[16] ^ 0xF4), (char)(arrayOfChar[17] ^ 0x90), (char)('㥣' / arrayOfChar[18]), (char)(arrayOfChar[19] ^ 0x9E), (char)('偤' / arrayOfChar[20]), (char)('㱠' / arrayOfChar[21]), (char)(-arrayOfChar[22] + 301), (char)(arrayOfChar[23] ^ 0xA9), (char)('䚹' / arrayOfChar[24]), (char)('⩹' / arrayOfChar[25]) });
  }
  
  public static String N()
  {
    char[] arrayOfChar = new char[61];
    arrayOfChar[0] = ((char)'');
    int i = (char)'';
    arrayOfChar[1] = i;
    arrayOfChar[2] = ((char)'º');
    int j = (char)'Ä';
    arrayOfChar[3] = j;
    arrayOfChar[4] = ((char)'¿');
    arrayOfChar[5] = ((char)'');
    arrayOfChar[6] = i;
    arrayOfChar[7] = ((char)'¤');
    arrayOfChar[8] = ((char)'');
    arrayOfChar[9] = ((char)'Ë');
    arrayOfChar[10] = j;
    arrayOfChar[11] = ((char)'Ã');
    i = (char)'Â';
    arrayOfChar[12] = i;
    arrayOfChar[13] = ((char)'Ô');
    j = (char)'Ù';
    arrayOfChar[14] = j;
    int k = (char)'';
    arrayOfChar[15] = k;
    int m = (char)'';
    arrayOfChar[16] = m;
    int n = (char)'';
    arrayOfChar[17] = n;
    int i1 = (char)'Õ';
    arrayOfChar[18] = i1;
    arrayOfChar[19] = ((char)'·');
    arrayOfChar[20] = ((char)'');
    arrayOfChar[21] = ((char)'¥');
    arrayOfChar[22] = ((char)'');
    arrayOfChar[23] = ((char)'²');
    arrayOfChar[24] = ((char)'');
    arrayOfChar[25] = ((char)'');
    arrayOfChar[26] = i1;
    arrayOfChar[27] = ((char)' ');
    arrayOfChar[28] = m;
    i1 = (char)'¼';
    arrayOfChar[29] = i1;
    arrayOfChar[30] = ((char)'Ê');
    arrayOfChar[31] = ((char)'');
    arrayOfChar[32] = ((char)'è');
    arrayOfChar[33] = ((char)'');
    arrayOfChar[34] = i1;
    arrayOfChar[35] = ((char)'Ñ');
    arrayOfChar[36] = ((char)'ë');
    arrayOfChar[37] = ((char)'ê');
    arrayOfChar[38] = ((char)'');
    arrayOfChar[39] = ((char)'');
    arrayOfChar[40] = ((char)'þ');
    arrayOfChar[41] = i;
    arrayOfChar[42] = m;
    arrayOfChar[43] = ((char)'Ð');
    arrayOfChar[44] = ((char)'ô');
    arrayOfChar[45] = ((char)'³');
    arrayOfChar[46] = ((char)'');
    arrayOfChar[47] = ((char)'®');
    arrayOfChar[48] = ((char)'Ç');
    arrayOfChar[49] = ((char)'ç');
    arrayOfChar[50] = i;
    arrayOfChar[51] = ((char)'');
    arrayOfChar[52] = n;
    arrayOfChar[53] = ((char)'ò');
    arrayOfChar[54] = ((char)'');
    arrayOfChar[55] = k;
    arrayOfChar[56] = ((char)'');
    arrayOfChar[57] = ((char)'ù');
    arrayOfChar[58] = ((char)'ð');
    arrayOfChar[59] = j;
    arrayOfChar[60] = ((char)'Å');
    return String.valueOf(new char[] { (char)('㣙' / arrayOfChar[0]), (char)('䀬' / arrayOfChar[1]), (char)('俬' / arrayOfChar[2]), (char)(-arrayOfChar[3] + 312), (char)(-arrayOfChar[4] + 292), (char)(arrayOfChar[5] ^ 0xF5), (char)('䌐' / arrayOfChar[6]), (char)('┨' / arrayOfChar[7]), (char)('ᨒ' / arrayOfChar[8]), (char)('╅' / arrayOfChar[9]), (char)(-arrayOfChar[10] + 295), (char)('咍' / arrayOfChar[11]), (char)(arrayOfChar[12] ^ 0xAF), (char)(-arrayOfChar[13] + 258), (char)('刹' / arrayOfChar[14]), (char)(-arrayOfChar[15] + 261), (char)(-arrayOfChar[16] + 246), (char)(-arrayOfChar[17] + 259), (char)(arrayOfChar[18] ^ 0xBA), (char)(-arrayOfChar[19] + 288), (char)(arrayOfChar[20] ^ 0xFC), (char)('ᶦ' / arrayOfChar[21]), (char)('㣴' / arrayOfChar[22]), (char)(arrayOfChar[23] ^ 0xD3), (char)('㯟' / arrayOfChar[24]), (char)('㰨' / arrayOfChar[25]), (char)('剟' / arrayOfChar[26]), (char)(arrayOfChar[27] ^ 0xC8), (char)(-arrayOfChar[28] + 247), (char)(arrayOfChar[29] ^ 0xCE), (char)('⑌' / arrayOfChar[30]), (char)('䍢' / arrayOfChar[31]), (char)('守' / arrayOfChar[32]), (char)('㫨' / arrayOfChar[33]), (char)(arrayOfChar[34] ^ 0xC8), (char)('喹' / arrayOfChar[35]), (char)('擺' / arrayOfChar[36]), (char)(-arrayOfChar[37] + 337), (char)('㮿' / arrayOfChar[38]), (char)(-arrayOfChar[39] + 206), (char)(arrayOfChar[40] ^ 0x98), (char)('䦂' / arrayOfChar[41]), (char)('䍌' / arrayOfChar[42]), (char)('娰' / arrayOfChar[43]), (char)(arrayOfChar[44] ^ 0x86), (char)(arrayOfChar[45] ^ 0xDA), (char)(-arrayOfChar[46] + 274), (char)(-arrayOfChar[47] + 275), (char)('奥' / arrayOfChar[48]), (char)(arrayOfChar[49] ^ 0xD8), (char)('卜' / arrayOfChar[50]), (char)(-arrayOfChar[51] + 243), (char)(-arrayOfChar[52] + 261), (char)('捂' / arrayOfChar[53]), (char)(arrayOfChar[54] ^ 0xFA), (char)(arrayOfChar[55] ^ 0xEE), (char)('₥' / arrayOfChar[56]), (char)('烔' / arrayOfChar[57]), (char)(arrayOfChar[58] ^ 0x82), (char)(-arrayOfChar[59] + 334), (char)('䶹' / arrayOfChar[60]) });
  }
  
  public static String O()
  {
    char[] arrayOfChar = new char[7];
    arrayOfChar[0] = ((char)'æ');
    int i = (char)'±';
    arrayOfChar[1] = i;
    arrayOfChar[2] = ((char)'');
    arrayOfChar[3] = ((char)'ó');
    arrayOfChar[4] = i;
    arrayOfChar[5] = ((char)'Ç');
    arrayOfChar[6] = ((char)'');
    return String.valueOf(new char[] { (char)(-arrayOfChar[0] + 346), (char)(arrayOfChar[1] ^ 0xD8), (char)(arrayOfChar[2] ^ 0xEE), (char)(-arrayOfChar[3] + 351), (char)(-arrayOfChar[4] + 278), (char)(arrayOfChar[5] ^ 0xFA), (char)('᾿' / arrayOfChar[6]) });
  }
  
  public static String P()
  {
    char[] arrayOfChar = new char[41];
    int j = (char)'';
    arrayOfChar[0] = j;
    arrayOfChar[1] = ((char)'ï');
    arrayOfChar[2] = ((char)'Ö');
    int k = (char)'';
    arrayOfChar[3] = k;
    arrayOfChar[4] = ((char)'µ');
    int i = (char)'«';
    arrayOfChar[5] = i;
    arrayOfChar[6] = ((char)'Æ');
    arrayOfChar[7] = k;
    arrayOfChar[8] = ((char)'ø');
    arrayOfChar[9] = ((char)'ö');
    arrayOfChar[10] = ((char)'');
    arrayOfChar[11] = ((char)'ç');
    arrayOfChar[12] = j;
    arrayOfChar[13] = ((char)'í');
    arrayOfChar[14] = ((char)'ð');
    arrayOfChar[15] = ((char)'¿');
    arrayOfChar[16] = ((char)'Ó');
    arrayOfChar[17] = ((char)'Ú');
    arrayOfChar[18] = ((char)' ');
    arrayOfChar[19] = ((char)'á');
    arrayOfChar[20] = ((char)'¦');
    arrayOfChar[21] = ((char)'Ñ');
    arrayOfChar[22] = ((char)'©');
    arrayOfChar[23] = ((char)'');
    j = (char)'ó';
    arrayOfChar[24] = j;
    k = (char)'ÿ';
    arrayOfChar[25] = k;
    arrayOfChar[26] = ((char)'');
    arrayOfChar[27] = ((char)'¯');
    arrayOfChar[28] = ((char)'Â');
    arrayOfChar[29] = j;
    arrayOfChar[30] = ((char)'³');
    arrayOfChar[31] = ((char)'ß');
    arrayOfChar[32] = i;
    arrayOfChar[33] = ((char)'¶');
    arrayOfChar[34] = ((char)'');
    arrayOfChar[35] = ((char)'Ù');
    arrayOfChar[36] = ((char)'¼');
    arrayOfChar[37] = k;
    arrayOfChar[38] = ((char)'ò');
    arrayOfChar[39] = ((char)127);
    arrayOfChar[40] = ((char)'»');
    return String.valueOf(new char[] { (char)('㮎' / arrayOfChar[0]), (char)(-arrayOfChar[1] + 350), (char)(-arrayOfChar[2] + 323), (char)(arrayOfChar[3] ^ 0xBA), (char)(-arrayOfChar[4] + 278), (char)('䥺' / arrayOfChar[5]), (char)(-arrayOfChar[6] + 298), (char)('䇨' / arrayOfChar[7]), (char)('殈' / arrayOfChar[8]), (char)(arrayOfChar[9] ^ 0x9F), (char)(-arrayOfChar[10] + 243), (char)(-arrayOfChar[11] + 277), (char)(arrayOfChar[12] ^ 0xF6), (char)('姍' / arrayOfChar[13]), (char)('涰' / arrayOfChar[14]), (char)(-arrayOfChar[15] + 301), (char)('写' / arrayOfChar[16]), (char)('墐' / arrayOfChar[17]), (char)(-arrayOfChar[18] + 261), (char)(arrayOfChar[19] ^ 0x93), (char)('ᷔ' / arrayOfChar[20]), (char)(arrayOfChar[21] ^ 0xA2), (char)('䊭' / arrayOfChar[22]), (char)(-arrayOfChar[23] + 258), (char)('渜' / arrayOfChar[24]), (char)(-arrayOfChar[25] + 360), (char)(-arrayOfChar[26] + 250), (char)(-arrayOfChar[27] + 278), (char)('圦' / arrayOfChar[28]), (char)('㜎' / arrayOfChar[29]), (char)('ᙠ' / arrayOfChar[30]), (char)('嘽' / arrayOfChar[31]), (char)(-arrayOfChar[32] + 282), (char)('匮' / arrayOfChar[33]), (char)(arrayOfChar[34] ^ 0xFC), (char)('扔' / arrayOfChar[35]), (char)('ក' / arrayOfChar[36]), (char)(-arrayOfChar[37] + 316), (char)('Ṁ' / arrayOfChar[38]), (char)(arrayOfChar[39] ^ 0x5A), (char)('䤌' / arrayOfChar[40]) });
  }
  
  public static String Q()
  {
    char[] arrayOfChar = new char[62];
    arrayOfChar[0] = ((char)'');
    int i = (char)'Í';
    arrayOfChar[1] = i;
    arrayOfChar[2] = ((char)'Ü');
    arrayOfChar[3] = ((char)'¯');
    arrayOfChar[4] = ((char)'ä');
    int j = (char)'Î';
    arrayOfChar[5] = j;
    arrayOfChar[6] = j;
    int i1 = (char)'Ç';
    arrayOfChar[7] = i1;
    j = (char)'';
    arrayOfChar[8] = j;
    int m = (char)'µ';
    arrayOfChar[9] = m;
    int k = (char)'À';
    arrayOfChar[10] = k;
    arrayOfChar[11] = ((char)'');
    arrayOfChar[12] = ((char)'ë');
    arrayOfChar[13] = ((char)'á');
    arrayOfChar[14] = ((char)'¡');
    int i2 = (char)'ö';
    arrayOfChar[15] = i2;
    arrayOfChar[16] = ((char)'ß');
    arrayOfChar[17] = m;
    arrayOfChar[18] = ((char)'ñ');
    arrayOfChar[19] = ((char)'Ø');
    m = (char)'ì';
    arrayOfChar[20] = m;
    int n = (char)'©';
    arrayOfChar[21] = n;
    arrayOfChar[22] = ((char)'');
    arrayOfChar[23] = ((char)'æ');
    arrayOfChar[24] = k;
    arrayOfChar[25] = i2;
    arrayOfChar[26] = ((char)'¶');
    i2 = (char)'í';
    arrayOfChar[27] = i2;
    arrayOfChar[28] = i1;
    arrayOfChar[29] = ((char)'¥');
    arrayOfChar[30] = ((char)'Õ');
    arrayOfChar[31] = ((char)127);
    arrayOfChar[32] = ((char)'¿');
    arrayOfChar[33] = ((char)'ô');
    i1 = (char)'²';
    arrayOfChar[34] = i1;
    arrayOfChar[35] = ((char)'Ä');
    arrayOfChar[36] = ((char)'ù');
    int i3 = (char)'';
    arrayOfChar[37] = i3;
    arrayOfChar[38] = ((char)'');
    arrayOfChar[39] = i2;
    arrayOfChar[40] = ((char)'Æ');
    arrayOfChar[41] = ((char)'¸');
    arrayOfChar[42] = ((char)'½');
    arrayOfChar[43] = ((char)'ç');
    i2 = (char)'õ';
    arrayOfChar[44] = i2;
    arrayOfChar[45] = n;
    arrayOfChar[46] = ((char)'à');
    arrayOfChar[47] = m;
    arrayOfChar[48] = i1;
    arrayOfChar[49] = ((char)'¦');
    arrayOfChar[50] = ((char)'«');
    arrayOfChar[51] = ((char)'Å');
    arrayOfChar[52] = i3;
    arrayOfChar[53] = ((char)'»');
    arrayOfChar[54] = k;
    arrayOfChar[55] = i2;
    arrayOfChar[56] = i;
    arrayOfChar[57] = ((char)'');
    arrayOfChar[58] = ((char)'·');
    arrayOfChar[59] = ((char)'Ð');
    arrayOfChar[60] = ((char)'ú');
    arrayOfChar[61] = j;
    return String.valueOf(new char[] { (char)('㨂' / arrayOfChar[0]), (char)(arrayOfChar[1] ^ 0xA2), (char)('庈' / arrayOfChar[2]), (char)(arrayOfChar[3] ^ 0xDB), (char)(-arrayOfChar[4] + 329), (char)(arrayOfChar[5] ^ 0xA0), (char)(-arrayOfChar[6] + 322), (char)('ⴖ' / arrayOfChar[7]), (char)(-arrayOfChar[8] + 175), (char)(arrayOfChar[9] ^ 0x9A), (char)(arrayOfChar[10] ^ 0xA3), (char)(-arrayOfChar[11] + 257), (char)(-arrayOfChar[12] + 344), (char)(arrayOfChar[13] ^ 0xCF), (char)('㴁' / arrayOfChar[14]), (char)('榴' / arrayOfChar[15]), (char)(arrayOfChar[16] ^ 0xBB), (char)(arrayOfChar[17] ^ 0xC7), (char)(-arrayOfChar[18] + 352), (char)('墘' / arrayOfChar[19]), (char)('尰' / arrayOfChar[20]), (char)(arrayOfChar[21] ^ 0x87), (char)('㬐' / arrayOfChar[22]), (char)(-arrayOfChar[23] + 327), (char)(arrayOfChar[24] ^ 0xB5), (char)('榴' / arrayOfChar[25]), (char)(-arrayOfChar[26] + 281), (char)(-arrayOfChar[27] + 341), (char)(-arrayOfChar[28] + 300), (char)(arrayOfChar[29] ^ 0xD7), (char)('⦚' / arrayOfChar[30]), (char)(arrayOfChar[31] ^ 0x51), (char)(-arrayOfChar[32] + 306), (char)(-arrayOfChar[33] + 345), (char)(arrayOfChar[34] ^ 0xC6), (char)(arrayOfChar[35] ^ 0xB0), (char)(arrayOfChar[36] ^ 0x90), (char)(-arrayOfChar[37] + 267), (char)(arrayOfChar[38] ^ 0xEF), (char)(arrayOfChar[39] ^ 0x9E), (char)(arrayOfChar[40] ^ 0xE9), (char)(arrayOfChar[41] ^ 0xDE), (char)(-arrayOfChar[42] + 286), (char)(-arrayOfChar[43] + 349), (char)(-arrayOfChar[44] + 356), (char)(arrayOfChar[45] ^ 0xDB), (char)(-arrayOfChar[46] + 329), (char)('櫰' / arrayOfChar[47]), (char)('䘺' / arrayOfChar[48]), (char)(arrayOfChar[49] ^ 0xD5), (char)(-arrayOfChar[50] + 234), (char)(arrayOfChar[51] ^ 0xAB), (char)(arrayOfChar[52] ^ 0xF2), (char)(arrayOfChar[53] ^ 0xCF), (char)(-arrayOfChar[54] + 297), (char)('憞' / arrayOfChar[55]), (char)(arrayOfChar[56] ^ 0xB4), (char)('┬' / arrayOfChar[57]), (char)('勬' / arrayOfChar[58]), (char)(arrayOfChar[59] ^ 0xA2), (char)(-arrayOfChar[60] + 367), (char)(arrayOfChar[61] ^ 0xE5) });
  }
  
  public static String R()
  {
    char[] arrayOfChar = new char[7];
    arrayOfChar[0] = ((char)'æ');
    arrayOfChar[1] = ((char)'ð');
    arrayOfChar[2] = ((char)'¤');
    arrayOfChar[3] = ((char)'Ü');
    arrayOfChar[4] = ((char)'');
    arrayOfChar[5] = ((char)'');
    arrayOfChar[6] = ((char)'¡');
    return String.valueOf(new char[] { (char)(-arrayOfChar[0] + 346), (char)(arrayOfChar[1] ^ 0x99), (char)(-arrayOfChar[2] + 280), (char)(-arrayOfChar[3] + 328), (char)(arrayOfChar[4] ^ 0xE1), (char)('΅' / arrayOfChar[5]), (char)(-arrayOfChar[6] + 224) });
  }
  
  public static String S()
  {
    char[] arrayOfChar = new char[42];
    arrayOfChar[0] = ((char)'');
    arrayOfChar[1] = ((char)'Ä');
    int n = (char)'Ç';
    arrayOfChar[2] = n;
    arrayOfChar[3] = ((char)'ð');
    int i = (char)'¤';
    arrayOfChar[4] = i;
    int k = (char)'Å';
    arrayOfChar[5] = k;
    arrayOfChar[6] = ((char)'¢');
    int j = (char)'';
    arrayOfChar[7] = j;
    arrayOfChar[8] = k;
    arrayOfChar[9] = ((char)'');
    arrayOfChar[10] = ((char)'');
    arrayOfChar[11] = ((char)'ÿ');
    k = (char)'';
    arrayOfChar[12] = k;
    int m = (char)'÷';
    arrayOfChar[13] = m;
    arrayOfChar[14] = n;
    arrayOfChar[15] = ((char)'');
    arrayOfChar[16] = ((char)'');
    int i1 = (char)'';
    arrayOfChar[17] = i1;
    arrayOfChar[18] = ((char)'¶');
    arrayOfChar[19] = ((char)'þ');
    n = (char)'';
    arrayOfChar[20] = n;
    arrayOfChar[21] = ((char)'²');
    arrayOfChar[22] = ((char)'Ì');
    arrayOfChar[23] = k;
    arrayOfChar[24] = i1;
    arrayOfChar[25] = m;
    arrayOfChar[26] = ((char)'Á');
    arrayOfChar[27] = ((char)'');
    arrayOfChar[28] = ((char)'­');
    arrayOfChar[29] = j;
    j = (char)'';
    arrayOfChar[30] = j;
    arrayOfChar[31] = ((char)'¬');
    arrayOfChar[32] = ((char)'È');
    arrayOfChar[33] = ((char)'');
    arrayOfChar[34] = n;
    arrayOfChar[35] = ((char)'ô');
    arrayOfChar[36] = i;
    arrayOfChar[37] = j;
    arrayOfChar[38] = ((char)'¥');
    arrayOfChar[39] = ((char)'');
    arrayOfChar[40] = ((char)'Þ');
    arrayOfChar[41] = ((char)'');
    return String.valueOf(new char[] { (char)(arrayOfChar[0] ^ 0xF9), (char)(-arrayOfChar[1] + 307), (char)(arrayOfChar[2] ^ 0xAA), (char)('⬠' / arrayOfChar[3]), (char)(-arrayOfChar[4] + 261), (char)('咦' / arrayOfChar[5]), (char)(-arrayOfChar[6] + 262), (char)(arrayOfChar[7] ^ 0xF7), (char)('啫' / arrayOfChar[8]), (char)(-arrayOfChar[9] + 236), (char)(-arrayOfChar[10] + 236), (char)(-arrayOfChar[11] + 301), (char)(arrayOfChar[12] ^ 0xFC), (char)(arrayOfChar[13] ^ 0x96), (char)(arrayOfChar[14] ^ 0xB2), (char)('㴄' / arrayOfChar[15]), (char)(-arrayOfChar[16] + 248), (char)('㵘' / arrayOfChar[17]), (char)(-arrayOfChar[18] + 283), (char)(arrayOfChar[19] ^ 0x8C), (char)(arrayOfChar[20] ^ 0xAE), (char)('ῼ' / arrayOfChar[21]), (char)(arrayOfChar[22] ^ 0xBF), (char)(arrayOfChar[23] ^ 0xF5), (char)(-arrayOfChar[24] + 267), (char)(-arrayOfChar[25] + 363), (char)(-arrayOfChar[26] + 298), (char)('㫞' / arrayOfChar[27]), (char)('䖛' / arrayOfChar[28]), (char)(-arrayOfChar[29] + 248), (char)(-arrayOfChar[30] + 210), (char)(-arrayOfChar[31] + 204), (char)(-arrayOfChar[32] + 299), (char)(arrayOfChar[33] ^ 0xF4), (char)(-arrayOfChar[34] + 273), (char)(-arrayOfChar[35] + 354), (char)(arrayOfChar[36] ^ 0xD0), (char)(arrayOfChar[37] ^ 0xB8), (char)(-arrayOfChar[38] + 226), (char)('Ꭰ' / arrayOfChar[39]), (char)(arrayOfChar[40] ^ 0xFB), (char)(-arrayOfChar[41] + 239) });
  }
  
  public static String T()
  {
    char[] arrayOfChar = new char[68];
    arrayOfChar[0] = ((char)'ê');
    arrayOfChar[1] = ((char)'í');
    arrayOfChar[2] = ((char)'¦');
    int i = (char)'Ú';
    arrayOfChar[3] = i;
    arrayOfChar[4] = ((char)'£');
    arrayOfChar[5] = ((char)'Â');
    int j = (char)'õ';
    arrayOfChar[6] = j;
    int k = (char)'á';
    arrayOfChar[7] = k;
    arrayOfChar[8] = ((char)'Ä');
    arrayOfChar[9] = ((char)'²');
    arrayOfChar[10] = ((char)'â');
    arrayOfChar[11] = ((char)'');
    arrayOfChar[12] = ((char)'Ã');
    arrayOfChar[13] = ((char)'à');
    int m = (char)'Ô';
    arrayOfChar[14] = m;
    int n = (char)'¯';
    arrayOfChar[15] = n;
    arrayOfChar[16] = ((char)'ÿ');
    arrayOfChar[17] = ((char)'');
    arrayOfChar[18] = ((char)'ã');
    int i1 = (char)'';
    arrayOfChar[19] = i1;
    arrayOfChar[20] = ((char)'³');
    arrayOfChar[21] = m;
    arrayOfChar[22] = ((char)'×');
    arrayOfChar[23] = ((char)'ô');
    int i3 = (char)'Õ';
    arrayOfChar[24] = i3;
    arrayOfChar[25] = ((char)'¾');
    int i2 = (char)'¡';
    arrayOfChar[26] = i2;
    arrayOfChar[27] = ((char)'');
    arrayOfChar[28] = ((char)'ó');
    arrayOfChar[29] = i3;
    arrayOfChar[30] = ((char)'ö');
    arrayOfChar[31] = ((char)'');
    arrayOfChar[32] = ((char)'·');
    i3 = (char)'';
    arrayOfChar[33] = i3;
    arrayOfChar[34] = i;
    arrayOfChar[35] = ((char)'ò');
    arrayOfChar[36] = i2;
    arrayOfChar[37] = ((char)'Å');
    arrayOfChar[38] = ((char)'º');
    arrayOfChar[39] = n;
    arrayOfChar[40] = k;
    arrayOfChar[41] = ((char)'À');
    arrayOfChar[42] = ((char)' ');
    arrayOfChar[43] = ((char)'Æ');
    arrayOfChar[44] = i1;
    arrayOfChar[45] = ((char)'¢');
    arrayOfChar[46] = ((char)'ä');
    arrayOfChar[47] = ((char)'ý');
    arrayOfChar[48] = ((char)'ª');
    arrayOfChar[49] = i3;
    arrayOfChar[50] = ((char)'Þ');
    arrayOfChar[51] = ((char)'÷');
    arrayOfChar[52] = ((char)'Ö');
    arrayOfChar[53] = ((char)'');
    arrayOfChar[54] = ((char)'');
    arrayOfChar[55] = ((char)'');
    arrayOfChar[56] = ((char)'ü');
    arrayOfChar[57] = ((char)'È');
    arrayOfChar[58] = ((char)'Î');
    arrayOfChar[59] = ((char)'É');
    arrayOfChar[60] = m;
    arrayOfChar[61] = ((char)'');
    arrayOfChar[62] = i3;
    arrayOfChar[63] = ((char)'');
    arrayOfChar[64] = ((char)'');
    arrayOfChar[65] = ((char)'');
    arrayOfChar[66] = ((char)'»');
    arrayOfChar[67] = j;
    return String.valueOf(new char[] { (char)(-arrayOfChar[0] + 333), (char)(-arrayOfChar[1] + 348), (char)(-arrayOfChar[2] + 276), (char)(arrayOfChar[3] ^ 0xAE), (char)(-arrayOfChar[4] + 264), (char)(-arrayOfChar[5] + 304), (char)('漄' / arrayOfChar[6]), (char)(arrayOfChar[7] ^ 0xDB), (char)('⏼' / arrayOfChar[8]), (char)(-arrayOfChar[9] + 225), (char)(arrayOfChar[10] ^ 0x81), (char)(-arrayOfChar[11] + 263), (char)('匇' / arrayOfChar[12]), (char)(arrayOfChar[13] ^ 0xCE), (char)(-arrayOfChar[14] + 316), (char)('俻' / arrayOfChar[15]), (char)(arrayOfChar[16] ^ 0x9E), (char)(-arrayOfChar[17] + 255), (char)(arrayOfChar[18] ^ 0x86), (char)('㚍' / arrayOfChar[19]), (char)('‪' / arrayOfChar[20]), (char)('偔' / arrayOfChar[21]), (char)(-arrayOfChar[22] + 325), (char)(arrayOfChar[23] ^ 0x90), (char)('廚' / arrayOfChar[24]), (char)(arrayOfChar[25] ^ 0xD1), (char)(arrayOfChar[26] ^ 0xC8), (char)(arrayOfChar[27] ^ 0xF2), (char)('⮪' / arrayOfChar[28]), (char)('姜' / arrayOfChar[29]), (char)(-arrayOfChar[30] + 343), (char)('䝌' / arrayOfChar[31]), (char)(-arrayOfChar[32] + 293), (char)(arrayOfChar[33] ^ 0xE8), (char)('墐' / arrayOfChar[34]), (char)(-arrayOfChar[35] + 343), (char)(-arrayOfChar[36] + 275), (char)('⍦' / arrayOfChar[37]), (char)(arrayOfChar[38] ^ 0xC9), (char)(-arrayOfChar[39] + 276), (char)(-arrayOfChar[40] + 341), (char)('圀' / arrayOfChar[41]), (char)('䆠' / arrayOfChar[42]), (char)(-arrayOfChar[43] + 308), (char)(arrayOfChar[44] ^ 0xE2), (char)(arrayOfChar[45] ^ 0xD1), (char)('⧜' / arrayOfChar[46]), (char)('擎' / arrayOfChar[47]), (char)(arrayOfChar[48] ^ 0xCB), (char)(arrayOfChar[49] ^ 0xFD), (char)('恂' / arrayOfChar[50]), (char)(-arrayOfChar[51] + 361), (char)(-arrayOfChar[52] + 319), (char)(arrayOfChar[53] ^ 0xF3), (char)(arrayOfChar[54] ^ 0xFF), (char)('㫙' / arrayOfChar[55]), (char)('㸄' / arrayOfChar[56]), (char)('嗰' / arrayOfChar[57]), (char)(-arrayOfChar[58] + 317), (char)('嬔' / arrayOfChar[59]), (char)('围' / arrayOfChar[60]), (char)(arrayOfChar[61] ^ 0xF2), (char)('䆳' / arrayOfChar[62]), (char)(arrayOfChar[63] ^ 0xB0), (char)(arrayOfChar[64] ^ 0xED), (char)('㴂' / arrayOfChar[65]), (char)('啷' / arrayOfChar[66]), (char)(-arrayOfChar[67] + 346) });
  }
  
  public static String U()
  {
    char[] arrayOfChar = new char[7];
    arrayOfChar[0] = ((char)'Ï');
    arrayOfChar[1] = ((char)'');
    arrayOfChar[2] = ((char)'ä');
    arrayOfChar[3] = ((char)'»');
    arrayOfChar[4] = ((char)'¬');
    arrayOfChar[5] = ((char)'Ë');
    arrayOfChar[6] = ((char)'±');
    return String.valueOf(new char[] { (char)(0xBB ^ arrayOfChar[0]), (char)(arrayOfChar[1] ^ 0xFC), (char)(arrayOfChar[2] ^ 0x90), (char)(-arrayOfChar[3] + 295), (char)(arrayOfChar[4] ^ 0xC9), (char)(-arrayOfChar[5] + 264), (char)(arrayOfChar[6] ^ 0x8E) });
  }
  
  public static String V()
  {
    char[] arrayOfChar = new char[48];
    int j = (char)'î';
    arrayOfChar[0] = j;
    int i = (char)'';
    arrayOfChar[1] = i;
    arrayOfChar[2] = ((char)'¯');
    arrayOfChar[3] = ((char)'§');
    arrayOfChar[4] = ((char)'ÿ');
    arrayOfChar[5] = ((char)'Í');
    arrayOfChar[6] = ((char)'µ');
    arrayOfChar[7] = ((char)'é');
    arrayOfChar[8] = j;
    arrayOfChar[9] = ((char)'ö');
    arrayOfChar[10] = ((char)'·');
    j = (char)'';
    arrayOfChar[11] = j;
    int k = (char)'Ó';
    arrayOfChar[12] = k;
    arrayOfChar[13] = ((char)'ª');
    arrayOfChar[14] = ((char)'¤');
    arrayOfChar[15] = ((char)'³');
    int m = (char)'À';
    arrayOfChar[16] = m;
    int n = (char)'';
    arrayOfChar[17] = n;
    arrayOfChar[18] = ((char)'Â');
    arrayOfChar[19] = i;
    arrayOfChar[20] = ((char)'¼');
    arrayOfChar[21] = ((char)'ì');
    arrayOfChar[22] = ((char)'°');
    arrayOfChar[23] = ((char)'Õ');
    int i1 = (char)'¥';
    arrayOfChar[24] = i1;
    arrayOfChar[25] = m;
    arrayOfChar[26] = k;
    arrayOfChar[27] = i;
    arrayOfChar[28] = n;
    arrayOfChar[29] = ((char)'ä');
    arrayOfChar[30] = ((char)'È');
    arrayOfChar[31] = ((char)'Ý');
    arrayOfChar[32] = ((char)'÷');
    arrayOfChar[33] = ((char)'ß');
    arrayOfChar[34] = j;
    arrayOfChar[35] = i1;
    arrayOfChar[36] = ((char)'Ä');
    arrayOfChar[37] = ((char)'«');
    arrayOfChar[38] = ((char)'Ö');
    arrayOfChar[39] = ((char)'');
    arrayOfChar[40] = ((char)'ê');
    arrayOfChar[41] = ((char)'Ø');
    arrayOfChar[42] = ((char)'£');
    arrayOfChar[43] = ((char)'ü');
    arrayOfChar[44] = ((char)'¾');
    arrayOfChar[45] = ((char)'Ò');
    arrayOfChar[46] = ((char)'û');
    arrayOfChar[47] = ((char)'');
    return String.valueOf(new char[] { (char)(-arrayOfChar[0] + 337), (char)(arrayOfChar[1] ^ 0xF3), (char)('䪃' / arrayOfChar[2]), (char)(arrayOfChar[3] ^ 0x89), (char)(-arrayOfChar[4] + 359), (char)(arrayOfChar[5] ^ 0xB8), (char)(arrayOfChar[6] ^ 0xD4), (char)(-arrayOfChar[7] + 352), (char)(-arrayOfChar[8] + 339), (char)(-arrayOfChar[9] + 351), (char)(-arrayOfChar[10] + 229), (char)('メ' / arrayOfChar[11]), (char)('媪' / arrayOfChar[12]), (char)('䉨' / arrayOfChar[13]), (char)(-arrayOfChar[14] + 278), (char)('䶝' / arrayOfChar[15]), (char)(-arrayOfChar[16] + 297), (char)(arrayOfChar[17] ^ 0xFD), (char)(-arrayOfChar[18] + 240), (char)(-arrayOfChar[19] + 264), (char)(-arrayOfChar[20] + 285), (char)(-arrayOfChar[21] + 353), (char)(-arrayOfChar[22] + 286), (char)(arrayOfChar[23] ^ 0xB6), (char)(arrayOfChar[24] ^ 0xCD), (char)('䯀' / arrayOfChar[25]), (char)(arrayOfChar[26] ^ 0xA1), (char)(arrayOfChar[27] ^ 0xB2), (char)(arrayOfChar[28] ^ 0xEA), (char)('姴' / arrayOfChar[29]), (char)('媠' / arrayOfChar[30]), (char)(-arrayOfChar[31] + 337), (char)('敏' / arrayOfChar[32]), (char)('忒' / arrayOfChar[33]), (char)(-arrayOfChar[34] + 232), (char)(arrayOfChar[35] ^ 0xD6), (char)(arrayOfChar[36] ^ 0xFE), (char)(arrayOfChar[37] ^ 0x8B), (char)(-arrayOfChar[38] + 313), (char)(-arrayOfChar[39] + 249), (char)(-arrayOfChar[40] + 351), (char)('峐' / arrayOfChar[41]), (char)('䧜' / arrayOfChar[42]), (char)('ᾀ' / arrayOfChar[43]), (char)('ⵆ' / arrayOfChar[44]), (char)(-arrayOfChar[45] + 242), (char)('⑇' / arrayOfChar[46]), (char)(arrayOfChar[47] ^ 0xE2) });
  }
  
  public static String W()
  {
    char[] arrayOfChar = new char[63];
    arrayOfChar[0] = ((char)'');
    arrayOfChar[1] = ((char)'¶');
    int i = (char)'Ó';
    arrayOfChar[2] = i;
    arrayOfChar[3] = ((char)'');
    arrayOfChar[4] = ((char)'ô');
    int k = (char)'ï';
    arrayOfChar[5] = k;
    int j = (char)'¹';
    arrayOfChar[6] = j;
    arrayOfChar[7] = ((char)'â');
    arrayOfChar[8] = ((char)'');
    int m = (char)'';
    arrayOfChar[9] = m;
    arrayOfChar[10] = ((char)'ÿ');
    arrayOfChar[11] = ((char)'Ú');
    arrayOfChar[12] = ((char)'î');
    int n = (char)'á';
    arrayOfChar[13] = n;
    arrayOfChar[14] = j;
    arrayOfChar[15] = k;
    arrayOfChar[16] = n;
    k = (char)'º';
    arrayOfChar[17] = k;
    arrayOfChar[18] = ((char)'¯');
    arrayOfChar[19] = ((char)'Á');
    n = (char)'û';
    arrayOfChar[20] = n;
    arrayOfChar[21] = ((char)'');
    arrayOfChar[22] = ((char)'');
    arrayOfChar[23] = ((char)'Å');
    arrayOfChar[24] = ((char)'í');
    arrayOfChar[25] = ((char)'÷');
    arrayOfChar[26] = ((char)'¥');
    arrayOfChar[27] = ((char)'');
    arrayOfChar[28] = ((char)'ß');
    arrayOfChar[29] = ((char)'');
    arrayOfChar[30] = n;
    arrayOfChar[31] = m;
    arrayOfChar[32] = ((char)'²');
    arrayOfChar[33] = ((char)'Ù');
    arrayOfChar[34] = ((char)'µ');
    m = (char)'ú';
    arrayOfChar[35] = m;
    arrayOfChar[36] = ((char)'¢');
    n = (char)'£';
    arrayOfChar[37] = n;
    arrayOfChar[38] = ((char)'Î');
    int i1 = (char)'Æ';
    arrayOfChar[39] = i1;
    arrayOfChar[40] = ((char)'');
    arrayOfChar[41] = ((char)'Ä');
    arrayOfChar[42] = ((char)'Ï');
    arrayOfChar[43] = i1;
    arrayOfChar[44] = ((char)'¼');
    arrayOfChar[45] = i1;
    arrayOfChar[46] = i;
    arrayOfChar[47] = ((char)'ù');
    arrayOfChar[48] = ((char)'³');
    arrayOfChar[49] = ((char)'ü');
    arrayOfChar[50] = ((char)'Ñ');
    arrayOfChar[51] = ((char)'Ô');
    arrayOfChar[52] = ((char)'æ');
    arrayOfChar[53] = m;
    arrayOfChar[54] = ((char)'ò');
    arrayOfChar[55] = n;
    arrayOfChar[56] = k;
    arrayOfChar[57] = ((char)'Ø');
    arrayOfChar[58] = j;
    arrayOfChar[59] = ((char)'ñ');
    arrayOfChar[60] = ((char)'±');
    arrayOfChar[61] = ((char)'É');
    arrayOfChar[62] = ((char)'');
    return String.valueOf(new char[] { (char)(-arrayOfChar[0] + 241), (char)(-arrayOfChar[1] + 293), (char)('媪' / arrayOfChar[2]), (char)(-arrayOfChar[3] + 266), (char)(-arrayOfChar[4] + 345), (char)(-arrayOfChar[5] + 349), (char)(-arrayOfChar[6] + 301), (char)(-arrayOfChar[7] + 284), (char)('᭛' / arrayOfChar[8]), (char)('Ფ' / arrayOfChar[9]), (char)(-arrayOfChar[10] + 354), (char)(-arrayOfChar[11] + 329), (char)(-arrayOfChar[12] + 347), (char)(-arrayOfChar[13] + 271), (char)('仅' / arrayOfChar[14]), (char)(arrayOfChar[15] ^ 0x86), (char)('曕' / arrayOfChar[16]), (char)(arrayOfChar[17] ^ 0xD3), (char)(arrayOfChar[18] ^ 0x81), (char)(arrayOfChar[19] ^ 0xA9), (char)(arrayOfChar[20] ^ 0x94), (char)('㳣' / arrayOfChar[21]), (char)(-arrayOfChar[22] + 259), (char)(arrayOfChar[23] ^ 0xEB), (char)('揼' / arrayOfChar[24]), (char)('嶗' / arrayOfChar[25]), (char)('䭩' / arrayOfChar[26]), (char)(arrayOfChar[27] ^ 0xFC), (char)(-arrayOfChar[28] + 322), (char)(arrayOfChar[29] ^ 0xF9), (char)(-arrayOfChar[30] + 352), (char)('䕸' / arrayOfChar[31]), (char)(-arrayOfChar[32] + 224), (char)(arrayOfChar[33] ^ 0xAA), (char)(-arrayOfChar[34] + 282), (char)(-arrayOfChar[35] + 366), (char)(arrayOfChar[36] ^ 0xD6), (char)(arrayOfChar[37] ^ 0xCA), (char)('墄' / arrayOfChar[38]), (char)(arrayOfChar[39] ^ 0xA1), (char)('㶋' / arrayOfChar[40]), (char)(-arrayOfChar[41] + 243), (char)(arrayOfChar[42] ^ 0xA9), (char)(arrayOfChar[43] ^ 0xA7), (char)(-arrayOfChar[44] + 306), (char)(-arrayOfChar[45] + 309), (char)(-arrayOfChar[46] + 325), (char)(-arrayOfChar[47] + 354), (char)(-arrayOfChar[48] + 295), (char)('捬' / arrayOfChar[49]), (char)(arrayOfChar[50] ^ 0xA2), (char)(-arrayOfChar[51] + 275), (char)('拔' / arrayOfChar[52]), (char)('汦' / arrayOfChar[53]), (char)(arrayOfChar[54] ^ 0x86), (char)(arrayOfChar[55] ^ 0xCA), (char)(arrayOfChar[56] ^ 0xDC), (char)(-arrayOfChar[57] + 337), (char)('Ⱅ' / arrayOfChar[58]), (char)(arrayOfChar[59] ^ 0x85), (char)('仒' / arrayOfChar[60]), (char)(-arrayOfChar[61] + 318), (char)(arrayOfChar[62] ^ 0xFC) });
  }
  
  public static String X()
  {
    char[] arrayOfChar = new char[7];
    arrayOfChar[0] = ((char)'Å');
    arrayOfChar[1] = ((char)'ï');
    arrayOfChar[2] = ((char)'');
    arrayOfChar[3] = ((char)'ô');
    arrayOfChar[4] = ((char)'Ü');
    arrayOfChar[5] = ((char)'Î');
    arrayOfChar[6] = ((char)'­');
    return String.valueOf(new char[] { (char)(arrayOfChar[0] ^ 0xB1), (char)('戇' / arrayOfChar[1]), (char)(-arrayOfChar[2] + 244), (char)(-arrayOfChar[3] + 352), (char)(arrayOfChar[4] ^ 0xB9), (char)('ㄖ' / arrayOfChar[5]), (char)('⪓' / arrayOfChar[6]) });
  }
  
  public static String Y()
  {
    char[] arrayOfChar = new char[43];
    arrayOfChar[0] = ((char)'Ñ');
    arrayOfChar[1] = ((char)'Ø');
    arrayOfChar[2] = ((char)'õ');
    int i = (char)'';
    arrayOfChar[3] = i;
    arrayOfChar[4] = ((char)'');
    arrayOfChar[5] = ((char)'ï');
    arrayOfChar[6] = ((char)'Ó');
    int j = (char)'´';
    arrayOfChar[7] = j;
    arrayOfChar[8] = ((char)'ü');
    arrayOfChar[9] = ((char)'');
    arrayOfChar[10] = ((char)'Å');
    arrayOfChar[11] = ((char)'³');
    arrayOfChar[12] = ((char)'');
    arrayOfChar[13] = ((char)'é');
    arrayOfChar[14] = ((char)'Ð');
    arrayOfChar[15] = ((char)'');
    arrayOfChar[16] = ((char)'');
    arrayOfChar[17] = ((char)'ä');
    arrayOfChar[18] = ((char)'');
    arrayOfChar[19] = ((char)'·');
    arrayOfChar[20] = ((char)'¢');
    arrayOfChar[21] = ((char)'Ù');
    arrayOfChar[22] = ((char)'Â');
    arrayOfChar[23] = ((char)'¬');
    arrayOfChar[24] = ((char)'');
    arrayOfChar[25] = ((char)'Ú');
    arrayOfChar[26] = ((char)'Ö');
    arrayOfChar[27] = ((char)'');
    arrayOfChar[28] = j;
    arrayOfChar[29] = ((char)'ò');
    arrayOfChar[30] = i;
    arrayOfChar[31] = ((char)'ì');
    arrayOfChar[32] = ((char)'');
    arrayOfChar[33] = ((char)'è');
    arrayOfChar[34] = ((char)'à');
    arrayOfChar[35] = ((char)'ñ');
    arrayOfChar[36] = ((char)'');
    arrayOfChar[37] = ((char)'å');
    arrayOfChar[38] = ((char)'ý');
    arrayOfChar[39] = ((char)'µ');
    arrayOfChar[40] = ((char)'«');
    arrayOfChar[41] = j;
    arrayOfChar[42] = ((char)'ù');
    return String.valueOf(new char[] { (char)('僓' / arrayOfChar[0]), (char)(-arrayOfChar[1] + 327), (char)(-arrayOfChar[2] + 354), (char)(arrayOfChar[3] ^ 0xA0), (char)(-arrayOfChar[4] + 242), (char)('戇' / arrayOfChar[5]), (char)(arrayOfChar[6] ^ 0xA6), (char)(-arrayOfChar[7] + 285), (char)(arrayOfChar[8] ^ 0xD2), (char)('㞨' / arrayOfChar[9]), (char)(-arrayOfChar[10] + 308), (char)(arrayOfChar[11] ^ 0xDE), (char)(arrayOfChar[12] ^ 0xEF), (char)(-arrayOfChar[13] + 279), (char)('埀' / arrayOfChar[14]), (char)('㋆' / arrayOfChar[15]), (char)('㶳' / arrayOfChar[16]), (char)(arrayOfChar[17] ^ 0x8A), (char)(arrayOfChar[18] ^ 0xEE), (char)('䩘' / arrayOfChar[19]), (char)(arrayOfChar[20] ^ 0xC7), (char)('悢' / arrayOfChar[21]), (char)(arrayOfChar[22] ^ 0xEC), (char)('䵄' / arrayOfChar[23]), (char)('㫉' / arrayOfChar[24]), (char)(-arrayOfChar[25] + 334), (char)('惸' / arrayOfChar[26]), (char)(-arrayOfChar[27] + 256), (char)(arrayOfChar[28] ^ 0xDA), (char)(arrayOfChar[29] ^ 0x95), (char)('㿊' / arrayOfChar[30]), (char)('㕸' / arrayOfChar[31]), (char)(arrayOfChar[32] ^ 0xAB), (char)(-arrayOfChar[33] + 331), (char)(-arrayOfChar[34] + 335), (char)(arrayOfChar[35] ^ 0x84), (char)(-arrayOfChar[36] + 253), (char)(arrayOfChar[37] ^ 0x91), (char)('ᾠ' / arrayOfChar[38]), (char)(arrayOfChar[39] ^ 0x88), (char)(-arrayOfChar[40] + 203), (char)(arrayOfChar[41] ^ 0x91), (char)('慄' / arrayOfChar[42]) });
  }
  
  public static String a()
  {
    char[] arrayOfChar = new char[66];
    arrayOfChar[0] = ((char)'Â');
    int n = (char)'Ê';
    arrayOfChar[1] = n;
    arrayOfChar[2] = ((char)'î');
    int i = (char)'Ý';
    arrayOfChar[3] = i;
    arrayOfChar[4] = ((char)'É');
    int m = (char)'é';
    arrayOfChar[5] = m;
    arrayOfChar[6] = ((char)'ü');
    int j = (char)'Ï';
    arrayOfChar[7] = j;
    int k = (char)'';
    arrayOfChar[8] = k;
    arrayOfChar[9] = ((char)'Ë');
    arrayOfChar[10] = ((char)'È');
    arrayOfChar[11] = ((char)'ç');
    arrayOfChar[12] = ((char)'');
    arrayOfChar[13] = ((char)'¨');
    arrayOfChar[14] = ((char)'Ã');
    arrayOfChar[15] = ((char)'Ô');
    arrayOfChar[16] = ((char)'ì');
    arrayOfChar[17] = ((char)'');
    arrayOfChar[18] = ((char)'ö');
    arrayOfChar[19] = ((char)'ù');
    arrayOfChar[20] = ((char)'û');
    arrayOfChar[21] = ((char)'¡');
    arrayOfChar[22] = n;
    n = (char)'©';
    arrayOfChar[23] = n;
    arrayOfChar[24] = ((char)'³');
    int i1 = (char)'';
    arrayOfChar[25] = i1;
    arrayOfChar[26] = ((char)'');
    arrayOfChar[27] = ((char)'¦');
    arrayOfChar[28] = ((char)'½');
    arrayOfChar[29] = m;
    arrayOfChar[30] = ((char)'®');
    arrayOfChar[31] = ((char)127);
    arrayOfChar[32] = ((char)'');
    arrayOfChar[33] = ((char)'÷');
    arrayOfChar[34] = ((char)'');
    arrayOfChar[35] = ((char)'');
    arrayOfChar[36] = ((char)'¤');
    arrayOfChar[37] = ((char)'');
    arrayOfChar[38] = ((char)'¼');
    arrayOfChar[39] = ((char)'¿');
    arrayOfChar[40] = ((char)'ê');
    arrayOfChar[41] = ((char)'');
    m = (char)'ñ';
    arrayOfChar[42] = m;
    arrayOfChar[43] = ((char)'ï');
    arrayOfChar[44] = ((char)'');
    arrayOfChar[45] = ((char)'«');
    arrayOfChar[46] = ((char)'¾');
    arrayOfChar[47] = ((char)'ø');
    arrayOfChar[48] = n;
    arrayOfChar[49] = k;
    arrayOfChar[50] = i1;
    arrayOfChar[51] = i;
    arrayOfChar[52] = ((char)'¯');
    arrayOfChar[53] = ((char)'â');
    arrayOfChar[54] = ((char)'');
    arrayOfChar[55] = ((char)'¹');
    arrayOfChar[56] = ((char)'Ø');
    arrayOfChar[57] = ((char)'ª');
    arrayOfChar[58] = j;
    arrayOfChar[59] = ((char)'Ð');
    arrayOfChar[60] = ((char)'ð');
    arrayOfChar[61] = ((char)'­');
    arrayOfChar[62] = ((char)'Ù');
    arrayOfChar[63] = m;
    arrayOfChar[64] = ((char)'´');
    arrayOfChar[65] = ((char)'å');
    return String.valueOf(new char[] { (char)(-arrayOfChar[0] + 293), (char)('垖' / arrayOfChar[1]), (char)(arrayOfChar[2] ^ 0x80), (char)(-arrayOfChar[3] + 337), (char)('位' / arrayOfChar[4]), (char)('搞' / arrayOfChar[5]), (char)(arrayOfChar[6] ^ 0x88), (char)('⻦' / arrayOfChar[7]), (char)(-arrayOfChar[8] + 176), (char)(arrayOfChar[9] ^ 0xE4), (char)(arrayOfChar[10] ^ 0xAB), (char)(arrayOfChar[11] ^ 0x88), (char)('䄥' / arrayOfChar[12]), (char)('Ḱ' / arrayOfChar[13]), (char)(-arrayOfChar[14] + 310), (char)(arrayOfChar[15] ^ 0xBB), (char)('敨' / arrayOfChar[16]), (char)(arrayOfChar[17] ^ 0xEB), (char)('梾' / arrayOfChar[18]), (char)(arrayOfChar[19] ^ 0x96), (char)(-arrayOfChar[20] + 349), (char)('䈉' / arrayOfChar[21]), (char)(arrayOfChar[22] ^ 0xA6), (char)('䊭' / arrayOfChar[23]), (char)(-arrayOfChar[24] + 225), (char)(-arrayOfChar[25] + 241), (char)(arrayOfChar[26] ^ 0xE1), (char)(-arrayOfChar[27] + 275), (char)('䪑' / arrayOfChar[28]), (char)('⧞' / arrayOfChar[29]), (char)(-arrayOfChar[30] + 273), (char)(-arrayOfChar[31] + 238), (char)(-arrayOfChar[32] + 240), (char)(arrayOfChar[33] ^ 0x91), (char)(arrayOfChar[34] ^ 0xF1), (char)(-arrayOfChar[35] + 238), (char)(arrayOfChar[36] ^ 0xD4), (char)(arrayOfChar[37] ^ 0xE6), (char)('冄' / arrayOfChar[38]), (char)(arrayOfChar[39] ^ 0xC9), (char)(-arrayOfChar[40] + 339), (char)('㌬' / arrayOfChar[41]), (char)(arrayOfChar[42] ^ 0x94), (char)(-arrayOfChar[43] + 353), (char)('ᥖ' / arrayOfChar[44]), (char)('䐢' / arrayOfChar[45]), (char)(arrayOfChar[46] ^ 0xDF), (char)('牐' / arrayOfChar[47]), (char)('䥇' / arrayOfChar[48]), (char)(-arrayOfChar[49] + 243), (char)(-arrayOfChar[50] + 242), (char)(arrayOfChar[51] ^ 0xA9), (char)(-arrayOfChar[52] + 276), (char)(arrayOfChar[53] ^ 0x91), (char)(arrayOfChar[54] ^ 0xA2), (char)(-arrayOfChar[55] + 295), (char)(-arrayOfChar[56] + 327), (char)(-arrayOfChar[57] + 286), (char)(-arrayOfChar[58] + 312), (char)(arrayOfChar[59] ^ 0xB6), (char)(arrayOfChar[60] ^ 0x89), (char)(arrayOfChar[61] ^ 0x90), (char)(arrayOfChar[62] ^ 0xAD), (char)(arrayOfChar[63] ^ 0x83), (char)('剄' / arrayOfChar[64]), (char)('婙' / arrayOfChar[65]) });
  }
  
  public static boolean a(Context paramContext, Class<?> paramClass, int paramInt, String paramString)
  {
    try
    {
      Intent localIntent1 = new Intent(G());
      Intent localIntent2 = new Intent(paramContext, paramClass);
      localIntent2.setAction(paramClass.getName());
      localIntent2.addFlags(268435456);
      localIntent1.putExtra(H(), localIntent2);
      localIntent1.putExtra(I(), paramString);
      localIntent1.putExtra(J(), false);
      paramClass = Intent.ShortcutIconResource.fromContext(paramContext, paramInt);
      localIntent1.putExtra(K(), paramClass);
      paramContext.sendBroadcast(localIntent1);
      return true;
    }
    catch (Exception paramContext)
    {
      paramContext.printStackTrace();
    }
    return false;
  }
  
  public static boolean a(Context paramContext, String paramString)
  {
    return (c(paramContext, paramString)) || (d(paramContext, paramString));
  }
  
  public static String b()
  {
    char[] arrayOfChar = new char[7];
    arrayOfChar[0] = ((char)'ó');
    arrayOfChar[1] = ((char)'');
    arrayOfChar[2] = ((char)'ì');
    arrayOfChar[3] = ((char)'');
    arrayOfChar[4] = ((char)'®');
    arrayOfChar[5] = ((char)'ô');
    arrayOfChar[6] = ((char)'¥');
    return String.valueOf(new char[] { (char)(arrayOfChar[0] ^ 0x87), (char)(arrayOfChar[1] ^ 0xF7), (char)(-arrayOfChar[2] + 352), (char)(arrayOfChar[3] ^ 0xED), (char)(arrayOfChar[4] ^ 0xCB), (char)(arrayOfChar[5] ^ 0xC9), (char)(arrayOfChar[6] ^ 0x9A) });
  }
  
  public static String b(Context paramContext, String paramString)
  {
    if (paramString == null) {
      return null;
    }
    paramContext = paramContext.getPackageManager().getInstalledPackages(8);
    if (paramContext != null)
    {
      if (paramContext.size() <= 0) {
        return null;
      }
      paramContext = paramContext.iterator();
      while (paramContext.hasNext())
      {
        paramString = (PackageInfo)paramContext.next();
        if ((paramString != null) && (paramString.providers != null))
        {
          paramString = paramString.providers;
          int j = paramString.length;
          int i = 0;
          while (i < j)
          {
            Object localObject = paramString[i];
            if (localObject != null)
            {
              if ((localObject.readPermission != null) && (Pattern.matches(L(), localObject.readPermission))) {
                return localObject.authority;
              }
              if ((localObject.writePermission != null) && (Pattern.matches(M(), localObject.writePermission))) {
                return localObject.authority;
              }
            }
            i += 1;
          }
        }
      }
    }
    return null;
  }
  
  public static String c()
  {
    char[] arrayOfChar = new char[46];
    arrayOfChar[0] = ((char)'Ï');
    arrayOfChar[1] = ((char)'Å');
    int j = (char)'Ë';
    arrayOfChar[2] = j;
    int i = (char)'';
    arrayOfChar[3] = i;
    arrayOfChar[4] = ((char)'Ó');
    int n = (char)'Á';
    arrayOfChar[5] = n;
    arrayOfChar[6] = ((char)'»');
    arrayOfChar[7] = ((char)'');
    int k = (char)'';
    arrayOfChar[8] = k;
    int m = (char)'¯';
    arrayOfChar[9] = m;
    arrayOfChar[10] = ((char)'');
    arrayOfChar[11] = n;
    arrayOfChar[12] = ((char)'ÿ');
    arrayOfChar[13] = ((char)'ò');
    arrayOfChar[14] = ((char)'ã');
    arrayOfChar[15] = ((char)'÷');
    arrayOfChar[16] = ((char)'ñ');
    arrayOfChar[17] = ((char)'Î');
    arrayOfChar[18] = ((char)'Ü');
    arrayOfChar[19] = ((char)'×');
    arrayOfChar[20] = ((char)'');
    arrayOfChar[21] = ((char)'ù');
    n = (char)'Ú';
    arrayOfChar[22] = n;
    arrayOfChar[23] = k;
    arrayOfChar[24] = ((char)'');
    arrayOfChar[25] = m;
    arrayOfChar[26] = ((char)'');
    arrayOfChar[27] = ((char)'');
    arrayOfChar[28] = ((char)'à');
    arrayOfChar[29] = ((char)'©');
    arrayOfChar[30] = ((char)'á');
    arrayOfChar[31] = ((char)'¦');
    arrayOfChar[32] = ((char)'­');
    arrayOfChar[33] = ((char)'¬');
    arrayOfChar[34] = ((char)'Í');
    arrayOfChar[35] = j;
    arrayOfChar[36] = ((char)'È');
    arrayOfChar[37] = ((char)127);
    arrayOfChar[38] = n;
    arrayOfChar[39] = ((char)'±');
    arrayOfChar[40] = ((char)'þ');
    j = (char)'À';
    arrayOfChar[41] = j;
    arrayOfChar[42] = i;
    arrayOfChar[43] = ((char)'');
    arrayOfChar[44] = j;
    arrayOfChar[45] = ((char)'Ä');
    return String.valueOf(new char[] { (char)(-arrayOfChar[0] + 306), (char)('啫' / arrayOfChar[1]), (char)('噯' / arrayOfChar[2]), (char)('ᤨ' / arrayOfChar[3]), (char)(arrayOfChar[4] ^ 0xA0), (char)(arrayOfChar[5] ^ 0xAE), (char)(arrayOfChar[6] ^ 0xD5), (char)(-arrayOfChar[7] + 253), (char)(arrayOfChar[8] ^ 0xEB), (char)('䯡' / arrayOfChar[9]), (char)(-arrayOfChar[10] + 241), (char)(-arrayOfChar[11] + 298), (char)('殔' / arrayOfChar[12]), (char)('彺' / arrayOfChar[13]), (char)(arrayOfChar[14] ^ 0xCD), (char)('摘' / arrayOfChar[15]), (char)(arrayOfChar[16] ^ 0x9E), (char)(arrayOfChar[17] ^ 0xA3), (char)('囌' / arrayOfChar[18]), (char)(arrayOfChar[19] ^ 0xF9), (char)(arrayOfChar[20] ^ 0xEB), (char)(arrayOfChar[21] ^ 0x96), (char)(-arrayOfChar[22] + 328), (char)(arrayOfChar[23] ^ 0xE0), (char)(arrayOfChar[24] ^ 0xF3), (char)(arrayOfChar[25] ^ 0xC8), (char)(arrayOfChar[26] ^ 0xF0), (char)(-arrayOfChar[27] + 263), (char)(-arrayOfChar[28] + 335), (char)(-arrayOfChar[29] + 287), (char)(arrayOfChar[30] ^ 0x88), (char)(-arrayOfChar[31] + 266), (char)(-arrayOfChar[32] + 274), (char)(-arrayOfChar[33] + 286), (char)(arrayOfChar[34] ^ 0xF7), (char)('ᥠ' / arrayOfChar[35]), (char)('䵘' / arrayOfChar[36]), (char)('㜑' / arrayOfChar[37]), (char)(arrayOfChar[38] ^ 0xAF), (char)('䰎' / arrayOfChar[39]), (char)(-arrayOfChar[40] + 370), (char)(arrayOfChar[41] ^ 0xE0), (char)('⅜' / arrayOfChar[42]), (char)(-arrayOfChar[43] + 185), (char)(-arrayOfChar[44] + 229), (char)('䲐' / arrayOfChar[45]) });
  }
  
  /* Error */
  private static boolean c(Context paramContext, String paramString)
  {
    // Byte code:
    //   0: aconst_null
    //   1: astore 17
    //   3: aconst_null
    //   4: astore 16
    //   6: iconst_1
    //   7: istore 4
    //   9: iconst_1
    //   10: istore 5
    //   12: iconst_1
    //   13: istore 6
    //   15: iconst_1
    //   16: istore 7
    //   18: iconst_1
    //   19: istore 8
    //   21: iconst_1
    //   22: istore 9
    //   24: iconst_1
    //   25: istore 10
    //   27: iconst_1
    //   28: istore 11
    //   30: iconst_1
    //   31: istore 12
    //   33: iconst_1
    //   34: istore 13
    //   36: iconst_1
    //   37: istore_3
    //   38: aload 16
    //   40: astore 15
    //   42: aload 17
    //   44: astore 14
    //   46: invokestatic 173	com/a/ll/ax:N	()Ljava/lang/String;
    //   49: invokestatic 179	android/net/Uri:parse	(Ljava/lang/String;)Landroid/net/Uri;
    //   52: astore 18
    //   54: aload 16
    //   56: astore 15
    //   58: aload 17
    //   60: astore 14
    //   62: aload_0
    //   63: invokevirtual 183	android/content/Context:getContentResolver	()Landroid/content/ContentResolver;
    //   66: aload 18
    //   68: aconst_null
    //   69: invokestatic 185	com/a/ll/ax:O	()Ljava/lang/String;
    //   72: iconst_1
    //   73: anewarray 8	java/lang/String
    //   76: dup
    //   77: iconst_0
    //   78: aload_1
    //   79: aastore
    //   80: aconst_null
    //   81: invokevirtual 191	android/content/ContentResolver:query	(Landroid/net/Uri;[Ljava/lang/String;Ljava/lang/String;[Ljava/lang/String;Ljava/lang/String;)Landroid/database/Cursor;
    //   84: astore 16
    //   86: aload 16
    //   88: ifnull +73 -> 161
    //   91: aload 16
    //   93: astore 15
    //   95: aload 16
    //   97: astore 14
    //   99: invokestatic 193	com/a/ll/ax:P	()Ljava/lang/String;
    //   102: pop
    //   103: aload 16
    //   105: astore 15
    //   107: aload 16
    //   109: astore 14
    //   111: aload 16
    //   113: invokeinterface 198 1 0
    //   118: pop
    //   119: aload 16
    //   121: astore 15
    //   123: aload 16
    //   125: astore 14
    //   127: aload 16
    //   129: invokeinterface 198 1 0
    //   134: istore_2
    //   135: iload_2
    //   136: ifle +6 -> 142
    //   139: goto +5 -> 144
    //   142: iconst_0
    //   143: istore_3
    //   144: aload 16
    //   146: invokeinterface 201 1 0
    //   151: iload_3
    //   152: ireturn
    //   153: astore_0
    //   154: goto +1328 -> 1482
    //   157: astore_0
    //   158: goto +1290 -> 1448
    //   161: aload 16
    //   163: astore 15
    //   165: aload 16
    //   167: astore 14
    //   169: invokestatic 203	com/a/ll/ax:Q	()Ljava/lang/String;
    //   172: invokestatic 179	android/net/Uri:parse	(Ljava/lang/String;)Landroid/net/Uri;
    //   175: astore 17
    //   177: aload 16
    //   179: astore 15
    //   181: aload 16
    //   183: astore 14
    //   185: aload_0
    //   186: invokevirtual 183	android/content/Context:getContentResolver	()Landroid/content/ContentResolver;
    //   189: aload 17
    //   191: aconst_null
    //   192: invokestatic 205	com/a/ll/ax:R	()Ljava/lang/String;
    //   195: iconst_1
    //   196: anewarray 8	java/lang/String
    //   199: dup
    //   200: iconst_0
    //   201: aload_1
    //   202: aastore
    //   203: aconst_null
    //   204: invokevirtual 191	android/content/ContentResolver:query	(Landroid/net/Uri;[Ljava/lang/String;Ljava/lang/String;[Ljava/lang/String;Ljava/lang/String;)Landroid/database/Cursor;
    //   207: astore 16
    //   209: aload 16
    //   211: ifnull +68 -> 279
    //   214: aload 16
    //   216: astore 15
    //   218: aload 16
    //   220: astore 14
    //   222: invokestatic 207	com/a/ll/ax:S	()Ljava/lang/String;
    //   225: pop
    //   226: aload 16
    //   228: astore 15
    //   230: aload 16
    //   232: astore 14
    //   234: aload 16
    //   236: invokeinterface 198 1 0
    //   241: pop
    //   242: aload 16
    //   244: astore 15
    //   246: aload 16
    //   248: astore 14
    //   250: aload 16
    //   252: invokeinterface 198 1 0
    //   257: istore_2
    //   258: iload_2
    //   259: ifle +9 -> 268
    //   262: iload 4
    //   264: istore_3
    //   265: goto +5 -> 270
    //   268: iconst_0
    //   269: istore_3
    //   270: aload 16
    //   272: invokeinterface 201 1 0
    //   277: iload_3
    //   278: ireturn
    //   279: aload 16
    //   281: astore 15
    //   283: aload 16
    //   285: astore 14
    //   287: invokestatic 209	com/a/ll/ax:T	()Ljava/lang/String;
    //   290: invokestatic 179	android/net/Uri:parse	(Ljava/lang/String;)Landroid/net/Uri;
    //   293: astore 17
    //   295: aload 16
    //   297: astore 15
    //   299: aload 16
    //   301: astore 14
    //   303: aload_0
    //   304: invokevirtual 183	android/content/Context:getContentResolver	()Landroid/content/ContentResolver;
    //   307: aload 17
    //   309: aconst_null
    //   310: invokestatic 211	com/a/ll/ax:U	()Ljava/lang/String;
    //   313: iconst_1
    //   314: anewarray 8	java/lang/String
    //   317: dup
    //   318: iconst_0
    //   319: aload_1
    //   320: aastore
    //   321: aconst_null
    //   322: invokevirtual 191	android/content/ContentResolver:query	(Landroid/net/Uri;[Ljava/lang/String;Ljava/lang/String;[Ljava/lang/String;Ljava/lang/String;)Landroid/database/Cursor;
    //   325: astore 16
    //   327: aload 16
    //   329: ifnull +68 -> 397
    //   332: aload 16
    //   334: astore 15
    //   336: aload 16
    //   338: astore 14
    //   340: invokestatic 213	com/a/ll/ax:V	()Ljava/lang/String;
    //   343: pop
    //   344: aload 16
    //   346: astore 15
    //   348: aload 16
    //   350: astore 14
    //   352: aload 16
    //   354: invokeinterface 198 1 0
    //   359: pop
    //   360: aload 16
    //   362: astore 15
    //   364: aload 16
    //   366: astore 14
    //   368: aload 16
    //   370: invokeinterface 198 1 0
    //   375: istore_2
    //   376: iload_2
    //   377: ifle +9 -> 386
    //   380: iload 5
    //   382: istore_3
    //   383: goto +5 -> 388
    //   386: iconst_0
    //   387: istore_3
    //   388: aload 16
    //   390: invokeinterface 201 1 0
    //   395: iload_3
    //   396: ireturn
    //   397: aload 16
    //   399: astore 15
    //   401: aload 16
    //   403: astore 14
    //   405: invokestatic 215	com/a/ll/ax:W	()Ljava/lang/String;
    //   408: invokestatic 179	android/net/Uri:parse	(Ljava/lang/String;)Landroid/net/Uri;
    //   411: astore 17
    //   413: aload 16
    //   415: astore 15
    //   417: aload 16
    //   419: astore 14
    //   421: aload_0
    //   422: invokevirtual 183	android/content/Context:getContentResolver	()Landroid/content/ContentResolver;
    //   425: aload 17
    //   427: aconst_null
    //   428: invokestatic 217	com/a/ll/ax:X	()Ljava/lang/String;
    //   431: iconst_1
    //   432: anewarray 8	java/lang/String
    //   435: dup
    //   436: iconst_0
    //   437: aload_1
    //   438: aastore
    //   439: aconst_null
    //   440: invokevirtual 191	android/content/ContentResolver:query	(Landroid/net/Uri;[Ljava/lang/String;Ljava/lang/String;[Ljava/lang/String;Ljava/lang/String;)Landroid/database/Cursor;
    //   443: astore 16
    //   445: aload 16
    //   447: ifnull +68 -> 515
    //   450: aload 16
    //   452: astore 15
    //   454: aload 16
    //   456: astore 14
    //   458: invokestatic 219	com/a/ll/ax:Y	()Ljava/lang/String;
    //   461: pop
    //   462: aload 16
    //   464: astore 15
    //   466: aload 16
    //   468: astore 14
    //   470: aload 16
    //   472: invokeinterface 198 1 0
    //   477: pop
    //   478: aload 16
    //   480: astore 15
    //   482: aload 16
    //   484: astore 14
    //   486: aload 16
    //   488: invokeinterface 198 1 0
    //   493: istore_2
    //   494: iload_2
    //   495: ifle +9 -> 504
    //   498: iload 6
    //   500: istore_3
    //   501: goto +5 -> 506
    //   504: iconst_0
    //   505: istore_3
    //   506: aload 16
    //   508: invokeinterface 201 1 0
    //   513: iload_3
    //   514: ireturn
    //   515: aload 16
    //   517: astore 15
    //   519: aload 16
    //   521: astore 14
    //   523: invokestatic 221	com/a/ll/ax:a	()Ljava/lang/String;
    //   526: invokestatic 179	android/net/Uri:parse	(Ljava/lang/String;)Landroid/net/Uri;
    //   529: astore 17
    //   531: aload 16
    //   533: astore 15
    //   535: aload 16
    //   537: astore 14
    //   539: aload_0
    //   540: invokevirtual 183	android/content/Context:getContentResolver	()Landroid/content/ContentResolver;
    //   543: aload 17
    //   545: aconst_null
    //   546: invokestatic 223	com/a/ll/ax:b	()Ljava/lang/String;
    //   549: iconst_1
    //   550: anewarray 8	java/lang/String
    //   553: dup
    //   554: iconst_0
    //   555: aload_1
    //   556: aastore
    //   557: aconst_null
    //   558: invokevirtual 191	android/content/ContentResolver:query	(Landroid/net/Uri;[Ljava/lang/String;Ljava/lang/String;[Ljava/lang/String;Ljava/lang/String;)Landroid/database/Cursor;
    //   561: astore 16
    //   563: aload 16
    //   565: ifnull +68 -> 633
    //   568: aload 16
    //   570: astore 15
    //   572: aload 16
    //   574: astore 14
    //   576: invokestatic 225	com/a/ll/ax:c	()Ljava/lang/String;
    //   579: pop
    //   580: aload 16
    //   582: astore 15
    //   584: aload 16
    //   586: astore 14
    //   588: aload 16
    //   590: invokeinterface 198 1 0
    //   595: pop
    //   596: aload 16
    //   598: astore 15
    //   600: aload 16
    //   602: astore 14
    //   604: aload 16
    //   606: invokeinterface 198 1 0
    //   611: istore_2
    //   612: iload_2
    //   613: ifle +9 -> 622
    //   616: iload 7
    //   618: istore_3
    //   619: goto +5 -> 624
    //   622: iconst_0
    //   623: istore_3
    //   624: aload 16
    //   626: invokeinterface 201 1 0
    //   631: iload_3
    //   632: ireturn
    //   633: aload 16
    //   635: astore 15
    //   637: aload 16
    //   639: astore 14
    //   641: invokestatic 227	com/a/ll/ax:d	()Ljava/lang/String;
    //   644: invokestatic 179	android/net/Uri:parse	(Ljava/lang/String;)Landroid/net/Uri;
    //   647: astore 17
    //   649: aload 16
    //   651: astore 15
    //   653: aload 16
    //   655: astore 14
    //   657: aload_0
    //   658: invokevirtual 183	android/content/Context:getContentResolver	()Landroid/content/ContentResolver;
    //   661: aload 17
    //   663: aconst_null
    //   664: invokestatic 230	com/a/ll/ax:e	()Ljava/lang/String;
    //   667: iconst_1
    //   668: anewarray 8	java/lang/String
    //   671: dup
    //   672: iconst_0
    //   673: aload_1
    //   674: aastore
    //   675: aconst_null
    //   676: invokevirtual 191	android/content/ContentResolver:query	(Landroid/net/Uri;[Ljava/lang/String;Ljava/lang/String;[Ljava/lang/String;Ljava/lang/String;)Landroid/database/Cursor;
    //   679: astore 16
    //   681: aload 16
    //   683: ifnull +68 -> 751
    //   686: aload 16
    //   688: astore 15
    //   690: aload 16
    //   692: astore 14
    //   694: invokestatic 233	com/a/ll/ax:f	()Ljava/lang/String;
    //   697: pop
    //   698: aload 16
    //   700: astore 15
    //   702: aload 16
    //   704: astore 14
    //   706: aload 16
    //   708: invokeinterface 198 1 0
    //   713: pop
    //   714: aload 16
    //   716: astore 15
    //   718: aload 16
    //   720: astore 14
    //   722: aload 16
    //   724: invokeinterface 198 1 0
    //   729: istore_2
    //   730: iload_2
    //   731: ifle +9 -> 740
    //   734: iload 8
    //   736: istore_3
    //   737: goto +5 -> 742
    //   740: iconst_0
    //   741: istore_3
    //   742: aload 16
    //   744: invokeinterface 201 1 0
    //   749: iload_3
    //   750: ireturn
    //   751: aload 16
    //   753: astore 15
    //   755: aload 16
    //   757: astore 14
    //   759: invokestatic 236	com/a/ll/ax:g	()Ljava/lang/String;
    //   762: invokestatic 179	android/net/Uri:parse	(Ljava/lang/String;)Landroid/net/Uri;
    //   765: astore 17
    //   767: aload 16
    //   769: astore 15
    //   771: aload 16
    //   773: astore 14
    //   775: aload_0
    //   776: invokevirtual 183	android/content/Context:getContentResolver	()Landroid/content/ContentResolver;
    //   779: aload 17
    //   781: aconst_null
    //   782: invokestatic 239	com/a/ll/ax:h	()Ljava/lang/String;
    //   785: iconst_1
    //   786: anewarray 8	java/lang/String
    //   789: dup
    //   790: iconst_0
    //   791: aload_1
    //   792: aastore
    //   793: aconst_null
    //   794: invokevirtual 191	android/content/ContentResolver:query	(Landroid/net/Uri;[Ljava/lang/String;Ljava/lang/String;[Ljava/lang/String;Ljava/lang/String;)Landroid/database/Cursor;
    //   797: astore 16
    //   799: aload 16
    //   801: ifnull +68 -> 869
    //   804: aload 16
    //   806: astore 15
    //   808: aload 16
    //   810: astore 14
    //   812: invokestatic 242	com/a/ll/ax:i	()Ljava/lang/String;
    //   815: pop
    //   816: aload 16
    //   818: astore 15
    //   820: aload 16
    //   822: astore 14
    //   824: aload 16
    //   826: invokeinterface 198 1 0
    //   831: pop
    //   832: aload 16
    //   834: astore 15
    //   836: aload 16
    //   838: astore 14
    //   840: aload 16
    //   842: invokeinterface 198 1 0
    //   847: istore_2
    //   848: iload_2
    //   849: ifle +9 -> 858
    //   852: iload 9
    //   854: istore_3
    //   855: goto +5 -> 860
    //   858: iconst_0
    //   859: istore_3
    //   860: aload 16
    //   862: invokeinterface 201 1 0
    //   867: iload_3
    //   868: ireturn
    //   869: aload 16
    //   871: astore 15
    //   873: aload 16
    //   875: astore 14
    //   877: invokestatic 245	com/a/ll/ax:j	()Ljava/lang/String;
    //   880: invokestatic 179	android/net/Uri:parse	(Ljava/lang/String;)Landroid/net/Uri;
    //   883: astore 17
    //   885: aload 16
    //   887: astore 15
    //   889: aload 16
    //   891: astore 14
    //   893: aload_0
    //   894: invokevirtual 183	android/content/Context:getContentResolver	()Landroid/content/ContentResolver;
    //   897: aload 17
    //   899: aconst_null
    //   900: invokestatic 248	com/a/ll/ax:k	()Ljava/lang/String;
    //   903: iconst_1
    //   904: anewarray 8	java/lang/String
    //   907: dup
    //   908: iconst_0
    //   909: aload_1
    //   910: aastore
    //   911: aconst_null
    //   912: invokevirtual 191	android/content/ContentResolver:query	(Landroid/net/Uri;[Ljava/lang/String;Ljava/lang/String;[Ljava/lang/String;Ljava/lang/String;)Landroid/database/Cursor;
    //   915: astore 16
    //   917: aload 16
    //   919: ifnull +68 -> 987
    //   922: aload 16
    //   924: astore 15
    //   926: aload 16
    //   928: astore 14
    //   930: invokestatic 251	com/a/ll/ax:l	()Ljava/lang/String;
    //   933: pop
    //   934: aload 16
    //   936: astore 15
    //   938: aload 16
    //   940: astore 14
    //   942: aload 16
    //   944: invokeinterface 198 1 0
    //   949: pop
    //   950: aload 16
    //   952: astore 15
    //   954: aload 16
    //   956: astore 14
    //   958: aload 16
    //   960: invokeinterface 198 1 0
    //   965: istore_2
    //   966: iload_2
    //   967: ifle +9 -> 976
    //   970: iload 10
    //   972: istore_3
    //   973: goto +5 -> 978
    //   976: iconst_0
    //   977: istore_3
    //   978: aload 16
    //   980: invokeinterface 201 1 0
    //   985: iload_3
    //   986: ireturn
    //   987: aload 16
    //   989: astore 15
    //   991: aload 16
    //   993: astore 14
    //   995: invokestatic 254	com/a/ll/ax:m	()Ljava/lang/String;
    //   998: invokestatic 179	android/net/Uri:parse	(Ljava/lang/String;)Landroid/net/Uri;
    //   1001: astore 17
    //   1003: aload 16
    //   1005: astore 15
    //   1007: aload 16
    //   1009: astore 14
    //   1011: aload_0
    //   1012: invokevirtual 183	android/content/Context:getContentResolver	()Landroid/content/ContentResolver;
    //   1015: aload 17
    //   1017: aconst_null
    //   1018: invokestatic 257	com/a/ll/ax:n	()Ljava/lang/String;
    //   1021: iconst_1
    //   1022: anewarray 8	java/lang/String
    //   1025: dup
    //   1026: iconst_0
    //   1027: aload_1
    //   1028: aastore
    //   1029: aconst_null
    //   1030: invokevirtual 191	android/content/ContentResolver:query	(Landroid/net/Uri;[Ljava/lang/String;Ljava/lang/String;[Ljava/lang/String;Ljava/lang/String;)Landroid/database/Cursor;
    //   1033: astore 16
    //   1035: aload 16
    //   1037: ifnull +68 -> 1105
    //   1040: aload 16
    //   1042: astore 15
    //   1044: aload 16
    //   1046: astore 14
    //   1048: invokestatic 260	com/a/ll/ax:o	()Ljava/lang/String;
    //   1051: pop
    //   1052: aload 16
    //   1054: astore 15
    //   1056: aload 16
    //   1058: astore 14
    //   1060: aload 16
    //   1062: invokeinterface 198 1 0
    //   1067: pop
    //   1068: aload 16
    //   1070: astore 15
    //   1072: aload 16
    //   1074: astore 14
    //   1076: aload 16
    //   1078: invokeinterface 198 1 0
    //   1083: istore_2
    //   1084: iload_2
    //   1085: ifle +9 -> 1094
    //   1088: iload 11
    //   1090: istore_3
    //   1091: goto +5 -> 1096
    //   1094: iconst_0
    //   1095: istore_3
    //   1096: aload 16
    //   1098: invokeinterface 201 1 0
    //   1103: iload_3
    //   1104: ireturn
    //   1105: aload 16
    //   1107: astore 15
    //   1109: aload 16
    //   1111: astore 14
    //   1113: invokestatic 263	com/a/ll/ax:p	()Ljava/lang/String;
    //   1116: invokestatic 179	android/net/Uri:parse	(Ljava/lang/String;)Landroid/net/Uri;
    //   1119: astore 17
    //   1121: aload 16
    //   1123: astore 15
    //   1125: aload 16
    //   1127: astore 14
    //   1129: aload_0
    //   1130: invokevirtual 183	android/content/Context:getContentResolver	()Landroid/content/ContentResolver;
    //   1133: aload 17
    //   1135: aconst_null
    //   1136: invokestatic 266	com/a/ll/ax:q	()Ljava/lang/String;
    //   1139: iconst_1
    //   1140: anewarray 8	java/lang/String
    //   1143: dup
    //   1144: iconst_0
    //   1145: aload_1
    //   1146: aastore
    //   1147: aconst_null
    //   1148: invokevirtual 191	android/content/ContentResolver:query	(Landroid/net/Uri;[Ljava/lang/String;Ljava/lang/String;[Ljava/lang/String;Ljava/lang/String;)Landroid/database/Cursor;
    //   1151: astore 16
    //   1153: aload 16
    //   1155: ifnull +68 -> 1223
    //   1158: aload 16
    //   1160: astore 15
    //   1162: aload 16
    //   1164: astore 14
    //   1166: invokestatic 269	com/a/ll/ax:r	()Ljava/lang/String;
    //   1169: pop
    //   1170: aload 16
    //   1172: astore 15
    //   1174: aload 16
    //   1176: astore 14
    //   1178: aload 16
    //   1180: invokeinterface 198 1 0
    //   1185: pop
    //   1186: aload 16
    //   1188: astore 15
    //   1190: aload 16
    //   1192: astore 14
    //   1194: aload 16
    //   1196: invokeinterface 198 1 0
    //   1201: istore_2
    //   1202: iload_2
    //   1203: ifle +9 -> 1212
    //   1206: iload 12
    //   1208: istore_3
    //   1209: goto +5 -> 1214
    //   1212: iconst_0
    //   1213: istore_3
    //   1214: aload 16
    //   1216: invokeinterface 201 1 0
    //   1221: iload_3
    //   1222: ireturn
    //   1223: aload 16
    //   1225: astore 15
    //   1227: aload 16
    //   1229: astore 14
    //   1231: aload_0
    //   1232: invokestatic 272	com/a/ll/ax:s	()Ljava/lang/String;
    //   1235: invokestatic 274	com/a/ll/ax:b	(Landroid/content/Context;Ljava/lang/String;)Ljava/lang/String;
    //   1238: astore 17
    //   1240: aload 17
    //   1242: ifnonnull +24 -> 1266
    //   1245: aload 16
    //   1247: astore 15
    //   1249: aload 16
    //   1251: astore 14
    //   1253: invokestatic 277	com/a/ll/ax:t	()Ljava/lang/String;
    //   1256: pop
    //   1257: aload 16
    //   1259: invokeinterface 201 1 0
    //   1264: iconst_0
    //   1265: ireturn
    //   1266: aload 16
    //   1268: astore 15
    //   1270: aload 16
    //   1272: astore 14
    //   1274: new 279	java/lang/StringBuilder
    //   1277: dup
    //   1278: invokespecial 281	java/lang/StringBuilder:<init>	()V
    //   1281: astore 18
    //   1283: aload 16
    //   1285: astore 15
    //   1287: aload 16
    //   1289: astore 14
    //   1291: aload 18
    //   1293: invokestatic 284	com/a/ll/ax:u	()Ljava/lang/String;
    //   1296: invokevirtual 288	java/lang/StringBuilder:append	(Ljava/lang/String;)Ljava/lang/StringBuilder;
    //   1299: pop
    //   1300: aload 16
    //   1302: astore 15
    //   1304: aload 16
    //   1306: astore 14
    //   1308: aload 18
    //   1310: aload 17
    //   1312: invokevirtual 288	java/lang/StringBuilder:append	(Ljava/lang/String;)Ljava/lang/StringBuilder;
    //   1315: pop
    //   1316: aload 16
    //   1318: astore 15
    //   1320: aload 16
    //   1322: astore 14
    //   1324: aload 18
    //   1326: invokestatic 291	com/a/ll/ax:v	()Ljava/lang/String;
    //   1329: invokevirtual 288	java/lang/StringBuilder:append	(Ljava/lang/String;)Ljava/lang/StringBuilder;
    //   1332: pop
    //   1333: aload 16
    //   1335: astore 15
    //   1337: aload 16
    //   1339: astore 14
    //   1341: aload 18
    //   1343: invokevirtual 294	java/lang/StringBuilder:toString	()Ljava/lang/String;
    //   1346: invokestatic 179	android/net/Uri:parse	(Ljava/lang/String;)Landroid/net/Uri;
    //   1349: astore 17
    //   1351: aload 16
    //   1353: astore 15
    //   1355: aload 16
    //   1357: astore 14
    //   1359: aload_0
    //   1360: invokevirtual 183	android/content/Context:getContentResolver	()Landroid/content/ContentResolver;
    //   1363: aload 17
    //   1365: aconst_null
    //   1366: invokestatic 297	com/a/ll/ax:w	()Ljava/lang/String;
    //   1369: iconst_1
    //   1370: anewarray 8	java/lang/String
    //   1373: dup
    //   1374: iconst_0
    //   1375: aload_1
    //   1376: aastore
    //   1377: aconst_null
    //   1378: invokevirtual 191	android/content/ContentResolver:query	(Landroid/net/Uri;[Ljava/lang/String;Ljava/lang/String;[Ljava/lang/String;Ljava/lang/String;)Landroid/database/Cursor;
    //   1381: astore_1
    //   1382: aload_1
    //   1383: ifnull +52 -> 1435
    //   1386: aload_1
    //   1387: astore_0
    //   1388: invokestatic 300	com/a/ll/ax:x	()Ljava/lang/String;
    //   1391: pop
    //   1392: aload_1
    //   1393: astore_0
    //   1394: aload_1
    //   1395: invokeinterface 198 1 0
    //   1400: pop
    //   1401: aload_1
    //   1402: astore_0
    //   1403: aload_1
    //   1404: invokeinterface 198 1 0
    //   1409: istore_2
    //   1410: iload_2
    //   1411: ifle +9 -> 1420
    //   1414: iload 13
    //   1416: istore_3
    //   1417: goto +5 -> 1422
    //   1420: iconst_0
    //   1421: istore_3
    //   1422: aload_1
    //   1423: invokeinterface 201 1 0
    //   1428: iload_3
    //   1429: ireturn
    //   1430: astore 14
    //   1432: goto +22 -> 1454
    //   1435: aload_1
    //   1436: invokeinterface 201 1 0
    //   1441: iconst_0
    //   1442: ireturn
    //   1443: astore_0
    //   1444: goto +38 -> 1482
    //   1447: astore_0
    //   1448: aload 14
    //   1450: astore_1
    //   1451: aload_0
    //   1452: astore 14
    //   1454: aload_1
    //   1455: astore_0
    //   1456: invokestatic 303	com/a/ll/ax:y	()Ljava/lang/String;
    //   1459: pop
    //   1460: aload_1
    //   1461: astore_0
    //   1462: aload 14
    //   1464: invokevirtual 306	java/lang/Exception:getMessage	()Ljava/lang/String;
    //   1467: pop
    //   1468: aload_1
    //   1469: invokeinterface 201 1 0
    //   1474: iconst_0
    //   1475: ireturn
    //   1476: astore_1
    //   1477: aload_0
    //   1478: astore 15
    //   1480: aload_1
    //   1481: astore_0
    //   1482: aload 15
    //   1484: invokeinterface 201 1 0
    //   1489: aload_0
    //   1490: athrow
    //   1491: astore_0
    //   1492: iload_3
    //   1493: ireturn
    //   1494: astore_0
    //   1495: iload_3
    //   1496: ireturn
    //   1497: astore_0
    //   1498: iload_3
    //   1499: ireturn
    //   1500: astore_0
    //   1501: iload_3
    //   1502: ireturn
    //   1503: astore_0
    //   1504: iload_3
    //   1505: ireturn
    //   1506: astore_0
    //   1507: iload_3
    //   1508: ireturn
    //   1509: astore_0
    //   1510: iload_3
    //   1511: ireturn
    //   1512: astore_0
    //   1513: iload_3
    //   1514: ireturn
    //   1515: astore_0
    //   1516: iload_3
    //   1517: ireturn
    //   1518: astore_0
    //   1519: iload_3
    //   1520: ireturn
    //   1521: astore_0
    //   1522: iconst_0
    //   1523: ireturn
    //   1524: astore_0
    //   1525: iload_3
    //   1526: ireturn
    //   1527: astore_0
    //   1528: iconst_0
    //   1529: ireturn
    //   1530: astore_0
    //   1531: iconst_0
    //   1532: ireturn
    //   1533: astore_1
    //   1534: goto -45 -> 1489
    // Local variable table:
    //   start	length	slot	name	signature
    //   0	1537	0	paramContext	Context
    //   0	1537	1	paramString	String
    //   134	1277	2	i	int
    //   37	1489	3	bool1	boolean
    //   7	256	4	bool2	boolean
    //   10	371	5	bool3	boolean
    //   13	486	6	bool4	boolean
    //   16	601	7	bool5	boolean
    //   19	716	8	bool6	boolean
    //   22	831	9	bool7	boolean
    //   25	946	10	bool8	boolean
    //   28	1061	11	bool9	boolean
    //   31	1176	12	bool10	boolean
    //   34	1381	13	bool11	boolean
    //   44	1314	14	localObject1	Object
    //   1430	19	14	localException	Exception
    //   1452	11	14	localContext	Context
    //   40	1443	15	localObject2	Object
    //   4	1352	16	localCursor	android.database.Cursor
    //   1	1363	17	localObject3	Object
    //   52	1290	18	localObject4	Object
    // Exception table:
    //   from	to	target	type
    //   99	103	153	finally
    //   111	119	153	finally
    //   127	135	153	finally
    //   169	177	153	finally
    //   185	209	153	finally
    //   340	344	153	finally
    //   352	360	153	finally
    //   368	376	153	finally
    //   405	413	153	finally
    //   421	445	153	finally
    //   576	580	153	finally
    //   588	596	153	finally
    //   604	612	153	finally
    //   641	649	153	finally
    //   657	681	153	finally
    //   812	816	153	finally
    //   824	832	153	finally
    //   840	848	153	finally
    //   877	885	153	finally
    //   893	917	153	finally
    //   1048	1052	153	finally
    //   1060	1068	153	finally
    //   1076	1084	153	finally
    //   1113	1121	153	finally
    //   1129	1153	153	finally
    //   99	103	157	java/lang/Exception
    //   111	119	157	java/lang/Exception
    //   127	135	157	java/lang/Exception
    //   169	177	157	java/lang/Exception
    //   185	209	157	java/lang/Exception
    //   340	344	157	java/lang/Exception
    //   352	360	157	java/lang/Exception
    //   368	376	157	java/lang/Exception
    //   405	413	157	java/lang/Exception
    //   421	445	157	java/lang/Exception
    //   576	580	157	java/lang/Exception
    //   588	596	157	java/lang/Exception
    //   604	612	157	java/lang/Exception
    //   641	649	157	java/lang/Exception
    //   657	681	157	java/lang/Exception
    //   812	816	157	java/lang/Exception
    //   824	832	157	java/lang/Exception
    //   840	848	157	java/lang/Exception
    //   877	885	157	java/lang/Exception
    //   893	917	157	java/lang/Exception
    //   1048	1052	157	java/lang/Exception
    //   1060	1068	157	java/lang/Exception
    //   1076	1084	157	java/lang/Exception
    //   1113	1121	157	java/lang/Exception
    //   1129	1153	157	java/lang/Exception
    //   1388	1392	1430	java/lang/Exception
    //   1394	1401	1430	java/lang/Exception
    //   1403	1410	1430	java/lang/Exception
    //   46	54	1443	finally
    //   62	86	1443	finally
    //   222	226	1443	finally
    //   234	242	1443	finally
    //   250	258	1443	finally
    //   287	295	1443	finally
    //   303	327	1443	finally
    //   458	462	1443	finally
    //   470	478	1443	finally
    //   486	494	1443	finally
    //   523	531	1443	finally
    //   539	563	1443	finally
    //   694	698	1443	finally
    //   706	714	1443	finally
    //   722	730	1443	finally
    //   759	767	1443	finally
    //   775	799	1443	finally
    //   930	934	1443	finally
    //   942	950	1443	finally
    //   958	966	1443	finally
    //   995	1003	1443	finally
    //   1011	1035	1443	finally
    //   1166	1170	1443	finally
    //   1178	1186	1443	finally
    //   1194	1202	1443	finally
    //   1231	1240	1443	finally
    //   1253	1257	1443	finally
    //   1274	1283	1443	finally
    //   1291	1300	1443	finally
    //   1308	1316	1443	finally
    //   1324	1333	1443	finally
    //   1341	1351	1443	finally
    //   1359	1382	1443	finally
    //   46	54	1447	java/lang/Exception
    //   62	86	1447	java/lang/Exception
    //   222	226	1447	java/lang/Exception
    //   234	242	1447	java/lang/Exception
    //   250	258	1447	java/lang/Exception
    //   287	295	1447	java/lang/Exception
    //   303	327	1447	java/lang/Exception
    //   458	462	1447	java/lang/Exception
    //   470	478	1447	java/lang/Exception
    //   486	494	1447	java/lang/Exception
    //   523	531	1447	java/lang/Exception
    //   539	563	1447	java/lang/Exception
    //   694	698	1447	java/lang/Exception
    //   706	714	1447	java/lang/Exception
    //   722	730	1447	java/lang/Exception
    //   759	767	1447	java/lang/Exception
    //   775	799	1447	java/lang/Exception
    //   930	934	1447	java/lang/Exception
    //   942	950	1447	java/lang/Exception
    //   958	966	1447	java/lang/Exception
    //   995	1003	1447	java/lang/Exception
    //   1011	1035	1447	java/lang/Exception
    //   1166	1170	1447	java/lang/Exception
    //   1178	1186	1447	java/lang/Exception
    //   1194	1202	1447	java/lang/Exception
    //   1231	1240	1447	java/lang/Exception
    //   1253	1257	1447	java/lang/Exception
    //   1274	1283	1447	java/lang/Exception
    //   1291	1300	1447	java/lang/Exception
    //   1308	1316	1447	java/lang/Exception
    //   1324	1333	1447	java/lang/Exception
    //   1341	1351	1447	java/lang/Exception
    //   1359	1382	1447	java/lang/Exception
    //   1388	1392	1476	finally
    //   1394	1401	1476	finally
    //   1403	1410	1476	finally
    //   1456	1460	1476	finally
    //   1462	1468	1476	finally
    //   144	151	1491	java/lang/Throwable
    //   270	277	1494	java/lang/Throwable
    //   388	395	1497	java/lang/Throwable
    //   506	513	1500	java/lang/Throwable
    //   624	631	1503	java/lang/Throwable
    //   742	749	1506	java/lang/Throwable
    //   860	867	1509	java/lang/Throwable
    //   978	985	1512	java/lang/Throwable
    //   1096	1103	1515	java/lang/Throwable
    //   1214	1221	1518	java/lang/Throwable
    //   1257	1264	1521	java/lang/Throwable
    //   1422	1428	1524	java/lang/Throwable
    //   1435	1441	1527	java/lang/Throwable
    //   1468	1474	1530	java/lang/Throwable
    //   1482	1489	1533	java/lang/Throwable
  }
  
  public static String d()
  {
    char[] arrayOfChar = new char[62];
    int i = (char)'';
    arrayOfChar[0] = i;
    arrayOfChar[1] = ((char)'Õ');
    int j = (char)'×';
    arrayOfChar[2] = j;
    arrayOfChar[3] = ((char)'ß');
    arrayOfChar[4] = ((char)'');
    arrayOfChar[5] = ((char)'Ó');
    arrayOfChar[6] = ((char)'');
    int k = (char)'ê';
    arrayOfChar[7] = k;
    int n = (char)'Í';
    arrayOfChar[8] = n;
    int m = (char)'õ';
    arrayOfChar[9] = m;
    arrayOfChar[10] = ((char)'£');
    int i2 = (char)'';
    arrayOfChar[11] = i2;
    arrayOfChar[12] = ((char)'');
    arrayOfChar[13] = ((char)'ö');
    int i1 = (char)'À';
    arrayOfChar[14] = i1;
    arrayOfChar[15] = ((char)'¶');
    arrayOfChar[16] = i2;
    arrayOfChar[17] = ((char)'û');
    arrayOfChar[18] = ((char)'¼');
    int i3 = (char)'Ø';
    arrayOfChar[19] = i3;
    arrayOfChar[20] = ((char)'');
    arrayOfChar[21] = ((char)'ô');
    arrayOfChar[22] = ((char)'Þ');
    arrayOfChar[23] = ((char)'Ð');
    arrayOfChar[24] = m;
    i2 = (char)'°';
    arrayOfChar[25] = i2;
    arrayOfChar[26] = ((char)'ç');
    m = (char)'Ù';
    arrayOfChar[27] = m;
    arrayOfChar[28] = ((char)'ë');
    arrayOfChar[29] = ((char)'à');
    arrayOfChar[30] = ((char)'©');
    arrayOfChar[31] = ((char)'Ç');
    arrayOfChar[32] = n;
    arrayOfChar[33] = i1;
    arrayOfChar[34] = ((char)'Ì');
    arrayOfChar[35] = i3;
    n = (char)'';
    arrayOfChar[36] = n;
    arrayOfChar[37] = ((char)'â');
    i1 = (char)'';
    arrayOfChar[38] = i1;
    arrayOfChar[39] = i2;
    arrayOfChar[40] = ((char)'³');
    i2 = (char)'¿';
    arrayOfChar[41] = i2;
    arrayOfChar[42] = ((char)'¦');
    arrayOfChar[43] = ((char)'±');
    arrayOfChar[44] = ((char)'Ë');
    arrayOfChar[45] = ((char)'');
    arrayOfChar[46] = n;
    arrayOfChar[47] = ((char)'Ñ');
    arrayOfChar[48] = i2;
    arrayOfChar[49] = ((char)'º');
    arrayOfChar[50] = ((char)'Ú');
    arrayOfChar[51] = j;
    arrayOfChar[52] = k;
    arrayOfChar[53] = i;
    arrayOfChar[54] = ((char)'Ï');
    arrayOfChar[55] = i1;
    arrayOfChar[56] = ((char)'¥');
    arrayOfChar[57] = ((char)'¤');
    arrayOfChar[58] = ((char)'æ');
    arrayOfChar[59] = m;
    arrayOfChar[60] = ((char)'¡');
    arrayOfChar[61] = m;
    return String.valueOf(new char[] { (char)(arrayOfChar[0] ^ 0xFD), (char)(arrayOfChar[1] ^ 0xBA), (char)(arrayOfChar[2] ^ 0xB9), (char)(-arrayOfChar[3] + 339), (char)(-arrayOfChar[4] + 260), (char)(arrayOfChar[5] ^ 0xBD), (char)(-arrayOfChar[6] + 259), (char)(arrayOfChar[7] ^ 0xD0), (char)('▣' / arrayOfChar[8]), (char)(arrayOfChar[9] ^ 0xDA), (char)(-arrayOfChar[10] + 262), (char)(-arrayOfChar[11] + 243), (char)(-arrayOfChar[12] + 257), (char)(arrayOfChar[13] ^ 0xD8), (char)('䣀' / arrayOfChar[14]), (char)('临' / arrayOfChar[15]), (char)(-arrayOfChar[16] + 232), (char)(arrayOfChar[17] ^ 0x89), (char)('冄' / arrayOfChar[18]), (char)(arrayOfChar[19] ^ 0xB1), (char)(arrayOfChar[20] ^ 0xEF), (char)(arrayOfChar[21] ^ 0xDA), (char)('嶨' / arrayOfChar[22]), (char)(-arrayOfChar[23] + 305), (char)('濹' / arrayOfChar[24]), (char)('䮠' / arrayOfChar[25]), (char)('奕' / arrayOfChar[26]), (char)(-arrayOfChar[27] + 321), (char)('岷' / arrayOfChar[28]), (char)(-arrayOfChar[29] + 338), (char)(-arrayOfChar[30] + 220), (char)(-arrayOfChar[31] + 245), (char)(-arrayOfChar[32] + 320), (char)(-arrayOfChar[33] + 293), (char)(arrayOfChar[34] ^ 0xB8), (char)(-arrayOfChar[35] + 332), (char)('㟈' / arrayOfChar[36]), (char)('愜' / arrayOfChar[37]), (char)('㬥' / arrayOfChar[38]), (char)(-arrayOfChar[39] + 291), (char)('⃝' / arrayOfChar[40]), (char)(arrayOfChar[41] ^ 0xD9), (char)(-arrayOfChar[42] + 263), (char)(-arrayOfChar[43] + 295), (char)('堅' / arrayOfChar[44]), (char)(-arrayOfChar[45] + 242), (char)('㟈' / arrayOfChar[46]), (char)('庴' / arrayOfChar[47]), (char)(arrayOfChar[48] ^ 0xDA), (char)(arrayOfChar[49] ^ 0xC9), (char)(-arrayOfChar[50] + 281), (char)(-arrayOfChar[51] + 325), (char)('敶' / arrayOfChar[52]), (char)('䞘' / arrayOfChar[53]), (char)('哧' / arrayOfChar[54]), (char)('㪒' / arrayOfChar[55]), (char)(arrayOfChar[56] ^ 0xDC), (char)(arrayOfChar[57] ^ 0x99), (char)(arrayOfChar[58] ^ 0x92), (char)('悢' / arrayOfChar[59]), (char)(arrayOfChar[60] ^ 0xD4), (char)('喝' / arrayOfChar[61]) });
  }
  
  /* Error */
  private static boolean d(Context paramContext, String paramString)
  {
    // Byte code:
    //   0: new 43	android/content/Intent
    //   3: dup
    //   4: invokespecial 307	android/content/Intent:<init>	()V
    //   7: astore_3
    //   8: aload_3
    //   9: invokestatic 310	com/a/ll/ax:z	()Ljava/lang/String;
    //   12: invokevirtual 61	android/content/Intent:setAction	(Ljava/lang/String;)Landroid/content/Intent;
    //   15: pop
    //   16: aload_3
    //   17: invokestatic 312	com/a/ll/ax:A	()Ljava/lang/String;
    //   20: invokevirtual 315	android/content/Intent:addCategory	(Ljava/lang/String;)Landroid/content/Intent;
    //   23: pop
    //   24: aload_0
    //   25: invokevirtual 115	android/content/Context:getPackageManager	()Landroid/content/pm/PackageManager;
    //   28: aload_3
    //   29: ldc_w 316
    //   32: invokevirtual 320	android/content/pm/PackageManager:queryIntentActivities	(Landroid/content/Intent;I)Ljava/util/List;
    //   35: astore_3
    //   36: new 322	java/util/ArrayList
    //   39: dup
    //   40: invokespecial 323	java/util/ArrayList:<init>	()V
    //   43: astore 4
    //   45: aload_3
    //   46: ifnull +46 -> 92
    //   49: iconst_0
    //   50: istore_2
    //   51: iload_2
    //   52: aload_3
    //   53: invokeinterface 127 1 0
    //   58: if_icmpge +34 -> 92
    //   61: aload 4
    //   63: aload_3
    //   64: iload_2
    //   65: invokeinterface 327 2 0
    //   70: checkcast 329	android/content/pm/ResolveInfo
    //   73: getfield 333	android/content/pm/ResolveInfo:activityInfo	Landroid/content/pm/ActivityInfo;
    //   76: getfield 338	android/content/pm/ActivityInfo:packageName	Ljava/lang/String;
    //   79: invokeinterface 342 2 0
    //   84: pop
    //   85: iload_2
    //   86: iconst_1
    //   87: iadd
    //   88: istore_2
    //   89: goto -38 -> 51
    //   92: aload 4
    //   94: invokeinterface 127 1 0
    //   99: ifgt +5 -> 104
    //   102: iconst_0
    //   103: ireturn
    //   104: aload 4
    //   106: invokeinterface 131 1 0
    //   111: astore 6
    //   113: aload 6
    //   115: invokeinterface 137 1 0
    //   120: ifeq +243 -> 363
    //   123: aload 6
    //   125: invokeinterface 141 1 0
    //   130: checkcast 8	java/lang/String
    //   133: astore 7
    //   135: new 279	java/lang/StringBuilder
    //   138: dup
    //   139: invokespecial 281	java/lang/StringBuilder:<init>	()V
    //   142: astore_3
    //   143: aload_3
    //   144: invokestatic 344	com/a/ll/ax:B	()Ljava/lang/String;
    //   147: invokevirtual 288	java/lang/StringBuilder:append	(Ljava/lang/String;)Ljava/lang/StringBuilder;
    //   150: pop
    //   151: aload_3
    //   152: aload 7
    //   154: invokevirtual 288	java/lang/StringBuilder:append	(Ljava/lang/String;)Ljava/lang/StringBuilder;
    //   157: pop
    //   158: aload_3
    //   159: invokevirtual 294	java/lang/StringBuilder:toString	()Ljava/lang/String;
    //   162: pop
    //   163: aconst_null
    //   164: astore 5
    //   166: aconst_null
    //   167: astore 4
    //   169: aload 4
    //   171: astore_3
    //   172: new 279	java/lang/StringBuilder
    //   175: dup
    //   176: invokespecial 281	java/lang/StringBuilder:<init>	()V
    //   179: astore 8
    //   181: aload 4
    //   183: astore_3
    //   184: aload 8
    //   186: invokestatic 346	com/a/ll/ax:C	()Ljava/lang/String;
    //   189: invokevirtual 288	java/lang/StringBuilder:append	(Ljava/lang/String;)Ljava/lang/StringBuilder;
    //   192: pop
    //   193: aload 4
    //   195: astore_3
    //   196: aload 8
    //   198: aload 7
    //   200: invokevirtual 288	java/lang/StringBuilder:append	(Ljava/lang/String;)Ljava/lang/StringBuilder;
    //   203: pop
    //   204: aload 4
    //   206: astore_3
    //   207: aload 8
    //   209: invokestatic 348	com/a/ll/ax:D	()Ljava/lang/String;
    //   212: invokevirtual 288	java/lang/StringBuilder:append	(Ljava/lang/String;)Ljava/lang/StringBuilder;
    //   215: pop
    //   216: aload 4
    //   218: astore_3
    //   219: aload 8
    //   221: invokevirtual 294	java/lang/StringBuilder:toString	()Ljava/lang/String;
    //   224: astore 7
    //   226: aload 4
    //   228: astore_3
    //   229: aload_0
    //   230: invokevirtual 183	android/content/Context:getContentResolver	()Landroid/content/ContentResolver;
    //   233: aload 7
    //   235: invokestatic 179	android/net/Uri:parse	(Ljava/lang/String;)Landroid/net/Uri;
    //   238: aconst_null
    //   239: invokestatic 350	com/a/ll/ax:E	()Ljava/lang/String;
    //   242: iconst_1
    //   243: anewarray 8	java/lang/String
    //   246: dup
    //   247: iconst_0
    //   248: aload_1
    //   249: aastore
    //   250: aconst_null
    //   251: invokevirtual 191	android/content/ContentResolver:query	(Landroid/net/Uri;[Ljava/lang/String;Ljava/lang/String;[Ljava/lang/String;Ljava/lang/String;)Landroid/database/Cursor;
    //   254: astore 4
    //   256: aload 4
    //   258: ifnull +43 -> 301
    //   261: aload 4
    //   263: invokeinterface 198 1 0
    //   268: ifle +33 -> 301
    //   271: invokestatic 352	com/a/ll/ax:F	()Ljava/lang/String;
    //   274: pop
    //   275: aload 4
    //   277: ifnull +10 -> 287
    //   280: aload 4
    //   282: invokeinterface 201 1 0
    //   287: iconst_1
    //   288: ireturn
    //   289: astore_0
    //   290: aload 4
    //   292: astore_3
    //   293: goto +58 -> 351
    //   296: astore 5
    //   298: goto +30 -> 328
    //   301: aload 4
    //   303: ifnull -190 -> 113
    //   306: aload 4
    //   308: invokeinterface 201 1 0
    //   313: goto -200 -> 113
    //   316: astore_0
    //   317: goto +34 -> 351
    //   320: astore_3
    //   321: aload 5
    //   323: astore 4
    //   325: aload_3
    //   326: astore 5
    //   328: aload 4
    //   330: astore_3
    //   331: aload 5
    //   333: invokevirtual 100	java/lang/Exception:printStackTrace	()V
    //   336: aload 4
    //   338: ifnull -225 -> 113
    //   341: aload 4
    //   343: invokeinterface 201 1 0
    //   348: goto -235 -> 113
    //   351: aload_3
    //   352: ifnull +9 -> 361
    //   355: aload_3
    //   356: invokeinterface 201 1 0
    //   361: aload_0
    //   362: athrow
    //   363: iconst_0
    //   364: ireturn
    // Local variable table:
    //   start	length	slot	name	signature
    //   0	365	0	paramContext	Context
    //   0	365	1	paramString	String
    //   50	39	2	i	int
    //   7	286	3	localObject1	Object
    //   320	6	3	localException1	Exception
    //   330	26	3	localObject2	Object
    //   43	299	4	localObject3	Object
    //   164	1	5	localObject4	Object
    //   296	26	5	localException2	Exception
    //   326	6	5	localException3	Exception
    //   111	13	6	localIterator	Iterator
    //   133	101	7	str	String
    //   179	41	8	localStringBuilder	StringBuilder
    // Exception table:
    //   from	to	target	type
    //   261	275	289	finally
    //   261	275	296	java/lang/Exception
    //   172	181	316	finally
    //   184	193	316	finally
    //   196	204	316	finally
    //   207	216	316	finally
    //   219	226	316	finally
    //   229	256	316	finally
    //   331	336	316	finally
    //   172	181	320	java/lang/Exception
    //   184	193	320	java/lang/Exception
    //   196	204	320	java/lang/Exception
    //   207	216	320	java/lang/Exception
    //   219	226	320	java/lang/Exception
    //   229	256	320	java/lang/Exception
  }
  
  public static String e()
  {
    char[] arrayOfChar = new char[7];
    arrayOfChar[0] = ((char)'þ');
    arrayOfChar[1] = ((char)'ü');
    arrayOfChar[2] = ((char)'¦');
    arrayOfChar[3] = ((char)'');
    arrayOfChar[4] = ((char)'ö');
    arrayOfChar[5] = ((char)'ã');
    arrayOfChar[6] = ((char)'Ä');
    return String.valueOf(new char[] { (char)(arrayOfChar[0] ^ 0x8A), (char)(-arrayOfChar[1] + 357), (char)(-arrayOfChar[2] + 282), (char)('䈼' / arrayOfChar[3]), (char)(-arrayOfChar[4] + 347), (char)(-arrayOfChar[5] + 288), (char)(arrayOfChar[6] ^ 0xFB) });
  }
  
  public static String f()
  {
    char[] arrayOfChar = new char[42];
    int i = (char)'ö';
    arrayOfChar[0] = i;
    arrayOfChar[1] = i;
    arrayOfChar[2] = ((char)'ô');
    i = (char)'';
    arrayOfChar[3] = i;
    arrayOfChar[4] = ((char)'');
    arrayOfChar[5] = ((char)'Ú');
    arrayOfChar[6] = ((char)'°');
    arrayOfChar[7] = ((char)'');
    arrayOfChar[8] = ((char)'Ê');
    arrayOfChar[9] = ((char)'º');
    arrayOfChar[10] = ((char)'é');
    int j = (char)'¬';
    arrayOfChar[11] = j;
    arrayOfChar[12] = ((char)'');
    arrayOfChar[13] = ((char)'è');
    arrayOfChar[14] = ((char)'Æ');
    arrayOfChar[15] = ((char)'Ó');
    arrayOfChar[16] = ((char)'ð');
    arrayOfChar[17] = ((char)'');
    arrayOfChar[18] = ((char)'ÿ');
    arrayOfChar[19] = ((char)'Ð');
    int k = (char)'';
    arrayOfChar[20] = k;
    arrayOfChar[21] = ((char)'ï');
    arrayOfChar[22] = ((char)'ä');
    arrayOfChar[23] = ((char)'¢');
    arrayOfChar[24] = ((char)'');
    arrayOfChar[25] = ((char)'Í');
    arrayOfChar[26] = ((char)'À');
    arrayOfChar[27] = ((char)'¯');
    arrayOfChar[28] = ((char)'ò');
    arrayOfChar[29] = j;
    arrayOfChar[30] = k;
    arrayOfChar[31] = ((char)'');
    arrayOfChar[32] = ((char)'');
    arrayOfChar[33] = ((char)'×');
    arrayOfChar[34] = ((char)'Ë');
    arrayOfChar[35] = ((char)'ú');
    arrayOfChar[36] = ((char)'þ');
    arrayOfChar[37] = ((char)'Ò');
    arrayOfChar[38] = ((char)'Î');
    arrayOfChar[39] = ((char)'í');
    arrayOfChar[40] = ((char)'');
    arrayOfChar[41] = i;
    return String.valueOf(new char[] { (char)(arrayOfChar[0] ^ 0x95), (char)(arrayOfChar[1] ^ 0x99), (char)('柤' / arrayOfChar[2]), (char)('៦' / arrayOfChar[3]), (char)(arrayOfChar[4] ^ 0xF1), (char)('嶬' / arrayOfChar[5]), (char)('䓀' / arrayOfChar[6]), (char)('䛎' / arrayOfChar[7]), (char)(-arrayOfChar[8] + 313), (char)(-arrayOfChar[9] + 291), (char)('嬄' / arrayOfChar[10]), (char)(arrayOfChar[11] ^ 0x82), (char)(arrayOfChar[12] ^ 0xF1), (char)(arrayOfChar[13] ^ 0x89), (char)(arrayOfChar[14] ^ 0xB3), (char)('媪' / arrayOfChar[15]), (char)('峐' / arrayOfChar[16]), (char)(arrayOfChar[17] ^ 0xF1), (char)(-arrayOfChar[18] + 356), (char)(-arrayOfChar[19] + 322), (char)(-arrayOfChar[20] + 203), (char)(-arrayOfChar[21] + 285), (char)('晬' / arrayOfChar[22]), (char)(-arrayOfChar[23] + 263), (char)('㽰' / arrayOfChar[24]), (char)('峤' / arrayOfChar[25]), (char)(-arrayOfChar[26] + 297), (char)('䬲' / arrayOfChar[27]), (char)('慞' / arrayOfChar[28]), (char)(arrayOfChar[29] ^ 0xDF), (char)('≰' / arrayOfChar[30]), (char)('፠' / arrayOfChar[31]), (char)(-arrayOfChar[32] + 248), (char)('崹' / arrayOfChar[33]), (char)(-arrayOfChar[34] + 320), (char)('歬' / arrayOfChar[35]), (char)(-arrayOfChar[36] + 370), (char)(-arrayOfChar[37] + 242), (char)(arrayOfChar[38] ^ 0xF3), (char)('ᶠ' / arrayOfChar[39]), (char)(arrayOfChar[40] ^ 0xB6), (char)(arrayOfChar[41] ^ 0xE1) });
  }
  
  public static String g()
  {
    char[] arrayOfChar = new char[68];
    arrayOfChar[0] = ((char)'»');
    arrayOfChar[1] = ((char)'');
    arrayOfChar[2] = ((char)'');
    arrayOfChar[3] = ((char)'¹');
    arrayOfChar[4] = ((char)'¼');
    int n = (char)'º';
    arrayOfChar[5] = n;
    int m = (char)'¯';
    arrayOfChar[6] = m;
    arrayOfChar[7] = ((char)'Ò');
    arrayOfChar[8] = ((char)'');
    int j = (char)'ú';
    arrayOfChar[9] = j;
    arrayOfChar[10] = ((char)'õ');
    int k = (char)'¥';
    arrayOfChar[11] = k;
    arrayOfChar[12] = ((char)'Ä');
    int i = (char)'²';
    arrayOfChar[13] = i;
    arrayOfChar[14] = n;
    arrayOfChar[15] = ((char)'');
    arrayOfChar[16] = ((char)'');
    arrayOfChar[17] = ((char)'¸');
    arrayOfChar[18] = ((char)'');
    n = (char)'±';
    arrayOfChar[19] = n;
    arrayOfChar[20] = ((char)'£');
    arrayOfChar[21] = ((char)'¶');
    int i1 = (char)'É';
    arrayOfChar[22] = i1;
    int i2 = (char)'';
    arrayOfChar[23] = i2;
    arrayOfChar[24] = m;
    arrayOfChar[25] = ((char)'ÿ');
    arrayOfChar[26] = ((char)'¦');
    arrayOfChar[27] = ((char)'');
    arrayOfChar[28] = m;
    arrayOfChar[29] = ((char)'Ö');
    arrayOfChar[30] = ((char)'');
    arrayOfChar[31] = i2;
    arrayOfChar[32] = i;
    arrayOfChar[33] = ((char)'÷');
    arrayOfChar[34] = ((char)'ì');
    m = (char)'ç';
    arrayOfChar[35] = m;
    arrayOfChar[36] = ((char)'');
    arrayOfChar[37] = ((char)'');
    arrayOfChar[38] = ((char)'');
    arrayOfChar[39] = k;
    arrayOfChar[40] = ((char)'½');
    arrayOfChar[41] = ((char)'é');
    arrayOfChar[42] = ((char)'â');
    arrayOfChar[43] = i1;
    arrayOfChar[44] = ((char)'«');
    arrayOfChar[45] = n;
    arrayOfChar[46] = ((char)'Á');
    arrayOfChar[47] = ((char)'¾');
    arrayOfChar[48] = ((char)'©');
    arrayOfChar[49] = ((char)'');
    arrayOfChar[50] = ((char)'');
    arrayOfChar[51] = ((char)'');
    arrayOfChar[52] = ((char)'Ø');
    arrayOfChar[53] = j;
    arrayOfChar[54] = m;
    j = (char)'µ';
    arrayOfChar[55] = j;
    arrayOfChar[56] = ((char)'À');
    arrayOfChar[57] = j;
    arrayOfChar[58] = ((char)'Æ');
    arrayOfChar[59] = i;
    arrayOfChar[60] = ((char)'');
    arrayOfChar[61] = ((char)'ý');
    arrayOfChar[62] = ((char)'ô');
    arrayOfChar[63] = ((char)'è');
    arrayOfChar[64] = ((char)'®');
    arrayOfChar[65] = ((char)'´');
    arrayOfChar[66] = ((char)'ü');
    arrayOfChar[67] = ((char)'Ú');
    return String.valueOf(new char[] { (char)(arrayOfChar[0] ^ 0xD8), (char)('䌵' / arrayOfChar[1]), (char)('䅐' / arrayOfChar[2]), (char)(-arrayOfChar[3] + 301), (char)(arrayOfChar[4] ^ 0xD9), (char)(arrayOfChar[5] ^ 0xD4), (char)(arrayOfChar[6] ^ 0xDB), (char)(-arrayOfChar[7] + 268), (char)(arrayOfChar[8] ^ 0xBD), (char)('ⷦ' / arrayOfChar[9]), (char)(arrayOfChar[10] ^ 0x96), (char)('䞋' / arrayOfChar[11]), (char)(arrayOfChar[12] ^ 0xA9), (char)(-arrayOfChar[13] + 224), (char)(-arrayOfChar[14] + 289), (char)(-arrayOfChar[15] + 240), (char)('㭧' / arrayOfChar[16]), (char)(-arrayOfChar[17] + 287), (char)(-arrayOfChar[18] + 242), (char)('䗕' / arrayOfChar[19]), (char)(arrayOfChar[20] ^ 0x8D), (char)(arrayOfChar[21] ^ 0xD7), (char)('噞' / arrayOfChar[22]), (char)('㸜' / arrayOfChar[23]), (char)(-arrayOfChar[24] + 289), (char)(arrayOfChar[25] ^ 0x90), (char)(arrayOfChar[26] ^ 0xCF), (char)(arrayOfChar[27] ^ 0xF8), (char)('ὲ' / arrayOfChar[28]), (char)(-arrayOfChar[29] + 322), (char)('㤷' / arrayOfChar[30]), (char)(-arrayOfChar[31] + 276), (char)(arrayOfChar[32] ^ 0xDC), (char)('待' / arrayOfChar[33]), (char)(-arrayOfChar[34] + 340), (char)('嬣' / arrayOfChar[35]), (char)(-arrayOfChar[36] + 247), (char)(-arrayOfChar[37] + 189), (char)('䈉' / arrayOfChar[38]), (char)('䄙' / arrayOfChar[39]), (char)('喤' / arrayOfChar[40]), (char)('榔' / arrayOfChar[41]), (char)('岲' / arrayOfChar[42]), (char)(-arrayOfChar[43] + 311), (char)('䓍' / arrayOfChar[44]), (char)(arrayOfChar[45] ^ 0xC2), (char)('⍯' / arrayOfChar[46]), (char)('䮴' / arrayOfChar[47]), (char)(arrayOfChar[48] ^ 0xC8), (char)(-arrayOfChar[49] + 249), (char)('㲴' / arrayOfChar[50]), (char)('䐢' / arrayOfChar[51]), (char)('墘' / arrayOfChar[52]), (char)('煈' / arrayOfChar[53]), (char)('嬣' / arrayOfChar[54]), (char)('兏' / arrayOfChar[55]), (char)(-arrayOfChar[56] + 255), (char)(-arrayOfChar[57] + 291), (char)(-arrayOfChar[58] + 309), (char)('储' / arrayOfChar[59]), (char)(-arrayOfChar[60] + 233), (char)('擎' / arrayOfChar[61]), (char)(arrayOfChar[62] ^ 0x8D), (char)('㝈' / arrayOfChar[63]), (char)(arrayOfChar[64] ^ 0xDA), (char)('倨' / arrayOfChar[65]), (char)(-arrayOfChar[66] + 369), (char)(arrayOfChar[67] ^ 0xBF) });
  }
  
  public static String h()
  {
    char[] arrayOfChar = new char[7];
    arrayOfChar[0] = ((char)'´');
    arrayOfChar[1] = ((char)'Ñ');
    arrayOfChar[2] = ((char)'¶');
    arrayOfChar[3] = ((char)'¬');
    arrayOfChar[4] = ((char)'â');
    arrayOfChar[5] = ((char)'');
    arrayOfChar[6] = ((char)'ì');
    return String.valueOf(new char[] { (char)(arrayOfChar[0] ^ 0xC0), (char)('喹' / arrayOfChar[1]), (char)('剸' / arrayOfChar[2]), (char)('䢐' / arrayOfChar[3]), (char)(arrayOfChar[4] ^ 0x87), (char)(arrayOfChar[5] ^ 0xBE), (char)(arrayOfChar[6] ^ 0xD3) });
  }
  
  public static String i()
  {
    char[] arrayOfChar = new char[40];
    arrayOfChar[0] = ((char)'Ä');
    int i = (char)'å';
    arrayOfChar[1] = i;
    arrayOfChar[2] = ((char)'£');
    arrayOfChar[3] = ((char)'Ð');
    arrayOfChar[4] = ((char)'ä');
    arrayOfChar[5] = ((char)'');
    arrayOfChar[6] = i;
    arrayOfChar[7] = ((char)'');
    arrayOfChar[8] = ((char)'´');
    i = (char)'Ù';
    arrayOfChar[9] = i;
    arrayOfChar[10] = ((char)'ÿ');
    arrayOfChar[11] = ((char)'Ã');
    arrayOfChar[12] = ((char)'Î');
    arrayOfChar[13] = ((char)'Â');
    arrayOfChar[14] = ((char)'á');
    int j = (char)'À';
    arrayOfChar[15] = j;
    arrayOfChar[16] = ((char)'ó');
    arrayOfChar[17] = ((char)'¨');
    arrayOfChar[18] = j;
    arrayOfChar[19] = i;
    arrayOfChar[20] = i;
    i = (char)'®';
    arrayOfChar[21] = i;
    arrayOfChar[22] = ((char)'Û');
    arrayOfChar[23] = ((char)'Ñ');
    arrayOfChar[24] = ((char)'¹');
    arrayOfChar[25] = ((char)'');
    arrayOfChar[26] = ((char)'');
    arrayOfChar[27] = ((char)'ç');
    arrayOfChar[28] = ((char)'');
    j = (char)'';
    arrayOfChar[29] = j;
    arrayOfChar[30] = ((char)'Á');
    arrayOfChar[31] = i;
    arrayOfChar[32] = j;
    arrayOfChar[33] = ((char)'Ë');
    arrayOfChar[34] = ((char)'ë');
    arrayOfChar[35] = ((char)'Ú');
    arrayOfChar[36] = ((char)'');
    arrayOfChar[37] = ((char)'');
    arrayOfChar[38] = ((char)'');
    arrayOfChar[39] = ((char)'Æ');
    return String.valueOf(new char[] { (char)(arrayOfChar[0] ^ 0xA7), (char)(arrayOfChar[1] ^ 0x8A), (char)(-arrayOfChar[2] + 272), (char)(-arrayOfChar[3] + 254), (char)(-arrayOfChar[4] + 331), (char)(-arrayOfChar[5] + 241), (char)('捋' / arrayOfChar[6]), (char)(-arrayOfChar[7] + 261), (char)(arrayOfChar[8] ^ 0xD8), (char)(-arrayOfChar[9] + 318), (char)(arrayOfChar[10] ^ 0xD1), (char)('剄' / arrayOfChar[11]), (char)(-arrayOfChar[12] + 303), (char)('墪' / arrayOfChar[13]), (char)(arrayOfChar[14] ^ 0x8F), (char)(-arrayOfChar[15] + 291), (char)('抸' / arrayOfChar[16]), (char)(-arrayOfChar[17] + 269), (char)('喀' / arrayOfChar[18]), (char)('⛾' / arrayOfChar[19]), (char)(arrayOfChar[20] ^ 0xAA), (char)(arrayOfChar[21] ^ 0xCB), (char)('挼' / arrayOfChar[22]), (char)('庴' / arrayOfChar[23]), (char)(arrayOfChar[24] ^ 0xD0), (char)(arrayOfChar[25] ^ 0xFD), (char)(-arrayOfChar[26] + 246), (char)(arrayOfChar[27] ^ 0x94), (char)('⇼' / arrayOfChar[28]), (char)('ፀ' / arrayOfChar[29]), (char)('䪣' / arrayOfChar[30]), (char)(arrayOfChar[31] ^ 0xC1), (char)(arrayOfChar[32] ^ 0xEF), (char)(-arrayOfChar[33] + 313), (char)(arrayOfChar[34] ^ 0x9F), (char)('ᭀ' / arrayOfChar[35]), (char)(arrayOfChar[36] ^ 0xBD), (char)('ᄀ' / arrayOfChar[37]), (char)('ᚌ' / arrayOfChar[38]), (char)('䵘' / arrayOfChar[39]) });
  }
  
  public static String j()
  {
    char[] arrayOfChar = new char[59];
    arrayOfChar[0] = ((char)'¢');
    arrayOfChar[1] = ((char)'Ö');
    arrayOfChar[2] = ((char)'Ò');
    arrayOfChar[3] = ((char)'Ð');
    arrayOfChar[4] = ((char)'°');
    int i = (char)'À';
    arrayOfChar[5] = i;
    arrayOfChar[6] = ((char)' ');
    arrayOfChar[7] = ((char)'');
    arrayOfChar[8] = ((char)'ü');
    int k = (char)'È';
    arrayOfChar[9] = k;
    arrayOfChar[10] = ((char)'´');
    arrayOfChar[11] = i;
    int m = (char)'Ì';
    arrayOfChar[12] = m;
    arrayOfChar[13] = ((char)'ë');
    arrayOfChar[14] = ((char)'');
    arrayOfChar[15] = ((char)'ª');
    arrayOfChar[16] = ((char)127);
    arrayOfChar[17] = ((char)'Ä');
    arrayOfChar[18] = ((char)'');
    arrayOfChar[19] = ((char)'ì');
    int n = (char)'í';
    arrayOfChar[20] = n;
    i = (char)'²';
    arrayOfChar[21] = i;
    arrayOfChar[22] = n;
    arrayOfChar[23] = ((char)'');
    arrayOfChar[24] = ((char)'Ñ');
    int j = (char)'';
    arrayOfChar[25] = j;
    arrayOfChar[26] = k;
    arrayOfChar[27] = ((char)'Û');
    arrayOfChar[28] = ((char)'¿');
    arrayOfChar[29] = m;
    arrayOfChar[30] = m;
    arrayOfChar[31] = n;
    arrayOfChar[32] = ((char)'É');
    arrayOfChar[33] = ((char)'');
    arrayOfChar[34] = ((char)'û');
    arrayOfChar[35] = ((char)'Ý');
    arrayOfChar[36] = ((char)'Ù');
    arrayOfChar[37] = ((char)'');
    arrayOfChar[38] = ((char)'Ë');
    arrayOfChar[39] = ((char)'ä');
    k = (char)'þ';
    arrayOfChar[40] = k;
    arrayOfChar[41] = k;
    arrayOfChar[42] = ((char)'¼');
    arrayOfChar[43] = ((char)'ø');
    k = (char)'æ';
    arrayOfChar[44] = k;
    arrayOfChar[45] = ((char)'');
    arrayOfChar[46] = ((char)'¤');
    m = (char)'¸';
    arrayOfChar[47] = m;
    arrayOfChar[48] = i;
    arrayOfChar[49] = m;
    arrayOfChar[50] = ((char)'ù');
    arrayOfChar[51] = ((char)'£');
    arrayOfChar[52] = ((char)'×');
    arrayOfChar[53] = j;
    arrayOfChar[54] = k;
    arrayOfChar[55] = ((char)'µ');
    arrayOfChar[56] = ((char)'');
    arrayOfChar[57] = ((char)'');
    arrayOfChar[58] = ((char)'©');
    return String.valueOf(new char[] { (char)('㺦' / arrayOfChar[0]), (char)(arrayOfChar[1] ^ 0xB9), (char)(arrayOfChar[2] ^ 0xBC), (char)(-arrayOfChar[3] + 324), (char)(arrayOfChar[4] ^ 0xD5), (char)(-arrayOfChar[5] + 302), (char)(arrayOfChar[6] ^ 0xD4), (char)('Ḣ' / arrayOfChar[7]), (char)('⹄' / arrayOfChar[8]), (char)(arrayOfChar[9] ^ 0xE7), (char)('䖜' / arrayOfChar[10]), (char)('區' / arrayOfChar[11]), (char)(-arrayOfChar[12] + 313), (char)(-arrayOfChar[13] + 281), (char)(-arrayOfChar[14] + 256), (char)(arrayOfChar[15] ^ 0xC3), (char)(arrayOfChar[16] ^ 0x17), (char)(arrayOfChar[17] ^ 0xAB), (char)(-arrayOfChar[18] + 255), (char)(arrayOfChar[19] ^ 0xDF), (char)(arrayOfChar[20] ^ 0xDB), (char)(arrayOfChar[21] ^ 0x82), (char)(arrayOfChar[22] ^ 0xC3), (char)(arrayOfChar[23] ^ 0xFE), (char)(arrayOfChar[24] ^ 0xBE), (char)(arrayOfChar[25] ^ 0xFF), (char)(-arrayOfChar[26] + 301), (char)('⫆' / arrayOfChar[27]), (char)(-arrayOfChar[28] + 237), (char)(arrayOfChar[29] ^ 0xBF), (char)(arrayOfChar[30] ^ 0xA9), (char)(arrayOfChar[31] ^ 0x99), (char)(arrayOfChar[32] ^ 0xBD), (char)('㼪' / arrayOfChar[33]), (char)(-arrayOfChar[34] + 361), (char)('士' / arrayOfChar[35]), (char)(-arrayOfChar[36] + 332), (char)(arrayOfChar[37] ^ 0xB3), (char)(-arrayOfChar[38] + 305), (char)('噤' / arrayOfChar[39]), (char)(-arrayOfChar[40] + 372), (char)('渢' / arrayOfChar[41]), (char)(-arrayOfChar[42] + 302), (char)('斸' / arrayOfChar[43]), (char)('核' / arrayOfChar[44]), (char)(-arrayOfChar[45] + 237), (char)(arrayOfChar[46] ^ 0xD7), (char)(arrayOfChar[47] ^ 0x87), (char)(-arrayOfChar[48] + 288), (char)('俈' / arrayOfChar[49]), (char)('烔' / arrayOfChar[50]), (char)(arrayOfChar[51] ^ 0xCA), (char)(-arrayOfChar[52] + 317), (char)('䔂' / arrayOfChar[53]), (char)(arrayOfChar[54] ^ 0xDB), (char)('刄' / arrayOfChar[55]), (char)('㻊' / arrayOfChar[56]), (char)(arrayOfChar[57] ^ 0xE1), (char)('䊭' / arrayOfChar[58]) });
  }
  
  public static String k()
  {
    char[] arrayOfChar = new char[7];
    arrayOfChar[0] = ((char)'¥');
    int i = (char)'ä';
    arrayOfChar[1] = i;
    arrayOfChar[2] = ((char)'Ç');
    arrayOfChar[3] = ((char)'');
    arrayOfChar[4] = ((char)'î');
    arrayOfChar[5] = i;
    arrayOfChar[6] = ((char)'');
    return String.valueOf(new char[] { (char)('䫄' / arrayOfChar[0]), (char)(arrayOfChar[1] ^ 0x8D), (char)(arrayOfChar[2] ^ 0xB3), (char)(arrayOfChar[3] ^ 0xF0), (char)(-arrayOfChar[4] + 339), (char)(-arrayOfChar[5] + 289), (char)(arrayOfChar[6] ^ 0xBD) });
  }
  
  public static String l()
  {
    char[] arrayOfChar = new char[39];
    arrayOfChar[0] = ((char)'');
    arrayOfChar[1] = ((char)'Ý');
    arrayOfChar[2] = ((char)'Ç');
    arrayOfChar[3] = ((char)'Ë');
    arrayOfChar[4] = ((char)'');
    arrayOfChar[5] = ((char)'');
    arrayOfChar[6] = ((char)'¾');
    arrayOfChar[7] = ((char)'­');
    int i = (char)'¤';
    arrayOfChar[8] = i;
    arrayOfChar[9] = ((char)'');
    arrayOfChar[10] = ((char)'°');
    arrayOfChar[11] = ((char)'Â');
    arrayOfChar[12] = ((char)'õ');
    arrayOfChar[13] = ((char)'î');
    int j = (char)'ê';
    arrayOfChar[14] = j;
    arrayOfChar[15] = ((char)'ü');
    int k = (char)'';
    arrayOfChar[16] = k;
    arrayOfChar[17] = ((char)'À');
    arrayOfChar[18] = ((char)'Ñ');
    arrayOfChar[19] = i;
    arrayOfChar[20] = ((char)'Ò');
    arrayOfChar[21] = k;
    arrayOfChar[22] = ((char)'¹');
    arrayOfChar[23] = ((char)'ì');
    arrayOfChar[24] = ((char)'é');
    arrayOfChar[25] = ((char)'û');
    arrayOfChar[26] = ((char)'³');
    arrayOfChar[27] = ((char)'');
    arrayOfChar[28] = ((char)'®');
    arrayOfChar[29] = ((char)' ');
    arrayOfChar[30] = ((char)'Æ');
    arrayOfChar[31] = ((char)'È');
    arrayOfChar[32] = ((char)'');
    arrayOfChar[33] = j;
    arrayOfChar[34] = ((char)'í');
    arrayOfChar[35] = ((char)'');
    arrayOfChar[36] = ((char)'Ã');
    arrayOfChar[37] = ((char)'ß');
    arrayOfChar[38] = k;
    return String.valueOf(new char[] { (char)('㕞' / arrayOfChar[0]), (char)(-arrayOfChar[1] + 332), (char)(-arrayOfChar[2] + 308), (char)(-arrayOfChar[3] + 249), (char)(-arrayOfChar[4] + 257), (char)(arrayOfChar[5] ^ 0xE2), (char)(arrayOfChar[6] ^ 0xD6), (char)(arrayOfChar[7] ^ 0xC2), (char)('䜜' / arrayOfChar[8]), (char)(arrayOfChar[9] ^ 0xAD), (char)(arrayOfChar[10] ^ 0x86), (char)(arrayOfChar[11] ^ 0xF2), (char)('Ⰶ' / arrayOfChar[12]), (char)(arrayOfChar[13] ^ 0x86), (char)(arrayOfChar[14] ^ 0x85), (char)('歌' / arrayOfChar[15]), (char)('㕃' / arrayOfChar[16]), (char)('▀' / arrayOfChar[17]), (char)('▎' / arrayOfChar[18]), (char)(-arrayOfChar[19] + 279), (char)(-arrayOfChar[20] + 311), (char)(arrayOfChar[21] ^ 0xF3), (char)(arrayOfChar[22] ^ 0xCD), (char)(arrayOfChar[23] ^ 0x85), (char)(arrayOfChar[24] ^ 0x87), (char)('擽' / arrayOfChar[25]), (char)(arrayOfChar[26] ^ 0xC0), (char)('Ḣ' / arrayOfChar[27]), (char)(-arrayOfChar[28] + 206), (char)('㷠' / arrayOfChar[29]), (char)('嗚' / arrayOfChar[30]), (char)('孨' / arrayOfChar[31]), (char)('䃢' / arrayOfChar[32]), (char)('樈' / arrayOfChar[33]), (char)('ᶠ' / arrayOfChar[34]), (char)(-arrayOfChar[35] + 208), (char)(-arrayOfChar[36] + 227), (char)('※' / arrayOfChar[37]), (char)(arrayOfChar[38] ^ 0xE3) });
  }
  
  public static String m()
  {
    char[] arrayOfChar = new char[67];
    arrayOfChar[0] = ((char)'ä');
    int i2 = (char)'¡';
    arrayOfChar[1] = i2;
    arrayOfChar[2] = ((char)'ð');
    arrayOfChar[3] = ((char)'');
    arrayOfChar[4] = ((char)'');
    arrayOfChar[5] = ((char)'°');
    arrayOfChar[6] = ((char)'¸');
    arrayOfChar[7] = ((char)'¹');
    arrayOfChar[8] = ((char)'Ê');
    arrayOfChar[9] = ((char)'');
    arrayOfChar[10] = ((char)'');
    arrayOfChar[11] = ((char)'ß');
    int i3 = (char)'ç';
    arrayOfChar[12] = i3;
    arrayOfChar[13] = ((char)127);
    int i = (char)'';
    arrayOfChar[14] = i;
    arrayOfChar[15] = i;
    i = (char)'Ì';
    arrayOfChar[16] = i;
    arrayOfChar[17] = i;
    arrayOfChar[18] = ((char)'Ø');
    arrayOfChar[19] = ((char)'à');
    int j = (char)'ñ';
    arrayOfChar[20] = j;
    int k = (char)'è';
    arrayOfChar[21] = k;
    arrayOfChar[22] = ((char)'');
    arrayOfChar[23] = ((char)'ú');
    int m = (char)'å';
    arrayOfChar[24] = m;
    arrayOfChar[25] = ((char)'');
    arrayOfChar[26] = ((char)'');
    arrayOfChar[27] = ((char)'Î');
    arrayOfChar[28] = ((char)'Ð');
    arrayOfChar[29] = ((char)'¢');
    arrayOfChar[30] = ((char)'');
    int n = (char)'÷';
    arrayOfChar[31] = n;
    arrayOfChar[32] = ((char)'');
    int i1 = (char)'¼';
    arrayOfChar[33] = i1;
    arrayOfChar[34] = ((char)'Ä');
    arrayOfChar[35] = ((char)' ');
    arrayOfChar[36] = ((char)'');
    arrayOfChar[37] = ((char)'½');
    arrayOfChar[38] = i3;
    arrayOfChar[39] = ((char)'ÿ');
    arrayOfChar[40] = i2;
    arrayOfChar[41] = ((char)'þ');
    arrayOfChar[42] = i2;
    arrayOfChar[43] = ((char)'ì');
    i2 = (char)'';
    arrayOfChar[44] = i2;
    arrayOfChar[45] = ((char)'º');
    arrayOfChar[46] = ((char)'Æ');
    arrayOfChar[47] = ((char)'¥');
    i3 = (char)'ê';
    arrayOfChar[48] = i3;
    arrayOfChar[49] = m;
    arrayOfChar[50] = ((char)'¶');
    arrayOfChar[51] = ((char)'é');
    arrayOfChar[52] = ((char)'Ý');
    arrayOfChar[53] = ((char)'Ç');
    arrayOfChar[54] = ((char)'¾');
    arrayOfChar[55] = i1;
    arrayOfChar[56] = j;
    arrayOfChar[57] = k;
    arrayOfChar[58] = ((char)'©');
    arrayOfChar[59] = ((char)'');
    arrayOfChar[60] = i;
    arrayOfChar[61] = i2;
    arrayOfChar[62] = ((char)'Ù');
    arrayOfChar[63] = n;
    arrayOfChar[64] = ((char)'³');
    arrayOfChar[65] = ((char)'');
    arrayOfChar[66] = i3;
    return String.valueOf(new char[] { (char)('堬' / arrayOfChar[0]), (char)(arrayOfChar[1] ^ 0xCE), (char)(arrayOfChar[2] ^ 0x9E), (char)('㨀' / arrayOfChar[3]), (char)(-arrayOfChar[4] + 245), (char)('䮠' / arrayOfChar[5]), (char)(arrayOfChar[6] ^ 0xCC), (char)(-arrayOfChar[7] + 243), (char)('┖' / arrayOfChar[8]), (char)('Ფ' / arrayOfChar[9]), (char)('㛪' / arrayOfChar[10]), (char)(-arrayOfChar[11] + 334), (char)('扛' / arrayOfChar[12]), (char)(-arrayOfChar[13] + 173), (char)('䑫' / arrayOfChar[14]), (char)(arrayOfChar[15] ^ 0xF2), (char)(-arrayOfChar[16] + 308), (char)('塴' / arrayOfChar[17]), (char)(-arrayOfChar[18] + 327), (char)('Ⲡ' / arrayOfChar[19]), (char)('㋖' / arrayOfChar[20]), (char)('⮀' / arrayOfChar[21]), (char)(arrayOfChar[22] ^ 0xA2), (char)(-arrayOfChar[23] + 354), (char)(arrayOfChar[24] ^ 0x8A), (char)('㼄' / arrayOfChar[25]), (char)(-arrayOfChar[26] + 251), (char)('┄' / arrayOfChar[27]), (char)('埀' / arrayOfChar[28]), (char)(-arrayOfChar[29] + 259), (char)('䌯' / arrayOfChar[30]), (char)('樢' / arrayOfChar[31]), (char)(arrayOfChar[32] ^ 0xFA), (char)(-arrayOfChar[33] + 292), (char)(-arrayOfChar[34] + 297), (char)('䝀' / arrayOfChar[35]), (char)(-arrayOfChar[36] + 180), (char)(arrayOfChar[37] ^ 0xCE), (char)(-arrayOfChar[38] + 332), (char)(arrayOfChar[39] ^ 0x8B), (char)(arrayOfChar[40] ^ 0xD5), (char)('栮' / arrayOfChar[41]), (char)(-arrayOfChar[42] + 271), (char)(-arrayOfChar[43] + 339), (char)(-arrayOfChar[44] + 250), (char)(-arrayOfChar[45] + 233), (char)(-arrayOfChar[46] + 300), (char)(arrayOfChar[47] ^ 0xC4), (char)('毜' / arrayOfChar[48]), (char)(-arrayOfChar[49] + 340), (char)(arrayOfChar[50] ^ 0xC4), (char)(-arrayOfChar[51] + 338), (char)(arrayOfChar[52] ^ 0xA9), (char)(arrayOfChar[53] ^ 0xA2), (char)(-arrayOfChar[54] + 305), (char)(-arrayOfChar[55] + 251), (char)('枎' / arrayOfChar[56]), (char)('撘' / arrayOfChar[57]), (char)(-arrayOfChar[58] + 285), (char)(-arrayOfChar[59] + 256), (char)(arrayOfChar[60] ^ 0xAA), (char)(-arrayOfChar[61] + 256), (char)(arrayOfChar[62] ^ 0xE4), (char)(-arrayOfChar[63] + 363), (char)(-arrayOfChar[64] + 293), (char)(arrayOfChar[65] ^ 0xFA), (char)('屒' / arrayOfChar[66]) });
  }
  
  public static String n()
  {
    char[] arrayOfChar = new char[7];
    arrayOfChar[0] = ((char)'Ò');
    arrayOfChar[1] = ((char)'º');
    arrayOfChar[2] = ((char)'µ');
    arrayOfChar[3] = ((char)'Ð');
    arrayOfChar[4] = ((char)'Ö');
    arrayOfChar[5] = ((char)'À');
    arrayOfChar[6] = ((char)'');
    return String.valueOf(new char[] { (char)(arrayOfChar[0] ^ 0xA6), (char)(arrayOfChar[1] ^ 0xD3), (char)(arrayOfChar[2] ^ 0xC1), (char)('埀' / arrayOfChar[3]), (char)('呮' / arrayOfChar[4]), (char)(-arrayOfChar[5] + 253), (char)(-arrayOfChar[6] + 207) });
  }
  
  public static String o()
  {
    char[] arrayOfChar = new char[47];
    arrayOfChar[0] = ((char)'å');
    arrayOfChar[1] = ((char)'¤');
    arrayOfChar[2] = ((char)'Þ');
    int i = (char)'¯';
    arrayOfChar[3] = i;
    int j = (char)'Õ';
    arrayOfChar[4] = j;
    int m = (char)'Ø';
    arrayOfChar[5] = m;
    arrayOfChar[6] = ((char)'»');
    arrayOfChar[7] = ((char)'');
    arrayOfChar[8] = ((char)'õ');
    arrayOfChar[9] = ((char)'Á');
    arrayOfChar[10] = ((char)'¿');
    arrayOfChar[11] = ((char)'Î');
    arrayOfChar[12] = ((char)'½');
    int k = (char)'Ä';
    arrayOfChar[13] = k;
    arrayOfChar[14] = m;
    arrayOfChar[15] = ((char)'Ù');
    arrayOfChar[16] = ((char)'×');
    arrayOfChar[17] = ((char)'');
    m = (char)'';
    arrayOfChar[18] = m;
    int n = (char)'³';
    arrayOfChar[19] = n;
    arrayOfChar[20] = ((char)'¹');
    arrayOfChar[21] = ((char)'­');
    arrayOfChar[22] = ((char)'¸');
    arrayOfChar[23] = ((char)'Ò');
    arrayOfChar[24] = ((char)'ª');
    arrayOfChar[25] = ((char)'¦');
    arrayOfChar[26] = ((char)'Û');
    arrayOfChar[27] = ((char)'§');
    arrayOfChar[28] = ((char)'¶');
    arrayOfChar[29] = ((char)'');
    arrayOfChar[30] = ((char)'¾');
    arrayOfChar[31] = k;
    arrayOfChar[32] = ((char)'ò');
    arrayOfChar[33] = j;
    arrayOfChar[34] = ((char)'ú');
    arrayOfChar[35] = ((char)'Â');
    arrayOfChar[36] = ((char)'í');
    arrayOfChar[37] = ((char)'ñ');
    arrayOfChar[38] = ((char)'Æ');
    arrayOfChar[39] = i;
    arrayOfChar[40] = ((char)'²');
    i = (char)'ë';
    arrayOfChar[41] = i;
    arrayOfChar[42] = m;
    arrayOfChar[43] = i;
    arrayOfChar[44] = n;
    arrayOfChar[45] = ((char)'');
    arrayOfChar[46] = ((char)'ô');
    return String.valueOf(new char[] { (char)(arrayOfChar[0] ^ 0x86), (char)(-arrayOfChar[1] + 275), (char)('庆' / arrayOfChar[2]), (char)(-arrayOfChar[3] + 221), (char)(-arrayOfChar[4] + 326), (char)(arrayOfChar[5] ^ 0xB1), (char)('䯸' / arrayOfChar[6]), (char)(-arrayOfChar[7] + 239), (char)(arrayOfChar[8] ^ 0x9A), (char)(-arrayOfChar[9] + 244), (char)(arrayOfChar[10] ^ 0x89), (char)(arrayOfChar[11] ^ 0xFE), (char)(-arrayOfChar[12] + 235), (char)(-arrayOfChar[13] + 300), (char)('嶨' / arrayOfChar[14]), (char)('履' / arrayOfChar[15]), (char)(arrayOfChar[16] ^ 0xB2), (char)(arrayOfChar[17] ^ 0xA5), (char)(arrayOfChar[18] ^ 0xFE), (char)('䏓' / arrayOfChar[19]), (char)('咍' / arrayOfChar[20]), (char)(-arrayOfChar[21] + 283), (char)(-arrayOfChar[22] + 283), (char)(arrayOfChar[23] ^ 0xBA), (char)('䌒' / arrayOfChar[24]), (char)(-arrayOfChar[25] + 280), (char)(-arrayOfChar[26] + 265), (char)(arrayOfChar[27] ^ 0xD4), (char)('䟎' / arrayOfChar[28]), (char)('䆴' / arrayOfChar[29]), (char)(-arrayOfChar[30] + 306), (char)(-arrayOfChar[31] + 301), (char)('柼' / arrayOfChar[32]), (char)(-arrayOfChar[33] + 316), (char)(-arrayOfChar[34] + 365), (char)('⯴' / arrayOfChar[35]), (char)(-arrayOfChar[36] + 269), (char)(-arrayOfChar[37] + 340), (char)(-arrayOfChar[38] + 309), (char)('俻' / arrayOfChar[39]), (char)(-arrayOfChar[40] + 288), (char)(-arrayOfChar[41] + 351), (char)(-arrayOfChar[42] + 178), (char)(-arrayOfChar[43] + 296), (char)(arrayOfChar[44] ^ 0x93), (char)('ᙂ' / arrayOfChar[45]), (char)(arrayOfChar[46] ^ 0x90) });
  }
  
  public static String p()
  {
    char[] arrayOfChar = new char[68];
    int i = (char)'Å';
    arrayOfChar[0] = i;
    arrayOfChar[1] = ((char)'Ë');
    arrayOfChar[2] = ((char)'û');
    arrayOfChar[3] = ((char)'Ý');
    int i1 = (char)'';
    arrayOfChar[4] = i1;
    arrayOfChar[5] = ((char)'');
    int j = (char)'ï';
    arrayOfChar[6] = j;
    arrayOfChar[7] = ((char)'Ø');
    int i4 = (char)'ú';
    arrayOfChar[8] = i4;
    int n = (char)'Í';
    arrayOfChar[9] = n;
    int k = (char)'É';
    arrayOfChar[10] = k;
    arrayOfChar[11] = ((char)'í');
    arrayOfChar[12] = ((char)'£');
    arrayOfChar[13] = ((char)'µ');
    int i2 = (char)'ª';
    arrayOfChar[14] = i2;
    arrayOfChar[15] = ((char)'Á');
    arrayOfChar[16] = ((char)'â');
    int m = (char)'ó';
    arrayOfChar[17] = m;
    arrayOfChar[18] = n;
    arrayOfChar[19] = ((char)'');
    arrayOfChar[20] = ((char)'ð');
    arrayOfChar[21] = ((char)'³');
    arrayOfChar[22] = ((char)'À');
    int i6 = (char)'Û';
    arrayOfChar[23] = i6;
    int i3 = (char)'æ';
    arrayOfChar[24] = i3;
    arrayOfChar[25] = ((char)'¯');
    n = (char)'ù';
    arrayOfChar[26] = n;
    arrayOfChar[27] = ((char)'');
    arrayOfChar[28] = i4;
    arrayOfChar[29] = k;
    i4 = (char)'Þ';
    arrayOfChar[30] = i4;
    int i5 = (char)'Ñ';
    arrayOfChar[31] = i5;
    arrayOfChar[32] = ((char)'');
    arrayOfChar[33] = i6;
    arrayOfChar[34] = ((char)'');
    arrayOfChar[35] = ((char)'¼');
    i6 = (char)'';
    arrayOfChar[36] = i6;
    arrayOfChar[37] = k;
    arrayOfChar[38] = ((char)'Ð');
    int i7 = (char)'´';
    arrayOfChar[39] = i7;
    arrayOfChar[40] = i1;
    arrayOfChar[41] = m;
    arrayOfChar[42] = i2;
    arrayOfChar[43] = ((char)'¨');
    arrayOfChar[44] = i7;
    arrayOfChar[45] = i3;
    arrayOfChar[46] = ((char)'Ó');
    arrayOfChar[47] = ((char)'');
    i1 = (char)'¬';
    arrayOfChar[48] = i1;
    arrayOfChar[49] = ((char)'ü');
    arrayOfChar[50] = i6;
    arrayOfChar[51] = i5;
    arrayOfChar[52] = ((char)127);
    arrayOfChar[53] = j;
    arrayOfChar[54] = k;
    arrayOfChar[55] = ((char)'Ô');
    arrayOfChar[56] = ((char)'');
    arrayOfChar[57] = ((char)'');
    arrayOfChar[58] = i4;
    arrayOfChar[59] = ((char)'ý');
    arrayOfChar[60] = ((char)'¿');
    arrayOfChar[61] = i;
    arrayOfChar[62] = m;
    i = (char)'';
    arrayOfChar[63] = i;
    arrayOfChar[64] = n;
    arrayOfChar[65] = i1;
    arrayOfChar[66] = i;
    arrayOfChar[67] = ((char)'©');
    return String.valueOf(new char[] { (char)(-arrayOfChar[0] + 296), (char)(arrayOfChar[1] ^ 0xA4), (char)('毚' / arrayOfChar[2]), (char)('搤' / arrayOfChar[3]), (char)(-arrayOfChar[4] + 251), (char)(arrayOfChar[5] ^ 0xFA), (char)('汌' / arrayOfChar[6]), (char)('ヰ' / arrayOfChar[7]), (char)(-arrayOfChar[8] + 297), (char)(arrayOfChar[9] ^ 0xE2), (char)('䶻' / arrayOfChar[10]), (char)(-arrayOfChar[11] + 348), (char)(arrayOfChar[12] ^ 0xCE), (char)(arrayOfChar[13] ^ 0x9B), (char)(arrayOfChar[14] ^ 0xDB), (char)(-arrayOfChar[15] + 298), (char)(-arrayOfChar[16] + 330), (char)(-arrayOfChar[17] + 354), (char)(arrayOfChar[18] ^ 0xA2), (char)(-arrayOfChar[19] + 180), (char)(-arrayOfChar[20] + 294), (char)(arrayOfChar[21] ^ 0x83), (char)(arrayOfChar[22] ^ 0xEE), (char)(arrayOfChar[23] ^ 0xB3), (char)('掺' / arrayOfChar[24]), (char)(arrayOfChar[25] ^ 0xC2), (char)('戽' / arrayOfChar[26]), (char)(-arrayOfChar[27] + 174), (char)('楸' / arrayOfChar[28]), (char)('䰩' / arrayOfChar[29]), (char)(arrayOfChar[30] ^ 0xAB), (char)('姎' / arrayOfChar[31]), (char)('㱔' / arrayOfChar[32]), (char)('壸' / arrayOfChar[33]), (char)('㧿' / arrayOfChar[34]), (char)(arrayOfChar[35] ^ 0xCE), (char)(-arrayOfChar[36] + 184), (char)(-arrayOfChar[37] + 247), (char)(-arrayOfChar[38] + 323), (char)(arrayOfChar[39] ^ 0xD1), (char)('䏸' / arrayOfChar[40]), (char)('渜' / arrayOfChar[41]), (char)(-arrayOfChar[42] + 275), (char)(arrayOfChar[43] ^ 0xC6), (char)(-arrayOfChar[44] + 283), (char)('杒' / arrayOfChar[45]), (char)(arrayOfChar[46] ^ 0xFC), (char)(arrayOfChar[47] ^ 0xF4), (char)(arrayOfChar[48] ^ 0xCD), (char)(arrayOfChar[49] ^ 0x8A), (char)(arrayOfChar[50] ^ 0xE9), (char)(arrayOfChar[51] ^ 0xA3), (char)(-arrayOfChar[52] + 232), (char)('汌' / arrayOfChar[53]), (char)('位' / arrayOfChar[54]), (char)(arrayOfChar[55] ^ 0xA7), (char)(arrayOfChar[56] ^ 0xB6), (char)('㩰' / arrayOfChar[57]), (char)(-arrayOfChar[58] + 333), (char)(arrayOfChar[59] ^ 0x89), (char)('乗' / arrayOfChar[60]), (char)(arrayOfChar[61] ^ 0xA3), (char)(-arrayOfChar[62] + 364), (char)('Ỻ' / arrayOfChar[63]), (char)('烔' / arrayOfChar[64]), (char)('䲘' / arrayOfChar[65]), (char)('㭪' / arrayOfChar[66]), (char)('䊭' / arrayOfChar[67]) });
  }
  
  public static String q()
  {
    char[] arrayOfChar = new char[7];
    arrayOfChar[0] = ((char)'ï');
    arrayOfChar[1] = ((char)'');
    arrayOfChar[2] = ((char)'');
    arrayOfChar[3] = ((char)'õ');
    arrayOfChar[4] = ((char)'ß');
    arrayOfChar[5] = ((char)'');
    arrayOfChar[6] = ((char)'ê');
    return String.valueOf(new char[] { (char)('汌' / arrayOfChar[0]), (char)('㧕' / arrayOfChar[1]), (char)(-arrayOfChar[2] + 253), (char)('杜' / arrayOfChar[3]), (char)(arrayOfChar[4] ^ 0xBA), (char)('╩' / arrayOfChar[5]), (char)('㦖' / arrayOfChar[6]) });
  }
  
  public static String r()
  {
    char[] arrayOfChar = new char[48];
    arrayOfChar[0] = ((char)'½');
    arrayOfChar[1] = ((char)'ô');
    arrayOfChar[2] = ((char)'·');
    arrayOfChar[3] = ((char)'¥');
    arrayOfChar[4] = ((char)'è');
    int j = (char)'';
    arrayOfChar[5] = j;
    int k = (char)'ù';
    arrayOfChar[6] = k;
    arrayOfChar[7] = ((char)'ö');
    arrayOfChar[8] = ((char)'È');
    arrayOfChar[9] = ((char)'');
    arrayOfChar[10] = ((char)'©');
    arrayOfChar[11] = ((char)'');
    arrayOfChar[12] = ((char)'¼');
    int i = (char)'Ì';
    arrayOfChar[13] = i;
    arrayOfChar[14] = ((char)'­');
    arrayOfChar[15] = ((char)'ß');
    arrayOfChar[16] = ((char)'ä');
    arrayOfChar[17] = ((char)'þ');
    arrayOfChar[18] = ((char)'æ');
    arrayOfChar[19] = ((char)'');
    arrayOfChar[20] = ((char)'Þ');
    arrayOfChar[21] = j;
    arrayOfChar[22] = ((char)'é');
    arrayOfChar[23] = k;
    arrayOfChar[24] = ((char)'Ú');
    arrayOfChar[25] = ((char)'');
    arrayOfChar[26] = ((char)'Ï');
    arrayOfChar[27] = ((char)'Ò');
    arrayOfChar[28] = ((char)'£');
    arrayOfChar[29] = ((char)'');
    arrayOfChar[30] = ((char)'¸');
    arrayOfChar[31] = ((char)'Ô');
    arrayOfChar[32] = ((char)'ý');
    arrayOfChar[33] = ((char)'Ü');
    arrayOfChar[34] = ((char)'÷');
    j = (char)'ì';
    arrayOfChar[35] = j;
    arrayOfChar[36] = ((char)'ü');
    arrayOfChar[37] = ((char)127);
    arrayOfChar[38] = ((char)'¾');
    arrayOfChar[39] = ((char)'');
    arrayOfChar[40] = ((char)'');
    arrayOfChar[41] = j;
    arrayOfChar[42] = ((char)'Ä');
    arrayOfChar[43] = i;
    arrayOfChar[44] = ((char)'§');
    arrayOfChar[45] = ((char)'¹');
    arrayOfChar[46] = ((char)'Ã');
    arrayOfChar[47] = ((char)'µ');
    return String.valueOf(new char[] { (char)(arrayOfChar[0] ^ 0xDE), (char)(arrayOfChar[1] ^ 0x9B), (char)(-arrayOfChar[2] + 292), (char)(-arrayOfChar[3] + 211), (char)(arrayOfChar[4] ^ 0x99), (char)(arrayOfChar[5] ^ 0xFB), (char)(-arrayOfChar[6] + 353), (char)('檪' / arrayOfChar[7]), (char)('嚸' / arrayOfChar[8]), (char)(-arrayOfChar[9] + 183), (char)(-arrayOfChar[10] + 223), (char)('᪠' / arrayOfChar[11]), (char)(-arrayOfChar[12] + 234), (char)('勠' / arrayOfChar[13]), (char)('䬃' / arrayOfChar[14]), (char)('廳' / arrayOfChar[15]), (char)(-arrayOfChar[16] + 329), (char)(-arrayOfChar[17] + 300), (char)(-arrayOfChar[18] + 338), (char)(arrayOfChar[19] ^ 0xE1), (char)('敶' / arrayOfChar[20]), (char)(arrayOfChar[21] ^ 0xFC), (char)(-arrayOfChar[22] + 332), (char)(-arrayOfChar[23] + 353), (char)(-arrayOfChar[24] + 319), (char)(-arrayOfChar[25] + 270), (char)('⡮' / arrayOfChar[26]), (char)(-arrayOfChar[27] + 256), (char)(arrayOfChar[28] ^ 0xD0), (char)('㘍' / arrayOfChar[29]), (char)(arrayOfChar[30] ^ 0xCC), (char)(-arrayOfChar[31] + 328), (char)('柅' / arrayOfChar[32]), (char)('庈' / arrayOfChar[33]), (char)(arrayOfChar[34] ^ 0x90), (char)(-arrayOfChar[35] + 351), (char)(-arrayOfChar[36] + 310), (char)(arrayOfChar[37] ^ 0x5F), (char)(-arrayOfChar[38] + 289), (char)(-arrayOfChar[39] + 249), (char)(arrayOfChar[40] ^ 0xEA), (char)(-arrayOfChar[41] + 346), (char)('壐' / arrayOfChar[42]), (char)('ᦀ' / arrayOfChar[43]), (char)(arrayOfChar[44] ^ 0x9A), (char)('ᜠ' / arrayOfChar[45]), (char)('ᰯ' / arrayOfChar[46]), (char)(-arrayOfChar[47] + 281) });
  }
  
  public static String s()
  {
    char[] arrayOfChar = new char[33];
    int i = (char)'ó';
    arrayOfChar[0] = i;
    arrayOfChar[1] = ((char)'­');
    arrayOfChar[2] = ((char)'õ');
    arrayOfChar[3] = ((char)'Ý');
    arrayOfChar[4] = ((char)'§');
    arrayOfChar[5] = ((char)'à');
    arrayOfChar[6] = ((char)'ú');
    arrayOfChar[7] = ((char)'Ø');
    arrayOfChar[8] = ((char)'');
    int j = (char)'Í';
    arrayOfChar[9] = j;
    arrayOfChar[10] = ((char)'');
    arrayOfChar[11] = ((char)'ù');
    arrayOfChar[12] = ((char)'');
    arrayOfChar[13] = ((char)'ä');
    arrayOfChar[14] = ((char)'');
    arrayOfChar[15] = ((char)'¯');
    arrayOfChar[16] = ((char)'Ñ');
    arrayOfChar[17] = ((char)'ÿ');
    arrayOfChar[18] = ((char)'É');
    arrayOfChar[19] = ((char)'Ò');
    int k = (char)'å';
    arrayOfChar[20] = k;
    arrayOfChar[21] = k;
    arrayOfChar[22] = ((char)'é');
    arrayOfChar[23] = ((char)'¹');
    arrayOfChar[24] = ((char)'');
    arrayOfChar[25] = j;
    arrayOfChar[26] = ((char)' ');
    arrayOfChar[27] = ((char)'½');
    arrayOfChar[28] = ((char)'ö');
    arrayOfChar[29] = ((char)'±');
    arrayOfChar[30] = ((char)'');
    arrayOfChar[31] = ((char)'');
    arrayOfChar[32] = i;
    return String.valueOf(new char[] { (char)(arrayOfChar[0] ^ 0x9F), (char)(-arrayOfChar[1] + 270), (char)(-arrayOfChar[2] + 362), (char)(-arrayOfChar[3] + 331), (char)(arrayOfChar[4] ^ 0xC4), (char)(-arrayOfChar[5] + 328), (char)(arrayOfChar[6] ^ 0x9F), (char)('怰' / arrayOfChar[7]), (char)(-arrayOfChar[8] + 188), (char)(arrayOfChar[9] ^ 0xBD), (char)('㕃' / arrayOfChar[10]), (char)(arrayOfChar[11] ^ 0x8B), (char)('䉬' / arrayOfChar[12]), (char)(arrayOfChar[13] ^ 0x8D), (char)('䈉' / arrayOfChar[14]), (char)(-arrayOfChar[15] + 290), (char)('喹' / arrayOfChar[16]), (char)(-arrayOfChar[17] + 366), (char)('噞' / arrayOfChar[18]), (char)('▼' / arrayOfChar[19]), (char)(arrayOfChar[20] ^ 0xB7), (char)(-arrayOfChar[21] + 298), (char)(-arrayOfChar[22] + 298), (char)('ㄤ' / arrayOfChar[23]), (char)(-arrayOfChar[24] + 247), (char)(arrayOfChar[25] ^ 0x9E), (char)(arrayOfChar[26] ^ 0xE5), (char)(arrayOfChar[27] ^ 0xE9), (char)(-arrayOfChar[28] + 330), (char)(arrayOfChar[29] ^ 0xF8), (char)(arrayOfChar[30] ^ 0xD9), (char)('⯒' / arrayOfChar[31]), (char)(-arrayOfChar[32] + 326) });
  }
  
  public static String t()
  {
    char[] arrayOfChar = new char[23];
    arrayOfChar[0] = ((char)'');
    int i = (char)'';
    arrayOfChar[1] = i;
    arrayOfChar[2] = ((char)'');
    arrayOfChar[3] = ((char)'Ô');
    arrayOfChar[4] = ((char)'ô');
    arrayOfChar[5] = ((char)'Ó');
    int j = (char)'É';
    arrayOfChar[6] = j;
    int k = (char)'ó';
    arrayOfChar[7] = k;
    arrayOfChar[8] = ((char)'Í');
    arrayOfChar[9] = ((char)'´');
    arrayOfChar[10] = ((char)'å');
    int m = (char)'';
    arrayOfChar[11] = m;
    arrayOfChar[12] = j;
    arrayOfChar[13] = ((char)'ß');
    arrayOfChar[14] = ((char)'Ø');
    arrayOfChar[15] = ((char)'«');
    arrayOfChar[16] = i;
    arrayOfChar[17] = ((char)'Ï');
    arrayOfChar[18] = ((char)'');
    arrayOfChar[19] = m;
    arrayOfChar[20] = k;
    arrayOfChar[21] = ((char)'§');
    arrayOfChar[22] = ((char)'Ç');
    return String.valueOf(new char[] { (char)(-arrayOfChar[0] + 231), (char)('ㅂ' / arrayOfChar[1]), (char)(arrayOfChar[2] ^ 0xEF), (char)(-arrayOfChar[3] + 320), (char)('恄' / arrayOfChar[4]), (char)('剬' / arrayOfChar[5]), (char)(-arrayOfChar[6] + 233), (char)(-arrayOfChar[7] + 359), (char)('壣' / arrayOfChar[8]), (char)(arrayOfChar[9] ^ 0x94), (char)(-arrayOfChar[10] + 332), (char)(arrayOfChar[11] ^ 0xF0), (char)(-arrayOfChar[12] + 317), (char)('ᯠ' / arrayOfChar[13]), (char)('凘' / arrayOfChar[14]), (char)(arrayOfChar[15] ^ 0xDE), (char)(arrayOfChar[16] ^ 0xF6), (char)(-arrayOfChar[17] + 311), (char)(arrayOfChar[18] ^ 0xE3), (char)('䉚' / arrayOfChar[19]), (char)(arrayOfChar[20] ^ 0x9A), (char)('䮬' / arrayOfChar[21]), (char)(arrayOfChar[22] ^ 0xBE) });
  }
  
  public static String u()
  {
    char[] arrayOfChar = new char[10];
    arrayOfChar[0] = ((char)'ì');
    arrayOfChar[1] = ((char)'ç');
    arrayOfChar[2] = ((char)'¢');
    arrayOfChar[3] = ((char)'ó');
    arrayOfChar[4] = ((char)'§');
    arrayOfChar[5] = ((char)'ò');
    arrayOfChar[6] = ((char)'®');
    arrayOfChar[7] = ((char)'£');
    arrayOfChar[8] = ((char)'à');
    arrayOfChar[9] = ((char)'Î');
    return String.valueOf(new char[] { (char)('孄' / arrayOfChar[0]), (char)(arrayOfChar[1] ^ 0x88), (char)('䖜' / arrayOfChar[2]), (char)(arrayOfChar[3] ^ 0x87), (char)(-arrayOfChar[4] + 268), (char)(arrayOfChar[5] ^ 0x9C), (char)(-arrayOfChar[6] + 290), (char)('⓮' / arrayOfChar[7]), (char)(-arrayOfChar[8] + 271), (char)('◒' / arrayOfChar[9]) });
  }
  
  public static String v()
  {
    char[] arrayOfChar = new char[22];
    arrayOfChar[0] = ((char)'£');
    arrayOfChar[1] = ((char)'');
    arrayOfChar[2] = ((char)'Û');
    arrayOfChar[3] = ((char)'Ü');
    arrayOfChar[4] = ((char)'');
    arrayOfChar[5] = ((char)'û');
    arrayOfChar[6] = ((char)'ð');
    arrayOfChar[7] = ((char)'á');
    arrayOfChar[8] = ((char)'');
    arrayOfChar[9] = ((char)'¹');
    arrayOfChar[10] = ((char)'Â');
    arrayOfChar[11] = ((char)'¦');
    arrayOfChar[12] = ((char)'í');
    arrayOfChar[13] = ((char)'ï');
    int i = (char)'Ó';
    arrayOfChar[14] = i;
    arrayOfChar[15] = ((char)'ë');
    arrayOfChar[16] = ((char)'ô');
    arrayOfChar[17] = ((char)'ò');
    arrayOfChar[18] = i;
    arrayOfChar[19] = ((char)'è');
    arrayOfChar[20] = ((char)'é');
    arrayOfChar[21] = ((char)'«');
    return String.valueOf(new char[] { (char)('ᷭ' / arrayOfChar[0]), (char)(-arrayOfChar[1] + 236), (char)('勻' / arrayOfChar[2]), (char)(arrayOfChar[3] ^ 0xAA), (char)(-arrayOfChar[4] + 246), (char)('濆' / arrayOfChar[5]), (char)(arrayOfChar[6] ^ 0x99), (char)(arrayOfChar[7] ^ 0x95), (char)(arrayOfChar[8] ^ 0xFA), (char)(arrayOfChar[9] ^ 0xCA), (char)(arrayOfChar[10] ^ 0xFD), (char)(-arrayOfChar[11] + 276), (char)('曃' / arrayOfChar[12]), (char)(arrayOfChar[13] ^ 0x9B), (char)('嚋' / arrayOfChar[14]), (char)(arrayOfChar[15] ^ 0x8D), (char)(-arrayOfChar[16] + 365), (char)(arrayOfChar[17] ^ 0xCF), (char)('徜' / arrayOfChar[18]), (char)(arrayOfChar[19] ^ 0x9A), (char)(arrayOfChar[20] ^ 0x9C), (char)(arrayOfChar[21] ^ 0xCE) });
  }
  
  public static String w()
  {
    char[] arrayOfChar = new char[7];
    arrayOfChar[0] = ((char)'¨');
    arrayOfChar[1] = ((char)'Ç');
    arrayOfChar[2] = ((char)'');
    arrayOfChar[3] = ((char)'ñ');
    arrayOfChar[4] = ((char)'°');
    arrayOfChar[5] = ((char)'å');
    arrayOfChar[6] = ((char)'ò');
    return String.valueOf(new char[] { (char)(arrayOfChar[0] ^ 0xDC), (char)(-arrayOfChar[1] + 304), (char)(-arrayOfChar[2] + 252), (char)('斬' / arrayOfChar[3]), (char)(arrayOfChar[4] ^ 0xD5), (char)('㚑' / arrayOfChar[5]), (char)('㮎' / arrayOfChar[6]) });
  }
  
  public static String x()
  {
    char[] arrayOfChar = new char[25];
    int i = (char)'';
    arrayOfChar[0] = i;
    arrayOfChar[1] = ((char)'');
    arrayOfChar[2] = ((char)'·');
    arrayOfChar[3] = ((char)'Ï');
    int j = (char)'Ä';
    arrayOfChar[4] = j;
    arrayOfChar[5] = ((char)'Ù');
    arrayOfChar[6] = ((char)'Ö');
    arrayOfChar[7] = ((char)'×');
    arrayOfChar[8] = ((char)'¬');
    arrayOfChar[9] = ((char)'ü');
    int k = (char)'';
    arrayOfChar[10] = k;
    arrayOfChar[11] = ((char)'Ë');
    arrayOfChar[12] = ((char)'º');
    arrayOfChar[13] = ((char)'');
    arrayOfChar[14] = j;
    arrayOfChar[15] = ((char)'î');
    arrayOfChar[16] = ((char)'');
    arrayOfChar[17] = ((char)'²');
    arrayOfChar[18] = i;
    arrayOfChar[19] = ((char)'í');
    arrayOfChar[20] = ((char)'ú');
    arrayOfChar[21] = ((char)'ã');
    arrayOfChar[22] = ((char)'');
    arrayOfChar[23] = ((char)'ý');
    arrayOfChar[24] = k;
    return String.valueOf(new char[] { (char)(arrayOfChar[0] ^ 0xEE), (char)('㶳' / arrayOfChar[1]), (char)(arrayOfChar[2] ^ 0xC3), (char)(-arrayOfChar[3] + 311), (char)('哼' / arrayOfChar[4]), (char)(-arrayOfChar[5] + 331), (char)(-arrayOfChar[6] + 319), (char)(arrayOfChar[7] ^ 0xA3), (char)('兌' / arrayOfChar[8]), (char)('❠' / arrayOfChar[9]), (char)(arrayOfChar[10] ^ 0xAF), (char)(arrayOfChar[11] ^ 0xB8), (char)(-arrayOfChar[12] + 227), (char)(-arrayOfChar[13] + 213), (char)('ᢀ' / arrayOfChar[14]), (char)(-arrayOfChar[15] + 337), (char)(-arrayOfChar[16] + 250), (char)(arrayOfChar[17] ^ 0xC7), (char)('㵲' / arrayOfChar[18]), (char)('此' / arrayOfChar[19]), (char)('ὀ' / arrayOfChar[20]), (char)('㘗' / arrayOfChar[21]), (char)(arrayOfChar[22] ^ 0xBC), (char)('⒑' / arrayOfChar[23]), (char)(arrayOfChar[24] ^ 0xEE) });
  }
  
  public static String y()
  {
    char[] arrayOfChar = new char[25];
    arrayOfChar[0] = ((char)'');
    arrayOfChar[1] = ((char)'Å');
    arrayOfChar[2] = ((char)'á');
    arrayOfChar[3] = ((char)'');
    arrayOfChar[4] = ((char)'Õ');
    arrayOfChar[5] = ((char)'');
    arrayOfChar[6] = ((char)'');
    arrayOfChar[7] = ((char)'Ó');
    arrayOfChar[8] = ((char)'þ');
    arrayOfChar[9] = ((char)'');
    arrayOfChar[10] = ((char)'');
    arrayOfChar[11] = ((char)'Ë');
    arrayOfChar[12] = ((char)'');
    arrayOfChar[13] = ((char)'Ù');
    arrayOfChar[14] = ((char)'ÿ');
    int i = (char)'¾';
    arrayOfChar[15] = i;
    arrayOfChar[16] = ((char)'¥');
    arrayOfChar[17] = i;
    arrayOfChar[18] = ((char)'');
    arrayOfChar[19] = ((char)127);
    arrayOfChar[20] = ((char)'Ç');
    i = (char)'¹';
    arrayOfChar[21] = i;
    int j = (char)'Ø';
    arrayOfChar[22] = j;
    arrayOfChar[23] = i;
    arrayOfChar[24] = j;
    return String.valueOf(new char[] { (char)(-arrayOfChar[0] + 260), (char)(-arrayOfChar[1] + 294), (char)(-arrayOfChar[2] + 340), (char)('⺰' / arrayOfChar[3]), (char)(arrayOfChar[4] ^ 0xBD), (char)(-arrayOfChar[5] + 240), (char)(arrayOfChar[6] ^ 0xEB), (char)(arrayOfChar[7] ^ 0xA7), (char)(-arrayOfChar[8] + 353), (char)('㪀' / arrayOfChar[9]), (char)(-arrayOfChar[10] + 261), (char)('ᥠ' / arrayOfChar[11]), (char)(-arrayOfChar[12] + 236), (char)(arrayOfChar[13] ^ 0xA1), (char)('抝' / arrayOfChar[14]), (char)(-arrayOfChar[15] + 291), (char)('䠰' / arrayOfChar[16]), (char)('嘘' / arrayOfChar[17]), (char)(-arrayOfChar[18] + 252), (char)(-arrayOfChar[19] + 238), (char)(-arrayOfChar[20] + 309), (char)(-arrayOfChar[21] + 243), (char)(-arrayOfChar[22] + 248), (char)(arrayOfChar[23] ^ 0x9C), (char)('愈' / arrayOfChar[24]) });
  }
  
  public static String z()
  {
    char[] arrayOfChar = new char[26];
    arrayOfChar[0] = ((char)'Ã');
    int i = (char)'×';
    arrayOfChar[1] = i;
    arrayOfChar[2] = ((char)'ò');
    arrayOfChar[3] = ((char)'Þ');
    arrayOfChar[4] = i;
    arrayOfChar[5] = ((char)'Î');
    i = (char)'Ç';
    arrayOfChar[6] = i;
    arrayOfChar[7] = ((char)'ã');
    arrayOfChar[8] = ((char)'Â');
    arrayOfChar[9] = ((char)'Ù');
    arrayOfChar[10] = ((char)'');
    arrayOfChar[11] = ((char)'¬');
    arrayOfChar[12] = ((char)'');
    int j = (char)'¤';
    arrayOfChar[13] = j;
    arrayOfChar[14] = ((char)'Ì');
    arrayOfChar[15] = ((char)'ß');
    arrayOfChar[16] = ((char)'§');
    arrayOfChar[17] = ((char)'');
    arrayOfChar[18] = j;
    arrayOfChar[19] = ((char)'');
    arrayOfChar[20] = ((char)'');
    arrayOfChar[21] = i;
    arrayOfChar[22] = ((char)'');
    arrayOfChar[23] = ((char)'Ó');
    arrayOfChar[24] = ((char)'÷');
    arrayOfChar[25] = ((char)'');
    return String.valueOf(new char[] { (char)('䧣' / arrayOfChar[0]), (char)('屢' / arrayOfChar[1]), (char)('庈' / arrayOfChar[2]), (char)('拜' / arrayOfChar[3]), (char)(arrayOfChar[4] ^ 0xB8), (char)('呾' / arrayOfChar[5]), (char)('䶼' / arrayOfChar[6]), (char)(-arrayOfChar[7] + 273), (char)('侒' / arrayOfChar[8]), (char)('崾' / arrayOfChar[9]), (char)(arrayOfChar[10] ^ 0xEA), (char)(-arrayOfChar[11] + 273), (char)(-arrayOfChar[12] + 239), (char)(-arrayOfChar[13] + 280), (char)(-arrayOfChar[14] + 250), (char)(arrayOfChar[15] ^ 0xBE), (char)(arrayOfChar[16] ^ 0xC4), (char)(-arrayOfChar[17] + 258), (char)('䍄' / arrayOfChar[18]), (char)('㫸' / arrayOfChar[19]), (char)(arrayOfChar[20] ^ 0xF6), (char)('⏂' / arrayOfChar[21]), (char)('⠁' / arrayOfChar[22]), (char)('㖓' / arrayOfChar[23]), (char)(arrayOfChar[24] ^ 0xBE), (char)(-arrayOfChar[25] + 225) });
  }
}
